Workbook

Sheet Comparison
A1: Portfolio Comparison — 5 Names Ranked by Margin of Safety
A2: Each model uses Buffett-style conservative assumptions (15-yr horizon, ~9% discount, mid-single-digit growth)
A4: RANK | B4: Ticker | C4: Currency | D4: Current Price | E4: Intrinsic Value | F4: Upside % | G4: Verdict | H4: Key Risk
A5: 1 | B5: UNH | C5: USD | D5: ='Portfolio DCF'!C85 | E5: ='Portfolio DCF'!C84 | F5: ='Portfolio DCF'!C86 | G5: BUY | H5: Medicare Advantage margin pressure, regulatory scrutiny
A6: 2 | B6: LEN | C6: USD | D6: ='Portfolio DCF'!E85 | E6: ='Portfolio DCF'!E84 | F6: ='Portfolio DCF'!E86 | G6: BUY | H6: Housing cycle bottom — FY25 FCF collapsed; recovery dependent on rates
A7: 3 | B7: 1810.HK | C7: HKD | D7: ='Portfolio DCF'!D85 | E7: ='Portfolio DCF'!D84 | F7: ='Portfolio DCF'!D86 | G7: FAIR | H7: China geopolitical risk, EV competition, no buybacks
A8: 4 | B8: TTE | C8: USD | D8: ='Portfolio DCF'!G85 | E8: ='Portfolio DCF'!G84 | F8: ='Portfolio DCF'!G86 | G8: FAIR | H8: Oil price cyclicality; energy transition long-term
A9: 5 | B9: POOL | C9: USD | D9: ='Portfolio DCF'!F85 | E9: ='Portfolio DCF'!F84 | F9: ='Portfolio DCF'!F86 | G9: FAIR | H9: Pool industry slowdown; consumer discretionary
A10: 6 | B10: DPZ | C10: USD | D10: ='Portfolio DCF'!B85 | E10: ='Portfolio DCF'!B84 | F10: ='Portfolio DCF'!B86 | G10: HOLD | H10: Fair value at $372; needs better entry — Buffett bought at $437 = ~fair
A11: 7 | B11: NVDA | C11: USD | D11: ='Portfolio DCF'!H85 | E11: ='Portfolio DCF'!H84 | F11: ='Portfolio DCF'!H86 | G11: AVOID | H11: Priced for perfection at $5T market cap; 18% growth assumed but discount rate haircut
A12: KEY INSIGHTS BY NAME
A13: UNH (+76% upside) — BIGGEST OPPORTUNITY
A14: • Trading at $354 vs intrinsic $621. Stock crushed in 2025-26 from MA pressure + DOJ probes.
A15: • LTM FCF $17.4B is depressed; normalized FCF capacity ~$24B+ with margin recovery
A16: • Mgmt RAISED FY26 guide to $18.25 adj EPS in April. Q1'26 beat. Turnaround intact.
A17: • Buffett-style: defensive moat + secular tailwind + temp dislocation = Buffett setup
A18: • BIGGEST RISK: regulatory (Medicare risk-coding probes) — watch closely
A20: LEN (+52% upside) — CYCLICAL CONTRARIAN
A21: • Trading at $94 vs intrinsic $143. Stock down 35% on housing slowdown.
A22: • FY25 FCF collapsed to $28M (was $2.27B FY24) — we use cycle-avg $1.5B
A23: • Aggressive buybacks: $1.7B in FY25 = ~7% share count reduction
A24: • Buffett historically buys cyclicals at trough — housing under-supplied long-term
... A75: AVOID: NVDA at current price — watchlist for material pullback

Sheet Portfolio DCF
A1: Portfolio DCF — 5 Names + DPZ Reference (Buffett Framework)
A2: Per-share owner-earnings model. All inputs blue, formulas black, links green. Currency local to each name.
A4: Ticker | B4: DPZ | C4: UNH | D4: 1810.HK | E4: LEN | F4: POOL | G4: TTE | H4: NVDA
A5: Currency | B5: USD | C5: USD | D5: HKD | E5: USD | F5: USD | G5: USD | H5: USD
A7: MARKET DATA & INPUTS
A8: Current price (local ccy) | B8: 372 | C8: 354 | D8: 31.2 | E8: 94 | F8: 234 | G8: 89.79 | H8: 216.61
A9: Diluted shares (M) | B9: 33.6 | C9: 908.2 | D9: 25500 | E9: 247.6 | F9: 36.7 | G9: 2130 | H9: 24300
A10: Market cap (local M) | B10: =B8*B9 | C10: =C8*C9 | D10: =D8*D9 | E10: =E8*E9 | F10: =F8*F9 | G10: =G8*G9 | H10: =H8*H9
A11: Net debt (local M) | B11: 4784 | C11: 80000 | D11: -100000 | E11: 2100 | F11: 1175 | G11: 20200 | H11: -38000
A12: Enterprise value | B12: =B10+B11 | C12: =C10+C11 | D12: =D10+D11 | E12: =E10+E11 | F12: =F10+F11 | G12: =G10+G11 | H12: =H10+H11
A14: BUSINESS METRICS (LTM, local M) | D14: (Xiaomi: RMB→HKD ~×1.1)
A15: Revenue (LTM) | B15: 5008 | C15: 449710 | D15: 457290 | E15: 34200 | F15: 5300 | G15: 200000 | H15: 215900
A16: Free Cash Flow (LTM) | B16: 680 | C16: 17400 | D16: 32000 | E16: 28 | F16: 336 | G16: 11400 | H16: 72000
A17: Normalized FCF (cycle-avg) | B17: 600 | C17: 24000 | D17: 35000 | E17: 1500 | F17: 380 | G17: 13000 | H17: 95000
A18: FCF margin (normalized) | B18: =B17/B15 | C18: =C17/C15 | D18: =D17/D15 | E18: =E17/E15 | F18: =F17/F15 | G18: =G17/G15 | H18: =H17/H15
A20: BUFFETT-STYLE ASSUMPTIONS
A21: FCF growth Y1-5 (high-vis) | B21: 0.05 | C21: 0.06 | D21: 0.12 | E21: 0.05 | F21: 0.05 | G21: 0.03 | H21: 0.18
A22: FCF growth Y6-10 (fade) | B22: 0.04 | C22: 0.05 | D22: 0.08 | E22: 0.04 | F22: 0.05 | G22: 0.02 | H22: 0.08
A23: FCF growth Y11-15 (mature) | B23: 0.03 | C23: 0.04 | D23: 0.05 | E23: 0.03 | F23: 0.04 | G23: 0.01 | H23: 0.04
A24: Discount rate (Buffett hurdle) | B24: 0.09 | C24: 0.09 | D24: 0.11 | E24: 0.1 | F24: 0.09 | G24: 0.09 | H24: 0.1
A25: Terminal growth | B25: 0.025 | C25: 0.025 | D25: 0.03 | E25: 0.02 | F25: 0.025 | G25: 0 | H25: 0.03
A26: Annual buyback yield (assumed) | B26: 0.034 | C26: 0.02 | D26: 0 | E26: 0.04 | F26: 0.03 | G26: 0.035 | H26: 0.018
A29: VALUATION ENGINE (15-yr per-share DCF)
A30: Year #
A31: Y1 | B31: =B$17*(1+B$21) | C31: =C$17*(1+C$21) | D31: =D$17*(1+D$21) | E31: =E$17*(1+E$21) | F31: =F$17*(1+F$21) | G31: =G$17*(1+G$21) | H31: =H$17*(1+H$21)
A32: Y2 | B32: =B31*(1+B$21) | C32: =C31*(1+C$21) | D32: =D31*(1+D$21) | E32: =E31*(1+E$21) | F32: =F31*(1+F$21) | G32: =G31*(1+G$21) | H32: =H31*(1+H$21)
A33: Y3 | B33: =B32*(1+B$21) | C33: =C32*(1+C$21) | D33: =D32*(1+D$21) | E33: =E32*(1+E$21) | F33: =F32*(1+F$21) | G33: =G32*(1+G$21) | H33: =H32*(1+H$21)
A34: Y4 | B34: =B33*(1+B$21) | C34: =C33*(1+C$21) | D34: =D33*(1+D$21) | E34: =E33*(1+E$21) | F34: =F33*(1+F$21) | G34: =G33*(1+G$21) | H34: =H33*(1+H$21)
A35: Y5 | B35: =B34*(1+B$21) | C35: =C34*(1+C$21) | D35: =D34*(1+D$21) | E35: =E34*(1+E$21) | F35: =F34*(1+F$21) | G35: =G34*(1+G$21) | H35: =H34*(1+H$21)
A36: Y6 | B36: =B35*(1+B$22) | C36: =C35*(1+C$22) | D36: =D35*(1+D$22) | E36: =E35*(1+E$22) | F36: =F35*(1+F$22) | G36: =G35*(1+G$22) | H36: =H35*(1+H$22)
A37: Y7 | B37: =B36*(1+B$22) | C37: =C36*(1+C$22) | D37: =D36*(1+D$22) | E37: =E36*(1+E$22) | F37: =F36*(1+F$22) | G37: =G36*(1+G$22) | H37: =H36*(1+H$22)
A38: Y8 | B38: =B37*(1+B$22) | C38: =C37*(1+C$22) | D38: =D37*(1+D$22) | E38: =E37*(1+E$22) | F38: =F37*(1+F$22) | G38: =G37*(1+G$22) | H38: =H37*(1+H$22)
A39: Y9 | B39: =B38*(1+B$22) | C39: =C38*(1+C$22) | D39: =D38*(1+D$22) | E39: =E38*(1+E$22) | F39: =F38*(1+F$22) | G39: =G38*(1+G$22) | H39: =H38*(1+H$22)
A40: Y10 | B40: =B39*(1+B$22) | C40: =C39*(1+C$22) | D40: =D39*(1+D$22) | E40: =E39*(1+E$22) | F40: =F39*(1+F$22) | G40: =G39*(1+G$22) | H40: =H39*(1+H$22)
A41: Y11 | B41: =B40*(1+B$23) | C41: =C40*(1+C$23) | D41: =D40*(1+D$23) | E41: =E40*(1+E$23) | F41: =F40*(1+F$23) | G41: =G40*(1+G$23) | H41: =H40*(1+H$23)
A42: Y12 | B42: =B41*(1+B$23) | C42: =C41*(1+C$23) | D42: =D41*(1+D$23) | E42: =E41*(1+E$23) | F42: =F41*(1+F$23) | G42: =G41*(1+G$23) | H42: =H41*(1+H$23)
A43: Y13 | B43: =B42*(1+B$23) | C43: =C42*(1+C$23) | D43: =D42*(1+D$23) | E43: =E42*(1+E$23) | F43: =F42*(1+F$23) | G43: =G42*(1+G$23) | H43: =H42*(1+H$23)
A44: Y14 | B44: =B43*(1+B$23) | C44: =C43*(1+C$23) | D44: =D43*(1+D$23) | E44: =E43*(1+E$23) | F44: =F43*(1+F$23) | G44: =G43*(1+G$23) | H44: =H43*(1+H$23)
A45: Y15 | B45: =B44*(1+B$23) | C45: =C44*(1+C$23) | D45: =D44*(1+D$23) | E45: =E44*(1+E$23) | F45: =F44*(1+F$23) | G45: =G44*(1+G$23) | H45: =H44*(1+H$23)
A47: VALUATION SUMMARY
A48: Sum PV of FCFs (Y1-15) | B48: {=SUMPRODUCT(B31:B45 / (1+B$24)^(ROW(B31:B45)-30-0.5))} | C48: {=SUMPRODUCT(C31:C45 / (1+C$24)^(ROW(C31:C45)-30-0.5))} | D48: {=SUMPRODUCT(D31:D45 / (1+D$24)^(ROW(D31:D45)-30-0.5))} | E48: {=SUMPRODUCT(E31:E45 / (1+E$24)^(ROW(E31:E45)-30-0.5))} | F48: {=SUMPRODUCT(F31:F45 / (1+F$24)^(ROW(F31:F45)-30-0.5))} | G48: {=SUMPRODUCT(G31:G45 / (1+G$24)^(ROW(G31:G45)-30-0.5))} | H48: {=SUMPRODUCT(H31:H45 / (1+H$24)^(ROW(H31:H45)-30-0.5))}
A49: Terminal Value (at Y15) | B49: =B45*(1+B$25)/(B$24-B$25) | C49: =C45*(1+C$25)/(C$24-C$25) | D49: =D45*(1+D$25)/(D$24-D$25) | E49: =E45*(1+E$25)/(E$24-E$25) | F49: =F45*(1+F$25)/(F$24-F$25) | G49: =G45*(1+G$25)/(G$24-G$25) | H49: =H45*(1+H$25)/(H$24-H$25)
A50: PV of Terminal Value | B50: =B49/(1+B$24)^14.5 | C50: =C49/(1+C$24)^14.5 | D50: =D49/(1+D$24)^14.5 | E50: =E49/(1+E$24)^14.5 | F50: =F49/(1+F$24)^14.5 | G50: =G49/(1+G$24)^14.5 | H50: =H49/(1+H$24)^14.5
A51: Enterprise Value | B51: =B48+B50 | C51: =C48+C50 | D51: =D48+D50 | E51: =E48+E50 | F51: =F48+F50 | G51: =G48+G50 | H51: =H48+H50
A52: (−) Net debt | B52: =-B11 | C52: =-C11 | D52: =-D11 | E52: =-E11 | F52: =-F11 | G52: =-G11 | H52: =-H11
A53: Equity Value | B53: =B51+B52 | C53: =C51+C52 | D53: =D51+D52 | E53: =E51+E52 | F53: =F51+F52 | G53: =G51+G52 | H53: =H51+H52
A55: PER-SHARE VALUATION (with buybacks)
A56: FCF per share (LTM normalized) | B56: =B17/B9 | C56: =C17/C9 | D56: =D17*1.1/D9 | E56: =E17/E9 | F56: =F17/F9 | G56: =G17/G9 | H56: =H17/H9
A57: Per-share growth Y1-5 | B57: =(1+B21)/(1-B26)-1 | C57: =(1+C21)/(1-C26)-1 | D57: =(1+D21)/(1-D26)-1 | E57: =(1+E21)/(1-E26)-1 | F57: =(1+F21)/(1-F26)-1 | G57: =(1+G21)/(1-G26)-1 | H57: =(1+H21)/(1-H26)-1
A58: Per-share growth Y6-10 | B58: =(1+B22)/(1-B26)-1 | C58: =(1+C22)/(1-C26)-1 | D58: =(1+D22)/(1-D26)-1 | E58: =(1+E22)/(1-E26)-1 | F58: =(1+F22)/(1-F26)-1 | G58: =(1+G22)/(1-G26)-1 | H58: =(1+H22)/(1-H26)-1
A59: Per-share growth Y11-15 | B59: =(1+B23)/(1-B26)-1 | C59: =(1+C23)/(1-C26)-1 | D59: =(1+D23)/(1-D26)-1 | E59: =(1+E23)/(1-E26)-1 | F59: =(1+F23)/(1-F26)-1 | G59: =(1+G23)/(1-G26)-1 | H59: =(1+H23)/(1-H26)-1
A62: FCF/share Y1-15 projection
B63: =B56*(1+B57) | C63: =C56*(1+C57) | D63: =D56*(1+D57) | E63: =E56*(1+E57) | F63: =F56*(1+F57) | G63: =G56*(1+G57) | H63: =H56*(1+H57)
B64: =B63*(1+B57) | C64: =C63*(1+C57) | D64: =D63*(1+D57) | E64: =E63*(1+E57) | F64: =F63*(1+F57) | G64: =G63*(1+G57) | H64: =H63*(1+H57)
B65: =B64*(1+B57) | C65: =C64*(1+C57) | D65: =D64*(1+D57) | E65: =E64*(1+E57) | F65: =F64*(1+F57) | G65: =G64*(1+G57) | H65: =H64*(1+H57)
B66: =B65*(1+B57) | C66: =C65*(1+C57) | D66: =D65*(1+D57) | E66: =E65*(1+E57) | F66: =F65*(1+F57) | G66: =G65*(1+G57) | H66: =H65*(1+H57)
B67: =B66*(1+B57) | C67: =C66*(1+C57) | D67: =D66*(1+D57) | E67: =E66*(1+E57) | F67: =F66*(1+F57) | G67: =G66*(1+G57) | H67: =H66*(1+H57)
B68: =B67*(1+B58) | C68: =C67*(1+C58) | D68: =D67*(1+D58) | E68: =E67*(1+E58) | F68: =F67*(1+F58) | G68: =G67*(1+G58) | H68: =H67*(1+H58)
B69: =B68*(1+B58) | C69: =C68*(1+C58) | D69: =D68*(1+D58) | E69: =E68*(1+E58) | F69: =F68*(1+F58) | G69: =G68*(1+G58) | H69: =H68*(1+H58)
B70: =B69*(1+B58) | C70: =C69*(1+C58) | D70: =D69*(1+D58) | E70: =E69*(1+E58) | F70: =F69*(1+F58) | G70: =G69*(1+G58) | H70: =H69*(1+H58)
B71: =B70*(1+B58) | C71: =C70*(1+C58) | D71: =D70*(1+D58) | E71: =E70*(1+E58) | F71: =F70*(1+F58) | G71: =G70*(1+G58) | H71: =H70*(1+H58)
B72: =B71*(1+B58) | C72: =C71*(1+C58) | D72: =D71*(1+D58) | E72: =E71*(1+E58) | F72: =F71*(1+F58) | G72: =G71*(1+G58) | H72: =H71*(1+H58)
B73: =B72*(1+B59) | C73: =C72*(1+C59) | D73: =D72*(1+D59) | E73: =E72*(1+E59) | F73: =F72*(1+F59) | G73: =G72*(1+G59) | H73: =H72*(1+H59)
B74: =B73*(1+B59) | C74: =C73*(1+C59) | D74: =D73*(1+D59) | E74: =E73*(1+E59) | F74: =F73*(1+F59) | G74: =G73*(1+G59) | H74: =H73*(1+H59)
B75: =B74*(1+B59) | C75: =C74*(1+C59) | D75: =D74*(1+D59) | E75: =E74*(1+E59) | F75: =F74*(1+F59) | G75: =G74*(1+G59) | H75: =H74*(1+H59)
B76: =B75*(1+B59) | C76: =C75*(1+C59) | D76: =D75*(1+D59) | E76: =E75*(1+E59) | F76: =F75*(1+F59) | G76: =G75*(1+G59) | H76: =H75*(1+H59)
B77: =B76*(1+B59) | C77: =C76*(1+C59) | D77: =D76*(1+D59) | E77: =E76*(1+E59) | F77: =F76*(1+F59) | G77: =G76*(1+G59) | H77: =H76*(1+H59)
A79: Sum PV of FCF/share (Y1-15) | B79: {=SUMPRODUCT(B63:B77 / (1+B24)^(ROW(B63:B77)-62-0.5))} | C79: {=SUMPRODUCT(C63:C77 / (1+C24)^(ROW(C63:C77)-62-0.5))} | D79: {=SUMPRODUCT(D63:D77 / (1+D24)^(ROW(D63:D77)-62-0.5))} | E79: {=SUMPRODUCT(E63:E77 / (1+E24)^(ROW(E63:E77)-62-0.5))} | F79: {=SUMPRODUCT(F63:F77 / (1+F24)^(ROW(F63:F77)-62-0.5))} | G79: {=SUMPRODUCT(G63:G77 / (1+G24)^(ROW(G63:G77)-62-0.5))} | H79: {=SUMPRODUCT(H63:H77 / (1+H24)^(ROW(H63:H77)-62-0.5))}
A80: Per-share TV at Y15 | B80: =B77*(1+B25)/(B24-B25) | C80: =C77*(1+C25)/(C24-C25) | D80: =D77*(1+D25)/(D24-D25) | E80: =E77*(1+E25)/(E24-E25) | F80: =F77*(1+F25)/(F24-F25) | G80: =G77*(1+G25)/(G24-G25) | H80: =H77*(1+H25)/(H24-H25)
A81: PV of TV per-share | B81: =B80/(1+B24)^14.5 | C81: =C80/(1+C24)^14.5 | D81: =D80/(1+D24)^14.5 | E81: =E80/(1+E24)^14.5 | F81: =F80/(1+F24)^14.5 | G81: =G80/(1+G24)^14.5 | H81: =H80/(1+H24)^14.5
A82: (−) Net debt per share | B82: =-B11/B9 | C82: =-C11/C9 | D82: =-D11*1.1/D9 | E82: =-E11/E9 | F82: =-F11/F9 | G82: =-G11/G9 | H82: =-H11/H9
A84: INTRINSIC VALUE PER SHARE | B84: =B79+B81+B82 | C84: =C79+C81+C82 | D84: =D79+D81+D82 | E84: =E79+E81+E82 | F84: =F79+F81+F82 | G84: =G79+G81+G82 | H84: =H79+H81+H82
A85: Current price | B85: =B8 | C85: =C8 | D85: =D8 | E85: =E8 | F85: =F8 | G85: =G8 | H85: =H8
A86: Upside / (Downside) % | B86: =B84/B85-1 | C86: =C84/C85-1 | D86: =D84/D85-1 | E86: =E84/E85-1 | F86: =F84/F85-1 | G86: =G84/G85-1 | H86: =H84/H85-1
A87: Verdict | B87: =IF(B86>0.3,"BUY",IF(B86>0.1,"FAIR",IF(B86>-0.1,"HOLD","AVOID"))) | C87: =IF(C86>0.3,"BUY",IF(C86>0.1,"FAIR",IF(C86>-0.1,"HOLD","AVOID"))) | D87: =IF(D86>0.3,"BUY",IF(D86>0.1,"FAIR",IF(D86>-0.1,"HOLD","AVOID"))) | E87: =IF(E86>0.3,"BUY",IF(E86>0.1,"FAIR",IF(E86>-0.1,"HOLD","AVOID"))) | F87: =IF(F86>0.3,"BUY",IF(F86>0.1,"FAIR",IF(F86>-0.1,"HOLD","AVOID"))) | G87: =IF(G86>0.3,"BUY",IF(G86>0.1,"FAIR",IF(G86>-0.1,"HOLD","AVOID"))) | H87: =IF(H86>0.3,"BUY",IF(H86>0.1,"FAIR",IF(H86>-0.1,"HOLD","AVOID")))

Sheet SpaceX DCF
A1: SpaceX (SPCX) — DCF Valuation Model
A2: Pre-IPO 2026 | Consolidated: Starlink + Launch + xAI/SpaceXAI | FYE Dec
A4: Case Selector (1=Bear, 2=Base, 3=Bull) | B4: 2
A5: Selected Case | B5: =IF(B4=1,"Bear",IF(B4=2,"Base","Bull"))
A7: MARKET DATA & KEY INPUTS
A8: Diluted Shares Outstanding (B, post 5-for-1 split) | B8: 5
A9: Insider Sale Price Dec 2025 ($/sh, post-split) | B9: =421.06/5
A10: Net Debt ($B) | B10: ='SpaceX WACC'!B20
A11: WACC | B11: ='SpaceX WACC'!B26
A12: Tax Rate | B12: ='SpaceX WACC'!B13
A14: PROJECTION YEARS | C14: FY2025A | D14: FY2026E | E14: FY2027E | F14: FY2028E | G14: FY2029E | H14: FY2030E
A16: BEAR CASE ASSUMPTIONS
A17: Starlink Revenue Growth % | D17: 0.4 | E17: 0.25 | F17: 0.15 | G17: 0.08 | H17: 0.05
A18: Launch Revenue Growth % | D18: 0.05 | E18: 0.05 | F18: 0.04 | G18: 0.03 | H18: 0.03
A19: xAI/Other Revenue Growth % | D19: 0.3 | E19: 0.2 | F19: 0.1 | G19: 0.05 | H19: 0.05
A20: EBIT Margin % | D20: 0.05 | E20: 0.08 | F20: 0.1 | G20: 0.12 | H20: 0.13
A21: Terminal Growth Rate | D21: 0.025
A23: BASE CASE ASSUMPTIONS
A24: Starlink Revenue Growth % | D24: 0.25 | E24: 0.2 | F24: 0.15 | G24: 0.1 | H24: 0.08
A25: Launch Revenue Growth % | D25: 0.1 | E25: 0.1 | F25: 0.08 | G25: 0.06 | H25: 0.05
A26: xAI/Other Revenue Growth % | D26: 0.5 | E26: 0.35 | F26: 0.2 | G26: 0.12 | H26: 0.08
A27: EBIT Margin % | D27: 0.08 | E27: 0.13 | F27: 0.17 | G27: 0.2 | H27: 0.22
A28: Terminal Growth Rate | D28: 0.03
A30: BULL CASE ASSUMPTIONS
A31: Starlink Revenue Growth % | D31: 0.6 | E31: 0.45 | F31: 0.3 | G31: 0.2 | H31: 0.12
A32: Launch Revenue Growth % | D32: 0.15 | E32: 0.15 | F32: 0.12 | G32: 0.1 | H32: 0.08
A33: xAI/Other Revenue Growth % | D33: 0.8 | E33: 0.5 | F33: 0.3 | G33: 0.2 | H33: 0.12
A34: EBIT Margin % | D34: 0.1 | E34: 0.16 | F34: 0.22 | G34: 0.26 | H34: 0.28
A35: Terminal Growth Rate | D35: 0.035
A37: ACTIVE CASE (auto-pulled) | D37: ACTIVE CASE (auto-pulled)
A38: Starlink Growth | D38: =CHOOSE($B$4,D17,D24,D31) | E38: =CHOOSE($B$4,E17,E24,E31) | F38: =CHOOSE($B$4,F17,F24,F31) | G38: =CHOOSE($B$4,G17,G24,G31) | H38: =CHOOSE($B$4,H17,H24,H31)
A39: Launch Growth | D39: =CHOOSE($B$4,D18,D25,D32) | E39: =CHOOSE($B$4,E18,E25,E32) | F39: =CHOOSE($B$4,F18,F25,F32) | G39: =CHOOSE($B$4,G18,G25,G32) | H39: =CHOOSE($B$4,H18,H25,H32)
A40: xAI/Other Growth | D40: =CHOOSE($B$4,D19,D26,D33) | E40: =CHOOSE($B$4,E19,E26,E33) | F40: =CHOOSE($B$4,F19,F26,F33) | G40: =CHOOSE($B$4,G19,G26,G33) | H40: =CHOOSE($B$4,H19,H26,H33)
A41: EBIT Margin | D41: =CHOOSE($B$4,D20,D27,D34) | E41: =CHOOSE($B$4,E20,E27,E34) | F41: =CHOOSE($B$4,F20,F27,F34) | G41: =CHOOSE($B$4,G20,G27,G34) | H41: =CHOOSE($B$4,H20,H27,H34)
A42: Terminal Growth | D42: =CHOOSE($B$4,$D$21,$D$28,$D$35)
A43: D&A % of Revenue | D43: 0.12 | E43: =$D$43 | F43: =$D$43 | G43: =$D$43 | H43: =$D$43
A44: CapEx % of Revenue | D44: 0.18 | E44: =$D$44 | F44: =$D$44 | G44: =$D$44 | H44: =$D$44
A45: Δ NWC % of ΔRev | D45: 0.05 | E45: =$D$45 | F45: =$D$45 | G45: =$D$45 | H45: =$D$45
A47: REVENUE BUILD ($B)
A48: Starlink Revenue | C48: 11.4 | D48: =C48*(1+D38) | E48: =D48*(1+E38) | F48: =E48*(1+F38) | G48: =F48*(1+G38) | H48: =G48*(1+H38)
A49: Launch Revenue | C49: 4.1 | D49: =C49*(1+D39) | E49: =D49*(1+E39) | F49: =E49*(1+F39) | G49: =F49*(1+G39) | H49: =G49*(1+H39)
A50: xAI/Other Revenue | C50: 3.2 | D50: =C50*(1+D40) | E50: =D50*(1+E40) | F50: =E50*(1+F40) | G50: =F50*(1+G40) | H50: =G50*(1+H40)
A51: Total Revenue | C51: =SUM(C48:C50) | D51: =SUM(D48:D50) | E51: =SUM(E48:E50) | F51: =SUM(F48:F50) | G51: =SUM(G48:G50) | H51: =SUM(H48:H50)
A52: Growth % | D52: =D51/C51-1 | E52: =E51/D51-1 | F52: =F51/E51-1 | G52: =G51/F51-1 | H52: =H51/G51-1
A54: FREE CASH FLOW BUILD ($B) | D54: FREE CASH FLOW BUILD ($B)
A55: EBIT | D55: =D51*D41 | E55: =E51*E41 | F55: =F51*F41 | G55: =G51*G41 | H55: =H51*H41
A56: EBIT Margin | D56: =D55/D51 | E56: =E55/E51 | F56: =F55/F51 | G56: =G55/G51 | H56: =H55/H51
A57: Less: Taxes | D57: =-D55*$B$12 | E57: =-E55*$B$12 | F57: =-F55*$B$12 | G57: =-G55*$B$12 | H57: =-H55*$B$12
A58: NOPAT | D58: =D55+D57 | E58: =E55+E57 | F58: =F55+F57 | G58: =G55+G57 | H58: =H55+H57
A59: Plus: D&A | D59: =D51*D43 | E59: =E51*E43 | F59: =F51*F43 | G59: =G51*G43 | H59: =H51*H43
A60: Less: CapEx | D60: =-D51*D44 | E60: =-E51*E44 | F60: =-F51*F44 | G60: =-G51*G44 | H60: =-H51*H44
A61: Less: Δ NWC | D61: =-(D51-C51)*D45 | E61: =-(E51-D51)*E45 | F61: =-(F51-E51)*F45 | G61: =-(G51-F51)*G45 | H61: =-(H51-G51)*H45
A62: Unlevered FCF | D62: =D58+D59+D60+D61 | E62: =E58+E59+E60+E61 | F62: =F58+F59+F60+F61 | G62: =G58+G59+G60+G61 | H62: =H58+H59+H60+H61
A63: FCF Margin | D63: =D62/D51 | E63: =E62/E51 | F63: =F62/F51 | G63: =G62/G51 | H63: =H62/H51
A65: DISCOUNTING (Mid-Year Convention)
A66: Discount Period (years) | D66: 0.5 | E66: 1.5 | F66: 2.5 | G66: 3.5 | H66: 4.5
A67: Discount Factor | D67: =1/(1+$B$11)^D66 | E67: =1/(1+$B$11)^E66 | F67: =1/(1+$B$11)^F66 | G67: =1/(1+$B$11)^G66 | H67: =1/(1+$B$11)^H66
A68: PV of Unlevered FCF ($B) | D68: =D62*D67 | E68: =E62*E67 | F68: =F62*F67 | G68: =G62*G67 | H68: =H62*H67
A70: TERMINAL VALUE
A71: Terminal Growth Rate | B71: =D42
A72: Terminal FCF (FY2031, $B) | B72: =H62*(1+B71)
A73: Terminal Value ($B) | B73: =B72/($B$11-B71)
A74: PV of Terminal Value ($B) | B74: =B73*H67
A75: TV as % of EV | B75: =B74/B80
A77: VALUATION SUMMARY
A78: Sum of PV Explicit FCFs ($B) | B78: =SUM(D68:H68)
A79: (+) PV of Terminal Value ($B) | B79: =B74
A80: = Enterprise Value ($B) | B80: =B78+B79
A81: (-) Net Debt ($B) | B81: =B10
A82: = Equity Value ($B) | B82: =B80-B81
A83: Diluted Shares Outstanding (B) | B83: =B8
A84: Implied Price per Share ($) | B84: =B82/B83
A86: Insider Price (Dec 2025, post-split) | B86: =B9
A87: Broker IPO Price ($1.75T / shares) | B87: =1750/B8
A88: Upside/(Downside) vs Insider | B88: =B84/B86-1
A89: Upside/(Downside) vs Broker IPO | B89: =B84/B87-1
A91: SENSITIVITY: WACC vs Terminal Growth — Implied Share Price ($)
A93: WACC ↓ / Term g → | B93: 0.02 | C93: 0.025 | D93: 0.03 | E93: 0.035 | F93: 0.04
A94: 0.1044 | B94: =(($D$62/(1+$A94)^0.5+$E$62/(1+$A94)^1.5+$F$62/(1+$A94)^2.5+$G$62/(1+$A94)^3.5+$H$62/(1+$A94)^4.5)+($H$62*(1+B$93)/($A94-B$93))/(1+$A94)^4.5-$B$10)/$B$8 | C94: =(($D$62/(1+$A94)^0.5+$E$62/(1+$A94)^1.5+$F$62/(1+$A94)^2.5+$G$62/(1+$A94)^3.5+$H$62/(1+$A94)^4.5)+($H$62*(1+C$93)/($A94-C$93))/(1+$A94)^4.5-$B$10)/$B$8 | D94: =(($D$62/(1+$A94)^0.5+$E$62/(1+$A94)^1.5+$F$62/(1+$A94)^2.5+$G$62/(1+$A94)^3.5+$H$62/(1+$A94)^4.5)+($H$62*(1+D$93)/($A94-D$93))/(1+$A94)^4.5-$B$10)/$B$8 | E94: =(($D$62/(1+$A94)^0.5+$E$62/(1+$A94)^1.5+$F$62/(1+$A94)^2.5+$G$62/(1+$A94)^3.5+$H$62/(1+$A94)^4.5)+($H$62*(1+E$93)/($A94-E$93))/(1+$A94)^4.5-$B$10)/$B$8 | F94: =(($D$62/(1+$A94)^0.5+$E$62/(1+$A94)^1.5+$F$62/(1+$A94)^2.5+$G$62/(1+$A94)^3.5+$H$62/(1+$A94)^4.5)+($H$62*(1+F$93)/($A94-F$93))/(1+$A94)^4.5-$B$10)/$B$8
A95: 0.1144 | B95: =(($D$62/(1+$A95)^0.5+$E$62/(1+$A95)^1.5+$F$62/(1+$A95)^2.5+$G$62/(1+$A95)^3.5+$H$62/(1+$A95)^4.5)+($H$62*(1+B$93)/($A95-B$93))/(1+$A95)^4.5-$B$10)/$B$8 | C95: =(($D$62/(1+$A95)^0.5+$E$62/(1+$A95)^1.5+$F$62/(1+$A95)^2.5+$G$62/(1+$A95)^3.5+$H$62/(1+$A95)^4.5)+($H$62*(1+C$93)/($A95-C$93))/(1+$A95)^4.5-$B$10)/$B$8 | D95: =(($D$62/(1+$A95)^0.5+$E$62/(1+$A95)^1.5+$F$62/(1+$A95)^2.5+$G$62/(1+$A95)^3.5+$H$62/(1+$A95)^4.5)+($H$62*(1+D$93)/($A95-D$93))/(1+$A95)^4.5-$B$10)/$B$8 | E95: =(($D$62/(1+$A95)^0.5+$E$62/(1+$A95)^1.5+$F$62/(1+$A95)^2.5+$G$62/(1+$A95)^3.5+$H$62/(1+$A95)^4.5)+($H$62*(1+E$93)/($A95-E$93))/(1+$A95)^4.5-$B$10)/$B$8 | F95: =(($D$62/(1+$A95)^0.5+$E$62/(1+$A95)^1.5+$F$62/(1+$A95)^2.5+$G$62/(1+$A95)^3.5+$H$62/(1+$A95)^4.5)+($H$62*(1+F$93)/($A95-F$93))/(1+$A95)^4.5-$B$10)/$B$8
A96: 0.1244 | B96: =(($D$62/(1+$A96)^0.5+$E$62/(1+$A96)^1.5+$F$62/(1+$A96)^2.5+$G$62/(1+$A96)^3.5+$H$62/(1+$A96)^4.5)+($H$62*(1+B$93)/($A96-B$93))/(1+$A96)^4.5-$B$10)/$B$8 | C96: =(($D$62/(1+$A96)^0.5+$E$62/(1+$A96)^1.5+$F$62/(1+$A96)^2.5+$G$62/(1+$A96)^3.5+$H$62/(1+$A96)^4.5)+($H$62*(1+C$93)/($A96-C$93))/(1+$A96)^4.5-$B$10)/$B$8 | D96: =(($D$62/(1+$A96)^0.5+$E$62/(1+$A96)^1.5+$F$62/(1+$A96)^2.5+$G$62/(1+$A96)^3.5+$H$62/(1+$A96)^4.5)+($H$62*(1+D$93)/($A96-D$93))/(1+$A96)^4.5-$B$10)/$B$8 | E96: =(($D$62/(1+$A96)^0.5+$E$62/(1+$A96)^1.5+$F$62/(1+$A96)^2.5+$G$62/(1+$A96)^3.5+$H$62/(1+$A96)^4.5)+($H$62*(1+E$93)/($A96-E$93))/(1+$A96)^4.5-$B$10)/$B$8 | F96: =(($D$62/(1+$A96)^0.5+$E$62/(1+$A96)^1.5+$F$62/(1+$A96)^2.5+$G$62/(1+$A96)^3.5+$H$62/(1+$A96)^4.5)+($H$62*(1+F$93)/($A96-F$93))/(1+$A96)^4.5-$B$10)/$B$8
A97: 0.1344 | B97: =(($D$62/(1+$A97)^0.5+$E$62/(1+$A97)^1.5+$F$62/(1+$A97)^2.5+$G$62/(1+$A97)^3.5+$H$62/(1+$A97)^4.5)+($H$62*(1+B$93)/($A97-B$93))/(1+$A97)^4.5-$B$10)/$B$8 | C97: =(($D$62/(1+$A97)^0.5+$E$62/(1+$A97)^1.5+$F$62/(1+$A97)^2.5+$G$62/(1+$A97)^3.5+$H$62/(1+$A97)^4.5)+($H$62*(1+C$93)/($A97-C$93))/(1+$A97)^4.5-$B$10)/$B$8 | D97: =(($D$62/(1+$A97)^0.5+$E$62/(1+$A97)^1.5+$F$62/(1+$A97)^2.5+$G$62/(1+$A97)^3.5+$H$62/(1+$A97)^4.5)+($H$62*(1+D$93)/($A97-D$93))/(1+$A97)^4.5-$B$10)/$B$8 | E97: =(($D$62/(1+$A97)^0.5+$E$62/(1+$A97)^1.5+$F$62/(1+$A97)^2.5+$G$62/(1+$A97)^3.5+$H$62/(1+$A97)^4.5)+($H$62*(1+E$93)/($A97-E$93))/(1+$A97)^4.5-$B$10)/$B$8 | F97: =(($D$62/(1+$A97)^0.5+$E$62/(1+$A97)^1.5+$F$62/(1+$A97)^2.5+$G$62/(1+$A97)^3.5+$H$62/(1+$A97)^4.5)+($H$62*(1+F$93)/($A97-F$93))/(1+$A97)^4.5-$B$10)/$B$8
A98: 0.1444 | B98: =(($D$62/(1+$A98)^0.5+$E$62/(1+$A98)^1.5+$F$62/(1+$A98)^2.5+$G$62/(1+$A98)^3.5+$H$62/(1+$A98)^4.5)+($H$62*(1+B$93)/($A98-B$93))/(1+$A98)^4.5-$B$10)/$B$8 | C98: =(($D$62/(1+$A98)^0.5+$E$62/(1+$A98)^1.5+$F$62/(1+$A98)^2.5+$G$62/(1+$A98)^3.5+$H$62/(1+$A98)^4.5)+($H$62*(1+C$93)/($A98-C$93))/(1+$A98)^4.5-$B$10)/$B$8 | D98: =(($D$62/(1+$A98)^0.5+$E$62/(1+$A98)^1.5+$F$62/(1+$A98)^2.5+$G$62/(1+$A98)^3.5+$H$62/(1+$A98)^4.5)+($H$62*(1+D$93)/($A98-D$93))/(1+$A98)^4.5-$B$10)/$B$8 | E98: =(($D$62/(1+$A98)^0.5+$E$62/(1+$A98)^1.5+$F$62/(1+$A98)^2.5+$G$62/(1+$A98)^3.5+$H$62/(1+$A98)^4.5)+($H$62*(1+E$93)/($A98-E$93))/(1+$A98)^4.5-$B$10)/$B$8 | F98: =(($D$62/(1+$A98)^0.5+$E$62/(1+$A98)^1.5+$F$62/(1+$A98)^2.5+$G$62/(1+$A98)^3.5+$H$62/(1+$A98)^4.5)+($H$62*(1+F$93)/($A98-F$93))/(1+$A98)^4.5-$B$10)/$B$8
A100: SENSITIVITY: FY2030 EBIT Margin vs Terminal Growth — Implied Share Price ($)
A102: EBIT Mgn ↓ / Term g → | B102: 0.02 | C102: 0.025 | D102: 0.03 | E102: 0.035 | F102: 0.04
A103: 0.15 | B103: =($B$78+(($H$51*(1+B$102)*($A103*(1-$B$12)+0.12-0.13))/($B$11-B$102))/(1+$B$11)^4.5-$B$10)/$B$8 | C103: =($B$78+(($H$51*(1+C$102)*($A103*(1-$B$12)+0.12-0.13))/($B$11-C$102))/(1+$B$11)^4.5-$B$10)/$B$8 | D103: =($B$78+(($H$51*(1+D$102)*($A103*(1-$B$12)+0.12-0.13))/($B$11-D$102))/(1+$B$11)^4.5-$B$10)/$B$8 | E103: =($B$78+(($H$51*(1+E$102)*($A103*(1-$B$12)+0.12-0.13))/($B$11-E$102))/(1+$B$11)^4.5-$B$10)/$B$8 | F103: =($B$78+(($H$51*(1+F$102)*($A103*(1-$B$12)+0.12-0.13))/($B$11-F$102))/(1+$B$11)^4.5-$B$10)/$B$8
A104: 0.2 | B104: =($B$78+(($H$51*(1+B$102)*($A104*(1-$B$12)+0.12-0.13))/($B$11-B$102))/(1+$B$11)^4.5-$B$10)/$B$8 | C104: =($B$78+(($H$51*(1+C$102)*($A104*(1-$B$12)+0.12-0.13))/($B$11-C$102))/(1+$B$11)^4.5-$B$10)/$B$8 | D104: =($B$78+(($H$51*(1+D$102)*($A104*(1-$B$12)+0.12-0.13))/($B$11-D$102))/(1+$B$11)^4.5-$B$10)/$B$8 | E104: =($B$78+(($H$51*(1+E$102)*($A104*(1-$B$12)+0.12-0.13))/($B$11-E$102))/(1+$B$11)^4.5-$B$10)/$B$8 | F104: =($B$78+(($H$51*(1+F$102)*($A104*(1-$B$12)+0.12-0.13))/($B$11-F$102))/(1+$B$11)^4.5-$B$10)/$B$8
A105: 0.25 | B105: =($B$78+(($H$51*(1+B$102)*($A105*(1-$B$12)+0.12-0.13))/($B$11-B$102))/(1+$B$11)^4.5-$B$10)/$B$8 | C105: =($B$78+(($H$51*(1+C$102)*($A105*(1-$B$12)+0.12-0.13))/($B$11-C$102))/(1+$B$11)^4.5-$B$10)/$B$8 | D105: =($B$78+(($H$51*(1+D$102)*($A105*(1-$B$12)+0.12-0.13))/($B$11-D$102))/(1+$B$11)^4.5-$B$10)/$B$8 | E105: =($B$78+(($H$51*(1+E$102)*($A105*(1-$B$12)+0.12-0.13))/($B$11-E$102))/(1+$B$11)^4.5-$B$10)/$B$8 | F105: =($B$78+(($H$51*(1+F$102)*($A105*(1-$B$12)+0.12-0.13))/($B$11-F$102))/(1+$B$11)^4.5-$B$10)/$B$8
A106: 0.3 | B106: =($B$78+(($H$51*(1+B$102)*($A106*(1-$B$12)+0.12-0.13))/($B$11-B$102))/(1+$B$11)^4.5-$B$10)/$B$8 | C106: =($B$78+(($H$51*(1+C$102)*($A106*(1-$B$12)+0.12-0.13))/($B$11-C$102))/(1+$B$11)^4.5-$B$10)/$B$8 | D106: =($B$78+(($H$51*(1+D$102)*($A106*(1-$B$12)+0.12-0.13))/($B$11-D$102))/(1+$B$11)^4.5-$B$10)/$B$8 | E106: =($B$78+(($H$51*(1+E$102)*($A106*(1-$B$12)+0.12-0.13))/($B$11-E$102))/(1+$B$11)^4.5-$B$10)/$B$8 | F106: =($B$78+(($H$51*(1+F$102)*($A106*(1-$B$12)+0.12-0.13))/($B$11-F$102))/(1+$B$11)^4.5-$B$10)/$B$8
A107: 0.35 | B107: =($B$78+(($H$51*(1+B$102)*($A107*(1-$B$12)+0.12-0.13))/($B$11-B$102))/(1+$B$11)^4.5-$B$10)/$B$8 | C107: =($B$78+(($H$51*(1+C$102)*($A107*(1-$B$12)+0.12-0.13))/($B$11-C$102))/(1+$B$11)^4.5-$B$10)/$B$8 | D107: =($B$78+(($H$51*(1+D$102)*($A107*(1-$B$12)+0.12-0.13))/($B$11-D$102))/(1+$B$11)^4.5-$B$10)/$B$8 | E107: =($B$78+(($H$51*(1+E$102)*($A107*(1-$B$12)+0.12-0.13))/($B$11-E$102))/(1+$B$11)^4.5-$B$10)/$B$8 | F107: =($B$78+(($H$51*(1+F$102)*($A107*(1-$B$12)+0.12-0.13))/($B$11-F$102))/(1+$B$11)^4.5-$B$10)/$B$8

Sheet SpaceX WACC
A1: SpaceX — Weighted Average Cost of Capital
A2: Pre-IPO consolidated entity (incl. Starlink, Launch, xAI/SpaceXAI)
A4: COST OF EQUITY (CAPM)
A5: Risk-Free Rate (10Y UST) | B5: 0.0425
A6: Equity Risk Premium | B6: 0.055
A7: Beta (peer-derived, levered) | B7: 1.4
A8: Country/Size Premium | B8: 0.005
A9: Cost of Equity | B9: =B5+B7*B6+B8
A11: COST OF DEBT
A12: Pre-Tax Cost of Debt | B12: 0.065
A13: Tax Rate | B13: 0.21
A14: After-Tax Cost of Debt | B14: =B12*(1-B13)
A16: CAPITAL STRUCTURE (at IPO)
A17: Market Cap at IPO ($B) | B17: 1750
A18: Total Debt ($B) | B18: 5
A19: Cash & Equivalents ($B) | B19: 3
A20: Net Debt ($B) | B20: =B18-B19
A21: Enterprise Value ($B) | B21: =B17+B20
A22: Equity Weight | B22: =B17/B21
A23: Debt Weight | B23: =B20/B21
A25: WACC
A26: WACC | B26: =B9*B22+B14*B23

Sheet SpaceX IPO Compare
A1: SpaceX — Intrinsic Value vs Broker IPO Price
A2: Change Case Selector on 'SpaceX DCF'!B4 to toggle Bear (1) / Base (2) / Bull (3)
A4: VALUATION SUMMARY (Active Case)
A5: Active Case | B5: ='SpaceX DCF'!B5
A6: Enterprise Value ($B) | B6: ='SpaceX DCF'!B80
A7: Equity Value ($B) | B7: ='SpaceX DCF'!B82
A8: Implied Share Price ($) | B8: ='SpaceX DCF'!B84
A10: BROKER IPO PRICE BENCHMARKS
A11: Scenario | B11: Valuation ($B) | C11: Price/Share ($) | D11: EV/2025 Rev (x) | E11: vs Intrinsic
A12: Insider Sale (Dec 2025) | B12: 800 | C12: =B12/'SpaceX DCF'!$B$8 | D12: =B12/'SpaceX DCF'!$C$51 | E12: ='SpaceX DCF'!$B$84/C12-1
A13: TechCrunch/WSJ Base IPO Target | B13: 1750 | C13: =B13/'SpaceX DCF'!$B$8 | D13: =B13/'SpaceX DCF'!$C$51 | E13: ='SpaceX DCF'!$B$84/C13-1
A14: Bloomberg Stretch IPO Target | B14: 2000 | C14: =B14/'SpaceX DCF'!$B$8 | D14: =B14/'SpaceX DCF'!$C$51 | E14: ='SpaceX DCF'!$B$84/C14-1
A16: INTERPRETATION
A17: Base case DCF (Starlink to $22B by FY30, Launch +3-5%/yr) yields ~$6.50/share intrinsic value.
A18: Broker IPO price of $350 (at $1.75T) implies a 98% premium to standalone DCF.
A19: This gap reflects:
A20: 1) Starship/Mars option value (not modeled in 5-year FCF horizon)
A21: 2) xAI/SpaceXAI long-term AI infrastructure optionality
A22: 3) Scarcity premium - the only listed pure-play LEO/launch leader
A23: 4) Passive index demand if added to S&P 500 / Nasdaq-100 fast-entry
A24: 5) Trading-multiple-based pricing (~87x P/S 2026E) vs intrinsic DCF
A26: EV/Sales context: $1.75T = ~94x 2025 revenue ($18.7B) - more than 2x Nvidia AI-peak multiple.
A27: For DCF to support $350/share, Starlink must reach ~$60-80B revenue or terminal margins ~35-40%.
A29: RECOMMENDATION
... A34: See sensitivity tables on 'SpaceX DCF' (rows 91-107) for the assumption combinations needed to close the gap.

Sheet DPZ Summary
A1: Domino's Pizza (DPZ) — Valuation Summary
A2: Why Buffett bought at $437 — the standard DCF is missing buybacks
A4: THE PUZZLE YOU IDENTIFIED
A5: Standard 15Y FCF DCF → implied price | B5: ='DPZ DCF'!B57
A6: Current market price | B6: ='DPZ DCF'!B5
A7: Buffett purchased at | B7: 437
A8: Standard DCF says current price is overvalued by: | B8: =B6/B5-1
A10: WHAT THE STANDARD DCF MISSES
A11: 1. Capital allocation (buybacks)
A12: DPZ retires ~3-4% of shares per year
A13: $1.46B buyback authorization (Apr 2026 = $1B new + $459.7M existing)
A14: Per-share FCF grows much faster than total FCF
A16: 2. Negative book equity is a feature, not a bug
A17: Stockholders' deficit of -$3.97B reflects $7B+ of cumulative buybacks
A18: Capital-light franchise model (99% franchised) needs minimal equity
A19: ROIC is enormous because invested capital is tiny
A21: 3. Defensive moat — lower required return
A22: Beta ~0.7, recession-resistant, 99% franchised → capital-light royalty stream
A23: Pricing power: low-cost meal occasion, scale advantage in supply chain
A25: PER-SHARE OWNER EARNINGS MODEL (Buffett's framework)
A26: FCF per share today (LTM Q1'26) | B26: ='Per-Share Model'!B7
A27: Annual buyback yield | B27: ='Per-Share Model'!B12
A28: Dividend yield | B28: ='Per-Share Model'!B13
A29: Total shareholder yield | B29: ='Per-Share Model'!B14
A31: Per-share intrinsic value (15Y, 9% disc, 2.5% term) | B31: ='Per-Share Model'!B38
A33: VS THE TWO REFERENCE POINTS
A34: Upside vs current price ($372) | B34: =B31/B6-1
A35: Margin of safety vs Buffett's $437 | B35: =B31/B7-1
A37: CONCLUSION
A38: Buffett did NOT buy on a standard DCF — he bought a per-share compounding machine.
A39: At $437, Buffett got DPZ at ~fair value of intrinsic per-share, with the buyback engine
A40: doing the heavy lifting on returns. At $372 today, you have ~16% upside before
A41: even counting the buybacks accelerating with the new $1B authorization.
A43: TODAY'S Q1'26 EARNINGS (Apr 27, 2026)
A44: Q1 EPS | B44: 4.13
A45: Q1 Revenue | B45: 1150.6
A46: NEW $1B buyback authorization announced today | B46: + existing $459.7M = $1.46B total firepower
A47: Implication: Q1 was a slight miss but BUYBACK was a clear bullish signal.
A48: Mgmt is signaling confidence in the per-share compounding model.

Sheet DPZ DCF
A1: 8
A2: Date: April 27, 2026 | FYE: Late December | All $ in millions except per-share
A4: MARKET DATA
A5: Current price | B5: =WACC!B16
A6: Diluted shares (M) | B6: =WACC!B17
A7: Market cap ($M) | B7: =B5*B6
A8: Net debt ($M) | B8: =WACC!B21
A9: Buffett purchase price (Q3 2024) | B9: 437
A11: HISTORICAL FINANCIALS ($M)
A12: Item | B12: FY2023 | C12: FY2024 | D12: FY2025 | E12: Q1'26 LTM*
A13: Revenue | B13: 4479 | C13: 4711 | D13: 4941 | E13: 5008
A14: Revenue growth % | C14: =C13/B13-1 | D14: =D13/C13-1 | E14: =E13/D13-1
A15: EBIT (Income from operations) | B15: 818 | C15: 879 | D15: 954 | E15: 977
A16: EBIT margin % | B16: =B15/B13 | C16: =C15/C13 | D16: =D15/D13 | E16: =E15/E13
A17: Net income | B17: 519 | C17: 584 | D17: 602 | E17: 600
A18: Operating cash flow | B18: 591 | C18: 625 | D18: 792 | E18: 800
A19: CapEx | B19: 105 | C19: 113 | D19: 121 | E19: 120
A20: Free Cash Flow | B20: =B18-B19 | C20: =C18-C19 | D20: =D18-D19 | E20: =E18-E19
A21: FCF margin % | B21: =B20/B13 | C21: =C20/C13 | D21: =D20/D13 | E21: =E20/E13
A23: BUFFETT-STYLE ASSUMPTIONS (Conservative)
A24: Revenue growth Y1-5 (high-vis) | B24: 0.05
A25: Revenue growth Y6-10 (fade) | B25: 0.04
A26: Revenue growth Y11-15 (mature) | B26: 0.03
A27: Steady-state FCF margin | B27: 0.13
A28: WACC (discount rate) | B28: =WACC!B27
A29: Buffett discount rate (alt) | B29: 0.09
A30: Terminal growth rate | B30: 0.025
A31: Use which discount rate? | B31: Buffett 9%
A32: Selected discount rate | B32: =IF(B31="WACC",B28,B29)
A34: 15-YEAR FCF PROJECTION ($M)
A35: Item | B35: FY26E | C35: FY27E | D35: FY28E | E35: FY29E | F35: FY30E | G35: FY31E | H35: FY32E | I35: FY33E | J35: FY34E | K35: FY35E | L35: FY36E | M35: FY37E | N35: FY38E | O35: FY39E | P35: FY40E
A36: Year # | B36: 1 | C36: 2 | D36: 3 | E36: 4 | F36: 5 | G36: 6 | H36: 7 | I36: 8 | J36: 9 | K36: 10 | L36: 11 | M36: 12 | N36: 13 | O36: 14 | P36: 15
A37: Revenue growth % | B37: =IF(B36<=5,$B$24,IF(B36<=10,$B$25,$B$26)) | C37: =IF(C36<=5,$B$24,IF(C36<=10,$B$25,$B$26)) | D37: =IF(D36<=5,$B$24,IF(D36<=10,$B$25,$B$26)) | E37: =IF(E36<=5,$B$24,IF(E36<=10,$B$25,$B$26)) | F37: =IF(F36<=5,$B$24,IF(F36<=10,$B$25,$B$26)) | G37: =IF(G36<=5,$B$24,IF(G36<=10,$B$25,$B$26)) | H37: =IF(H36<=5,$B$24,IF(H36<=10,$B$25,$B$26)) | I37: =IF(I36<=5,$B$24,IF(I36<=10,$B$25,$B$26)) | ... P37: =IF(P36<=5,$B$24,IF(P36<=10,$B$25,$B$26))
A38: Revenue | B38: =$E$13*(1+B37) | C38: =B38*(1+C37) | D38: =C38*(1+D37) | E38: =D38*(1+E37) | F38: =E38*(1+F37) | G38: =F38*(1+G37) | H38: =G38*(1+H37) | I38: =H38*(1+I37) | J38: =I38*(1+J37) | ... P38: =O38*(1+P37)
A39: FCF margin % | B39: =$B$27 | C39: =$B$27 | D39: =$B$27 | E39: =$B$27 | F39: =$B$27 | G39: =$B$27 | H39: =$B$27 | I39: =$B$27 | ... P39: =$B$27
A40: Free Cash Flow | B40: =B38*B39 | C40: =C38*C39 | D40: =D38*D39 | E40: =E38*E39 | F40: =F38*F39 | G40: =G38*G39 | H40: =H38*H39 | I40: =I38*I39 | ... P40: =P38*P39
A41: Discount period (mid-yr) | B41: =B36-0.5 | C41: =C36-0.5 | D41: =D36-0.5 | E41: =E36-0.5 | F41: =F36-0.5 | G41: =G36-0.5 | H41: =H36-0.5 | I41: =I36-0.5 | ... P41: =P36-0.5
A42: Discount factor | B42: =1/(1+$B$32)^B41 | C42: =1/(1+$B$32)^C41 | D42: =1/(1+$B$32)^D41 | E42: =1/(1+$B$32)^E41 | F42: =1/(1+$B$32)^F41 | G42: =1/(1+$B$32)^G41 | H42: =1/(1+$B$32)^H41 | I42: =1/(1+$B$32)^I41 | ... P42: =1/(1+$B$32)^P41
A43: PV of FCF | B43: =B40*B42 | C43: =C40*C42 | D43: =D40*D42 | E43: =E40*E42 | F43: =F40*F42 | G43: =G40*G42 | H43: =H40*H42 | I43: =I40*I42 | ... P43: =P40*P42
A45: TERMINAL VALUE & VALUATION SUMMARY
A46: Terminal Year FCF (Y15) | B46: =P40
A47: Terminal growth rate | B47: =B30
A48: Terminal Value (Gordon Growth) at Y15 | B48: =B46*(1+B47)/(B32-B47)
A49: PV of Terminal Value | B49: =B48*P42
A51: Sum of PV of FCFs (Y1-15) | B51: =SUM(B43:P43)
A52: (+) PV of Terminal Value | B52: =B49
A53: Enterprise Value | B53: =B51+B52
A54: (−) Net debt | B54: =-B8
A55: Equity Value | B55: =B53+B54
A56: ÷ Diluted shares (M) | B56: =B6
A57: Implied price per share | B57: =B55/B56
A59: Current price | B59: =B5
A60: Buffett purchase ($437) | B60: =B9
A61: Upside vs current price | B61: =B57/B59-1
A62: Margin of safety vs Buffett's $437 | B62: =B57/B60-1
A64: % of EV from Terminal Value | B64: =B52/B53

Sheet Per-Share Model
A1: DPZ — PER-SHARE OWNER EARNINGS MODEL (Why Buffett Bought)
A2: Key insight: DPZ retires ~3-4% of shares annually. Per-share FCF grows much faster than total FCF.
A4: STARTING POINT (LTM as of Q1'26)
A5: LTM Free Cash Flow ($M) | B5: ='DPZ DCF'!E20
A6: Diluted shares (M) | B6: ='DPZ DCF'!B6
A7: FCF per share (LTM) | B7: =B5/B6
A9: BUYBACK YIELD
A10: Total buyback authorization (Apr 2026) | B10: 1460
A11: Annual buyback pace ($M, conservative) | B11: 500
A12: Implied annual share retirement % | B12: =B11/('DPZ DCF'!B7)
A13: Dividend yield (current) | B13: 0.0214
A14: Total shareholder yield (FCF yield + buyback) | B14: =B7/'DPZ DCF'!B5+B12
A16: 15-YEAR PER-SHARE FCF PROJECTION
A17: Item | B17: FY26E | C17: FY27E | D17: FY28E | E17: FY29E | F17: FY30E | G17: FY31E | H17: FY32E | I17: FY33E | J17: FY34E | K17: FY35E | L17: FY36E | M17: FY37E | N17: FY38E | O17: FY39E | P17: FY40E
A18: Year # | B18: 1 | C18: 2 | D18: 3 | E18: 4 | F18: 5 | G18: 6 | H18: 7 | I18: 8 | J18: 9 | K18: 10 | L18: 11 | M18: 12 | N18: 13 | O18: 14 | P18: 15
A19: Total FCF growth % | B19: =IF(B18<=5,'DPZ DCF'!$B$24,IF(B18<=10,'DPZ DCF'!$B$25,'DPZ DCF'!$B$26)) | C19: =IF(C18<=5,'DPZ DCF'!$B$24,IF(C18<=10,'DPZ DCF'!$B$25,'DPZ DCF'!$B$26)) | D19: =IF(D18<=5,'DPZ DCF'!$B$24,IF(D18<=10,'DPZ DCF'!$B$25,'DPZ DCF'!$B$26)) | E19: =IF(E18<=5,'DPZ DCF'!$B$24,IF(E18<=10,'DPZ DCF'!$B$25,'DPZ DCF'!$B$26)) | F19: =IF(F18<=5,'DPZ DCF'!$B$24,IF(F18<=10,'DPZ DCF'!$B$25,'DPZ DCF'!$B$26)) | G19: =IF(G18<=5,'DPZ DCF'!$B$24,IF(G18<=10,'DPZ DCF'!$B$25,'DPZ DCF'!$B$26)) | H19: =IF(H18<=5,'DPZ DCF'!$B$24,IF(H18<=10,'DPZ DCF'!$B$25,'DPZ DCF'!$B$26)) | I19: =IF(I18<=5,'DPZ DCF'!$B$24,IF(I18<=10,'DPZ DCF'!$B$25,'DPZ DCF'!$B$26)) | ... P19: =IF(P18<=5,'DPZ DCF'!$B$24,IF(P18<=10,'DPZ DCF'!$B$25,'DPZ DCF'!$B$26))
A20: Total FCF ($M) | B20: =$B$5*(1+B19) | C20: =B20*(1+C19) | D20: =C20*(1+D19) | E20: =D20*(1+E19) | F20: =E20*(1+F19) | G20: =F20*(1+G19) | H20: =G20*(1+H19) | I20: =H20*(1+I19) | J20: =I20*(1+J19) | ... P20: =O20*(1+P19)
A21: Share retirement % | B21: =$B$12*0.85 | C21: =$B$12*0.85 | D21: =$B$12*0.85 | E21: =$B$12*0.85 | F21: =$B$12*0.85 | G21: =$B$12*0.85 | H21: =$B$12*0.85 | I21: =$B$12*0.85 | ... P21: =$B$12*0.85
A22: Shares outstanding (M) | B22: =$B$6*(1-B21) | C22: =B22*(1-C21) | D22: =C22*(1-D21) | E22: =D22*(1-E21) | F22: =E22*(1-F21) | G22: =F22*(1-G21) | H22: =G22*(1-H21) | I22: =H22*(1-I21) | J22: =I22*(1-J21) | ... P22: =O22*(1-P21)
A23: FCF per share | B23: =B20/B22 | C23: =C20/C22 | D23: =D20/D22 | E23: =E20/E22 | F23: =F20/F22 | G23: =G20/G22 | H23: =H20/H22 | I23: =I20/I22 | ... P23: =P20/P22
A24: per-share FCF growth | B24: — | C24: =C23/B23-1 | D24: =D23/C23-1 | E24: =E23/D23-1 | F24: =F23/E23-1 | G24: =G23/F23-1 | H24: =H23/G23-1 | I24: =I23/H23-1 | J24: =J23/I23-1 | ... P24: =P23/O23-1
A25: Discount factor (9%) | B25: =1/(1+'DPZ DCF'!$B$32)^(B18-0.5) | C25: =1/(1+'DPZ DCF'!$B$32)^(C18-0.5) | D25: =1/(1+'DPZ DCF'!$B$32)^(D18-0.5) | E25: =1/(1+'DPZ DCF'!$B$32)^(E18-0.5) | F25: =1/(1+'DPZ DCF'!$B$32)^(F18-0.5) | G25: =1/(1+'DPZ DCF'!$B$32)^(G18-0.5) | H25: =1/(1+'DPZ DCF'!$B$32)^(H18-0.5) | I25: =1/(1+'DPZ DCF'!$B$32)^(I18-0.5) | ... P25: =1/(1+'DPZ DCF'!$B$32)^(P18-0.5)
A26: PV of FCF/share | B26: =B23*B25 | C26: =C23*C25 | D26: =D23*D25 | E26: =E23*E25 | F26: =F23*F25 | G26: =G23*G25 | H26: =H23*H25 | I26: =I23*I25 | ... P26: =P23*P25
A28: PER-SHARE VALUATION SUMMARY
A29: Terminal year FCF/share (Y15) | B29: =P23
A30: Terminal growth | B30: ='DPZ DCF'!B30
A31: Discount rate | B31: ='DPZ DCF'!B32
A32: Terminal value per share at Y15 | B32: =B29*(1+B30)/(B31-B30)
A33: PV of terminal value per share | B33: =B32*P25
A35: Sum PV of FCF/share (Y1-15) | B35: =SUM(B26:P26)
A36: (+) PV terminal value/share | B36: =B33
A37: (−) Net debt per share (current) | B37: =-'DPZ DCF'!B8/B6
A38: Intrinsic value per share | B38: =B35+B36+B37
A40: Current price | B40: ='DPZ DCF'!B5
A41: Buffett's purchase price | B41: ='DPZ DCF'!B9
A42: Upside vs current ($372) | B42: =B38/B40-1
A43: Margin of safety vs Buffett ($437) | B43: =B38/B41-1
A46: SENSITIVITY: Intrinsic Value/Share — Discount Rate vs Terminal Growth
A48: Discount \ Term g → | B48: 0.015 | C48: 0.02 | D48: 0.025 | E48: 0.03 | F48: 0.035
A49: 0.07 | B49: {=SUMPRODUCT($B$23:$P$23, 1/(1+$A49)^($B$18:$P$18-0.5)) + ($P$23*(1+B$48)/($A49-B$48))/((1+$A49)^14.5) - 'DPZ DCF'!$B$8/$B$6} | C49: {=SUMPRODUCT($B$23:$P$23, 1/(1+$A49)^($B$18:$P$18-0.5)) + ($P$23*(1+C$48)/($A49-C$48))/((1+$A49)^14.5) - 'DPZ DCF'!$B$8/$B$6} | D49: {=SUMPRODUCT($B$23:$P$23, 1/(1+$A49)^($B$18:$P$18-0.5)) + ($P$23*(1+D$48)/($A49-D$48))/((1+$A49)^14.5) - 'DPZ DCF'!$B$8/$B$6} | E49: {=SUMPRODUCT($B$23:$P$23, 1/(1+$A49)^($B$18:$P$18-0.5)) + ($P$23*(1+E$48)/($A49-E$48))/((1+$A49)^14.5) - 'DPZ DCF'!$B$8/$B$6} | F49: {=SUMPRODUCT($B$23:$P$23, 1/(1+$A49)^($B$18:$P$18-0.5)) + ($P$23*(1+F$48)/($A49-F$48))/((1+$A49)^14.5) - 'DPZ DCF'!$B$8/$B$6}
A50: 0.08 | B50: {=SUMPRODUCT($B$23:$P$23, 1/(1+$A50)^($B$18:$P$18-0.5)) + ($P$23*(1+B$48)/($A50-B$48))/((1+$A50)^14.5) - 'DPZ DCF'!$B$8/$B$6} | C50: {=SUMPRODUCT($B$23:$P$23, 1/(1+$A50)^($B$18:$P$18-0.5)) + ($P$23*(1+C$48)/($A50-C$48))/((1+$A50)^14.5) - 'DPZ DCF'!$B$8/$B$6} | D50: {=SUMPRODUCT($B$23:$P$23, 1/(1+$A50)^($B$18:$P$18-0.5)) + ($P$23*(1+D$48)/($A50-D$48))/((1+$A50)^14.5) - 'DPZ DCF'!$B$8/$B$6} | E50: {=SUMPRODUCT($B$23:$P$23, 1/(1+$A50)^($B$18:$P$18-0.5)) + ($P$23*(1+E$48)/($A50-E$48))/((1+$A50)^14.5) - 'DPZ DCF'!$B$8/$B$6} | F50: {=SUMPRODUCT($B$23:$P$23, 1/(1+$A50)^($B$18:$P$18-0.5)) + ($P$23*(1+F$48)/($A50-F$48))/((1+$A50)^14.5) - 'DPZ DCF'!$B$8/$B$6}
A51: 0.09 | B51: {=SUMPRODUCT($B$23:$P$23, 1/(1+$A51)^($B$18:$P$18-0.5)) + ($P$23*(1+B$48)/($A51-B$48))/((1+$A51)^14.5) - 'DPZ DCF'!$B$8/$B$6} | C51: {=SUMPRODUCT($B$23:$P$23, 1/(1+$A51)^($B$18:$P$18-0.5)) + ($P$23*(1+C$48)/($A51-C$48))/((1+$A51)^14.5) - 'DPZ DCF'!$B$8/$B$6} | D51: {=SUMPRODUCT($B$23:$P$23, 1/(1+$A51)^($B$18:$P$18-0.5)) + ($P$23*(1+D$48)/($A51-D$48))/((1+$A51)^14.5) - 'DPZ DCF'!$B$8/$B$6} | E51: {=SUMPRODUCT($B$23:$P$23, 1/(1+$A51)^($B$18:$P$18-0.5)) + ($P$23*(1+E$48)/($A51-E$48))/((1+$A51)^14.5) - 'DPZ DCF'!$B$8/$B$6} | F51: {=SUMPRODUCT($B$23:$P$23, 1/(1+$A51)^($B$18:$P$18-0.5)) + ($P$23*(1+F$48)/($A51-F$48))/((1+$A51)^14.5) - 'DPZ DCF'!$B$8/$B$6}
A52: 0.1 | B52: {=SUMPRODUCT($B$23:$P$23, 1/(1+$A52)^($B$18:$P$18-0.5)) + ($P$23*(1+B$48)/($A52-B$48))/((1+$A52)^14.5) - 'DPZ DCF'!$B$8/$B$6} | C52: {=SUMPRODUCT($B$23:$P$23, 1/(1+$A52)^($B$18:$P$18-0.5)) + ($P$23*(1+C$48)/($A52-C$48))/((1+$A52)^14.5) - 'DPZ DCF'!$B$8/$B$6} | D52: {=SUMPRODUCT($B$23:$P$23, 1/(1+$A52)^($B$18:$P$18-0.5)) + ($P$23*(1+D$48)/($A52-D$48))/((1+$A52)^14.5) - 'DPZ DCF'!$B$8/$B$6} | E52: {=SUMPRODUCT($B$23:$P$23, 1/(1+$A52)^($B$18:$P$18-0.5)) + ($P$23*(1+E$48)/($A52-E$48))/((1+$A52)^14.5) - 'DPZ DCF'!$B$8/$B$6} | F52: {=SUMPRODUCT($B$23:$P$23, 1/(1+$A52)^($B$18:$P$18-0.5)) + ($P$23*(1+F$48)/($A52-F$48))/((1+$A52)^14.5) - 'DPZ DCF'!$B$8/$B$6}
A53: 0.11 | B53: {=SUMPRODUCT($B$23:$P$23, 1/(1+$A53)^($B$18:$P$18-0.5)) + ($P$23*(1+B$48)/($A53-B$48))/((1+$A53)^14.5) - 'DPZ DCF'!$B$8/$B$6} | C53: {=SUMPRODUCT($B$23:$P$23, 1/(1+$A53)^($B$18:$P$18-0.5)) + ($P$23*(1+C$48)/($A53-C$48))/((1+$A53)^14.5) - 'DPZ DCF'!$B$8/$B$6} | D53: {=SUMPRODUCT($B$23:$P$23, 1/(1+$A53)^($B$18:$P$18-0.5)) + ($P$23*(1+D$48)/($A53-D$48))/((1+$A53)^14.5) - 'DPZ DCF'!$B$8/$B$6} | E53: {=SUMPRODUCT($B$23:$P$23, 1/(1+$A53)^($B$18:$P$18-0.5)) + ($P$23*(1+E$48)/($A53-E$48))/((1+$A53)^14.5) - 'DPZ DCF'!$B$8/$B$6} | F53: {=SUMPRODUCT($B$23:$P$23, 1/(1+$A53)^($B$18:$P$18-0.5)) + ($P$23*(1+F$48)/($A53-F$48))/((1+$A53)^14.5) - 'DPZ DCF'!$B$8/$B$6}
A56: HISTORICAL CAPITAL RETURN SINCE IPO (2004) — Source: SEC 10-K filings
A58: Year | B58: Shares Outstanding (M, year-end) | C58: Buyback ($M) | D58: Avg Price ($) | E58: Share Reduction % | F58: FCF ($M) | G58: FCF/share ($) | H58: FCF/share Growth %
A59: FY2004 | B59: 65.5 | C59: 0 | F59: 80 | G59: =F59/B59
A60: FY2005 | B60: 66.8 | C60: 0 | E60: =1-B60/B59 | F60: 80 | G60: =F60/B60 | H60: =G60/G59-1
A61: FY2006 | B61: 64.5 | C61: 595 | D61: 26 | E61: =1-B61/B60 | F61: 100 | G61: =F61/B61 | H61: =G61/G60-1
A62: FY2007 | B62: 60 | C62: 200 | D62: 16 | E62: =1-B62/B61 | F62: 92 | G62: =F62/B62 | H62: =G62/G61-1
A63: FY2008 | B63: 57.7 | C63: 14 | D63: 11 | E63: =1-B63/B62 | F63: 119 | G63: =F63/B63 | H63: =G63/G62-1
A64: FY2009 | B64: 57.3 | C64: 0 | E64: =1-B64/B63 | F64: 88 | G64: =F64/B64 | H64: =G64/G63-1
A65: FY2010 | B65: 60 | C65: 53 | D65: 13 | E65: =1-B65/B64 | F65: 113 | G65: =F65/B65 | H65: =G65/G64-1
A66: FY2011 | B66: 60.4 | C66: 18 | D66: 27 | E66: =1-B66/B65 | F66: 145 | G66: =F66/B66 | H66: =G66/G65-1
A67: FY2012 | B67: 58.6 | C67: 88 | D67: 36 | E67: =1-B67/B66 | F67: 130 | G67: =F67/B67 | H67: =G67/G66-1
A68: FY2013 | B68: 56.9 | C68: 97 | D68: 58 | E68: =1-B68/B67 | F68: 156 | G68: =F68/B68 | H68: =G68/G67-1
A69: FY2014 | B69: 55.6 | C69: 82 | D69: 72 | E69: =1-B69/B68 | F69: 174 | G69: =F69/B69 | H69: =G69/G68-1
A70: FY2015 | B70: 56.5 | C70: 100 | D70: 105 | E70: =1-B70/B69 | F70: 220 | G70: =F70/B70 | H70: =G70/G69-1
A71: FY2016 | B71: 51 | C71: 502 | D71: 145 | E71: =1-B71/B70 | F71: 246 | G71: =F71/B71 | H71: =G71/G70-1
A72: FY2017 | B72: 47.9 | C72: 798 | D72: 188 | E72: =1-B72/B71 | F72: 281 | G72: =F72/B72 | H72: =G72/G71-1
A73: FY2018 | B73: 43 | C73: 600 | D73: 250 | E73: =1-B73/B72 | F73: 312 | G73: =F73/B73 | H73: =G73/G72-1
A74: FY2019 | B74: 41.5 | C74: 700 | D74: 270 | E74: =1-B74/B73 | F74: 379 | G74: =F74/B74 | H74: =G74/G73-1
A75: FY2020 | B75: 39.5 | C75: 187 | D75: 380 | E75: =1-B75/B74 | F75: 489 | G75: =F75/B75 | H75: =G75/G74-1
A76: FY2021 | B76: 37 | C76: 1085 | D76: 458 | E76: =1-B76/B75 | F76: 540 | G76: =F76/B76 | H76: =G76/G75-1
... A80: FY2025 | B80: 34.6 | C80: 540 | D80: 470 | E80: =1-B80/B79 | F80: 671 | G80: =F80/B80 | H80: =G80/G79-1
A82: TOTALS / SUMMARY (FY2004 → FY2025)
A83: Total $ deployed on buybacks | C83: =SUM(C59:C80)
A84: Total cumulative share reduction | B84: =B80/B59-1
A85: FCF/share CAGR (2004→2025, 21 yrs) | B85: =(G80/G59)^(1/21)-1
A86: FCF (total) CAGR (2004→2025) | B86: =(F80/F59)^(1/21)-1
A87: Avg annual share reduction (geometric) | B87: =1-(B80/B59)^(1/21)
A88: Avg annual FCF/share growth (geometric) | B88: =(G80/G59)^(1/21)-1
A90: Source: DPZ 10-K filings 2004-2025 (SEC EDGAR). Shares = year-end common stock outstanding.
A91: FY2006 buyback includes $13.50/share special dividend recapitalization (Apr 2007 effectively prior period). FY2010 had small reissuance offsetting buybacks.

Sheet WACC
A1: DPZ — WACC Calculation
A2: As of April 27, 2026
A4: COST OF EQUITY (CAPM)
A5: Risk-free rate (10Y Treasury) | B5: 0.043
A6: Beta (5Y monthly) | B6: 0.7
A7: Equity Risk Premium | B7: 0.055
A8: Cost of Equity = Rf + β × ERP | B8: =B5+B6*B7
A10: COST OF DEBT
A11: Pre-tax cost of debt (avg coupon) | B11: 0.052
A12: Tax rate | B12: 0.22
A13: After-tax cost of debt | B13: =B11*(1-B12)
A15: CAPITAL STRUCTURE
A16: Share price ($) | B16: 372
A17: Diluted shares (M) | B17: 33.6
A18: Market cap ($M) | B18: =B16*B17
A19: Total debt ($M) | B19: 5000
A20: Cash & restricted cash ($M) | B20: 216
A21: Net debt ($M) | B21: =B19-B20
A22: Enterprise value ($M) | B22: =B18+B21
A24: Equity weight | B24: =B18/B22
A25: Debt weight | B25: =B21/B22
A27: WACC | B27: =B8*B24+B13*B25
A29: Note: Buffett-style — we'll also test 9-10% as a more conservative discount rate.

Sheet Peer Comparison
A1: DPZ vs Peers vs Market Expectations — How Realistic is 5% FCF Growth?
A2: Question: Our DCF assumes 5% revenue/FCF growth Y1-5. Is that conservative, base-case, or aggressive?
A4: QSR PEER GROWTH PROFILE (Consensus FY26-28)
A5: Company | B5: Ticker | C5: Rev Growth FY26E | D5: EPS Growth FY26-28E CAGR | E5: Q4'25 SSS | F5: Business Model | G5: Note
A6: Domino's Pizza | B6: DPZ | C6: 0.055 | D6: 0.102 | E6: 0 | F6: 99% franchised + supply chain | G6: Most aggressive buyback in QSR
A7: Chipotle | B7: CMG | C7: 0.07 | D7: 0.13 | E7: -0.04 | F7: Company-owned | G7: Currently struggling — SSS turned negative
A8: Wingstop | B8: WING | C8: 0.12 | D8: 0.18 | E8: -0.058 | F8: Asset-light franchise | G8: High unit growth offsets weak SSS
A9: Yum! Brands | B9: YUM | C9: 0.05 | D9: 0.09 | E9: 0.04 | F9: Multi-brand franchise | G9: Closest peer to DPZ scale & model
A10: Restaurant Brands | B10: QSR | C10: 0.05 | D10: 0.08 | E10: 0.026 | F10: Multi-brand franchise | G10: BK/THI/Popeyes; mature
A11: McDonald's | B11: MCD | C11: 0.04 | D11: 0.07 | E11: 0.02 | F11: 95% franchised | G11: Most mature comp
A12: Papa John's | B12: PZZA | C12: 0.02 | D12: 0.04 | E12: -0.02 | F12: Franchise | G12: Direct pizza competitor — losing share to DPZ
A14: Restaurants Industry Avg (consensus) | C14: 0.067 | D14: 0.189
A15: US Pizza Foodservice Mkt CAGR 26-31 | C15: 0.0746
A16: DPZ mgmt LT target (US retail sales) | C16: 0.06
A17: DPZ mgmt LT target (op income growth) | D17: 0.07
A19: VERDICT: How likely is 5% FCF growth?
A20: Reference point | B20: Growth Rate | C20: Read
A21: DPZ historical FCF CAGR (FY04-FY25, 21yr) | B21: 0.107 | C21: Actual track record — well above 5%
A22: DPZ historical FCF CAGR (FY15-FY25, 10yr) | B22: 0.118 | C22: More recent 10-yr period even stronger
A23: DPZ historical Revenue CAGR (FY15-FY25, 10yr) | B23: 0.064 | C23: Revenue grew slower than FCF (margin expansion)
A24: Analyst consensus FY26 revenue growth | B24: 0.055 | C24: Matches our 5% assumption — in line
A25: Analyst consensus EPS CAGR FY26-28 | B25: 0.102 | C25: EPS grows ~2x faster than revenue (buyback effect)
A26: Mgmt long-term op income target | B26: 0.07 | C26: Mgmt confidence is above our 5%
A27: US Pizza foodservice market CAGR | B27: 0.0746 | C27: Industry growing faster than 5%
A28: Restaurants industry avg consensus rev | B28: 0.067 | C28: Industry expects 6.7% — we're below
A29: OUR DCF ASSUMPTION (Y1-5) | B29: 0.05 | C29: BELOW all reference points — conservative
A31: PROBABILITY ASSESSMENT
A32: Scenario | B32: Probability | C32: Implied FCF Growth Y1-5
A33: Bear: SSS stagnation, traffic loss, competition | B33: 0.2 | C33: 2-3%
A34: Base: 5% (our model) — conservative vs analyst 5.5%, mgmt 6-7% | B34: 0.55 | C34: 0.05
A35: Bull: hits mgmt LT target of 7%+, regains SSS momentum | B35: 0.25 | C35: 7-9%
A37: BOTTOM LINE
A38: 5% FCF growth is a CONSERVATIVE assumption.
A39: • DPZ delivered 10.7% FCF CAGR over 21 years
A40: • Analyst consensus FY26 = 5.5%; mgmt LT target = 6-7%
A41: • US pizza market CAGR forecast = 7.5%
A42: • Q1'26 was a soft quarter (flat SSS) — but mgmt confidence shown via $1B buyback
A43: • Real risk: GLP-1 drugs, 3rd-party delivery dilution, beef/labor inflation pressuring franchisee economics
A45: What WOULD make 5% wrong on the downside?
A46: 1. Persistent negative SSS (Q1'26 was already flat — watch closely)
A47: 2. International store growth slowing (60%+ of new units come from intl)
A48: 3. Franchisee margin pressure forcing closures (labor, beef)
A49: 4. Refinancing risk: $1.3B refi due July 2027 — if rates spike, FCF gets pinched

Sheet Dashboard
A1: S&P 500 Dashboard
A2: Last updated: 2026-10-20 15:02:44 | 482 full / 8 partial / 4 no-data (kept) | 145s elapsed
A3: Total: 494 companies | IV: 15-yr Buffett DCF + geo-risk v4 (Iran ceasefire fragile, Brent $104, S&P 7,500 ATH, fwd P/E 21.2, Fed 3.50-3.75% held 8-4) | BRK Q1 2026 13F (filed May 15): $263B portfolio, 29 positions (-13), 16 exits incl V/MA/UNH/DPZ/HEI/CHTR/AON/POOL/LAMR/ALLE, CVX -35%, STZ -95%, GOOGL TRIPLED to $15.6B, new DAL/GOOG/M. Abel cash $380B
J4: Run: python update_sp500_dashboard.py | M4: ▶ UPDATE DATA | O4: BRK: 13F thru Q4 2025 + Q1 26 earnings ($397B cash) | KHC exit REVERSED | BAC sell 7th qtr | $234M buyback | Abel "core four": AAPL AXP KO MCO
A5: # | B5: Ticker | C5: Company | D5: Industry | E5: Share Price ($) | F5: 1Y Price Change (%) | G5: Market Cap ($B) | H5: Revenue Growth (%) | I5: Gross Margin (%) | J5: P/E | K5: FCF ($M) | L5: Intrinsic Value ($B) | M5: IV vs MCap Discount (%) | N5: P/FCF | O5: BRK? | P5: BRK Pos ($B) | Q5: BRK Net Action | R5: BRK Avg Cost ($) | S5: Activity Detail (2025-Q1 2026)
A6: 1 | B6: MS | C6: Morgan Stanley | D6: Capital Markets | E6: 178.47 | F6: 0.12083149 | G6: 280.29898 | H6: 0.108 | I6: 0.87307 | J6: 14.153053 | K6: — | L6: — | M6: — | N6: — | O6: — | P6: — | Q6: — | R6: — | S6: —
A7: 2 | B7: SCHW | C7: Charles Schwab | D7: Capital Markets | E7: 89.58 | F7: -0.057945132 | G7: 154.9139 | H7: 0.169 | I7: 0.97506 | J7: 15.312821 | K7: — | L7: 58.800668 | M7: -0.62043 | N7: — | O7: — | P7: — | Q7: — | R7: — | S7: —
A8: 3 | B8: O | C8: Realty Income | D8: REIT - Retail | E8: 55.51 | F8: -0.07529569 | G8: 52.52456 | H8: 0.096 | I8: 0.9268 | J8: 40.224636 | K8: 1582.0819 | L8: 6.1463742 | M8: -0.88298095 | N8: 33.199648 | O8: — | P8: — | Q8: — | R8: — | S8: —
A9: 4 | B9: PLD | C9: Prologis | D9: REIT - Industrial | E9: 124.09 | F9: -0.015080571 | G9: 120.62681 | H9: 0.102 | I9: 0.75709 | J9: 27.575554 | K9: — | L9: 21.711072 | M9: -0.82001454 | N9: — | O9: — | P9: — | Q9: — | R9: — | S9: —
A10: 5 | B10: BAC | C10: Bank of America | D10: Banks - Diversified | E10: 50.39 | F10: -0.021933258 | G10: 352.36459 | H10: 0.071 | I10: 0 | J10: 12.026253 | K10: — | L10: 146.9885 | M10: -0.58285112 | N10: — | O10: YES | P10: 25.1 | Q10: Sell | R10: 25.7 | S10: Sold 48.7M Q1-25 → 26.3M Q2 → 50.8M Q4 → Q1-26: TRIMMED <1% (~4M sh) to 513M. 9.5% of portfolio. $ drop mostly price ($55→$49)
A11: 6 | B11: VRSN | C11: VeriSign | D11: Software - Infrastructure | E11: 306.48 | F11: 0.15019143 | G11: 27.705793 | H11: 0.06 | I11: 0.88465 | J11: 33.276875 | K11: 832.8375 | L11: 7.3862498 | M11: -0.73340413 | N11: 33.266744 | O11: YES | P11: 3.2 | Q11: Hold | R11: 27 | S11: Held Q1-Q2-25 → Trimmed Q3-Q4 → Q1-26: UNCHANGED (NOT exited — Kiplinger/Benzinga not in 16-exit list). ~13.5M sh
A12: 7 | B12: COF | C12: Capital One Financial | D12: Credit Services | E12: 199.83 | F12: -0.07933658 | G12: 122.59571 | H12: 11.11 | I12: 0 | J12: 12.834297 | K12: — | L12: 47.679789 | M12: -0.6110811 | N12: — | O12: YES | P12: 2.05 | Q12: Hold | R12: 95 | S12: ~9.9M sh since 2022. Q1-26: UNCHANGED (NOT exited despite Combs-era origin). Held through Combs departure
A13: 8 | B13: ESS | C13: Essex Property Trust | D13: REIT - Residential | E13: 266.65 | F13: 0.017825842 | G13: 18.379168 | H13: 0.031 | I13: 0.68771005 | J13: 41.469673 | K13: 1043.9267 | L13: 2.0062438 | M13: -0.89084142 | N13: 16.414364 | O13: — | P13: — | Q13: — | R13: — | S13: —
A14: 9 | B14: REG | C14: Regency Centers | D14: REIT - Retail | E14: 72.41 | F14: 0.0034645796 | G14: 13.537682 | H14: 0.089 | I14: 0.71539 | J14: 24.380472 | K14: 743.36397 | L14: 2.629481 | M14: -0.80576579 | N14: 17.837505 | O14: — | P14: — | Q14: — | R14: — | S14: —
A15: 10 | B15: V | C15: Visa | D15: Credit Services | E15: 402.92 | F15: 0.16045046 | G15: 756.42398 | H15: 0.144 | I15: 0.97725 | J15: 34.291065 | K15: 20404.001 | L15: 52.817226 | M15: -0.9301751 | N15: 33.651297 | O15: SOLD | P15: — | Q15: Sold | R15: 130 | S15: Held unchanged 2025 → Q1-26: ABEL FULLY EXITED. Combs-era position (since 2011). Symbolic: "no longer a fan of payments processors" (Kiplinger)
A16: 11 | B16: EXR | C16: Extra Space Storage | D16: REIT - Industrial | E16: 138.18 | F16: -0.08216542 | G16: 30.496676 | H16: 0.038 | I16: 0.74919 | J16: 30.503307 | K16: 1499.4376 | L16: 4.6436544 | M16: -0.84773244 | N16: 19.469452 | O16: — | P16: — | Q16: — | R16: — | S16: —
A17: 12 | B17: GS | C17: Goldman Sachs Group | D17: Capital Markets | E17: 875.78 | F17: 0.15389073 | G17: 255.00208 | H17: 0.233 | I17: 0.81287 | J17: 12.592092 | K17: — | L17: 103.35889 | M17: -0.59467431 | N17: — | O17: — | P17: — | Q17: — | R17: — | S17: —
A18: 13 | B18: SYF | C18: Synchrony Finl | D18: Credit Services | E18: 74.24 | F18: 0.003243208 | G18: 24.155531 | H18: 0.006 | I18: 0 | J18: 7.598771 | K18: — | L18: 17.08696 | M18: -0.29262745 | N18: — | O18: — | P18: — | Q18: — | R18: — | S18: —
A19: 14 | B19: SPG | C19: Simon Property Group | D19: REIT - Retail | E19: 202.49 | F19: 0.13300133 | G19: 76.86996 | H19: 0.195 | I19: 0.81426 | J19: 14.29005 | K19: 2595.2712 | L19: 6.352417 | M19: -0.91736151 | N19: 25.244355 | O19: — | P19: — | Q19: — | R19: — | S19: —
A20: 15 | B20: AVB | C20: AvalonBay Communities | D20: REIT - Residential | E20: 184.06 | F20: -0.008827567 | G20: 26.283393 | H20: 0.023 | I20: 0.62721 | J20: 25.248285 | K20: 1409.1441 | L20: 5.0274582 | M20: -0.80872111 | N20: 18.652027 | O20: — | P20: — | Q20: — | R20: — | S20: —
A21: 16 | B21: PSA | C21: Public Storage | D21: REIT - Industrial | E21: 295.69 | F21: -0.04080838 | G21: 55.250354 | H21: 0.033 | I21: 0.7442 | J21: 28.241642 | K21: 2334.2403 | L21: 5.688993 | M21: -0.89703246 | N21: 23.669524 | O21: — | P21: — | Q21: — | R21: — | S21: —
A22: 17 | B22: KIM | C22: Kimco Realty | D22: REIT - Retail | E22: 22.69 | F22: 0.021611929 | G22: 15.220212 | H22: 0.049 | I22: 0.68933 | J22: 26.694117 | K22: 871.48339 | L22: 2.8744259 | M22: -0.81114416 | N22: 17.464717 | O22: — | P22: — | Q22: — | R22: — | S22: —
A23: 18 | B23: CME | C23: CME Group | D23: Financial Data & Stock Exchanges | E23: 293.53 | F23: 0.092773914 | G23: 105.5473 | H23: 0.008 | I23: 1 | J23: 24.896523 | K23: 2909.0125 | L23: 22.398196 | M23: -0.78778997 | N23: 36.282546 | O23: — | P23: — | Q23: — | R23: — | S23: —
A24: 19 | B24: MAA | C24: Mid-America Apartment | D24: REIT - Residential | E24: 115.8 | F24: -0.13193405 | G24: 13.818025 | H24: 0.01 | I24: 0.58392 | J24: 33.85965 | K24: 921.18227 | L24: 1.8788979 | M24: -0.86402559 | N24: 14.630503 | O24: — | P24: — | Q24: — | R24: — | S24: —
A25: 20 | B25: STT | C25: State Street | D25: Asset Management | E25: 165.43 | F25: 0.44657218 | G25: 45.443912 | H25: 0.133 | I25: 0 | J25: 13.515523 | K25: — | L25: 17.145955 | M25: -0.62270072 | N25: — | O25: — | P25: — | Q25: — | R25: — | S25: —
A26: 21 | B26: DLR | C26: Digital Realty Trust | D26: REIT - Office | E26: 173 | F26: 0.007982254 | G26: 65.33582 | H26: 0.299 | I26: 0.56994 | J26: 83.98058 | K26: 3768.482 | L26: 3.8116993 | M26: -0.94165989 | N26: 17.031468 | O26: — | P26: — | Q26: — | R26: — | S26: —
A27: 22 | B27: EQR | C27: Equity Residential | D27: REIT - Residential | E27: 63.66 | F27: -0.012717128 | G27: 24.609972 | H27: 0.021 | I27: 0.62336 | J27: 28.675674 | K27: 1423.1534 | L27: 4.11841 | M27: -0.8326528 | N27: 16.770821 | O27: — | P27: — | Q27: — | R27: — | S27: —
A28: 23 | B28: KEY | C28: KeyCorp | D28: Banks - Regional | E28: 19.92 | F28: 0.13568985 | G28: 21.257202 | H28: 0.101 | I28: 0 | J28: 11.581395 | K28: — | L28: 8.859944 | M28: -0.58320271 | N28: — | O28: — | P28: — | Q28: — | R28: — | S28: —
A29: 24 | B29: MKTX | C29: MarketAxess Holdings | D29: Capital Markets | E29: 164.53 | F29: -0.048574567 | G29: 5.7909944 | H29: -0.005 | I29: 0.61662996 | J29: 19.44799 | K29: -457.79002 | L29: 1.5571058 | M29: -0.73111599 | N29: -12.649893 | O29: — | P29: — | Q29: — | R29: — | S29: —
A30: 25 | B30: ARE | C30: Alexandria Real Estate | D30: REIT - Office | E30: 40.63 | F30: -0.47089463 | G30: 6.9922314 | H30: -0.119 | I30: 0.68198997 | J30: -50.160496 | K30: 1344.974 | L30: 2.0695483 | M30: -0.70402177 | N30: 5.1987855 | O30: — | P30: — | Q30: — | R30: — | S30: —
A31: 26 | B31: BIIB | C31: Biogen | D31: Drug Manufacturers - General | E31: 233.48 | F31: 0.59677196 | G31: 34.497602 | H31: 0.034 | I31: 0.78322 | J31: 41.47069 | K31: 1266.9875 | L31: 11.541485 | M31: -0.66544094 | N31: 27.228053 | O31: — | P31: — | Q31: — | R31: — | S31: —
A32: 27 | B32: MA | C32: Mastercard | D32: Credit Services | E32: 616.4 | F32: 0.07756591 | G32: 539.97253 | H32: 0.141 | I32: 1 | J32: 33.90539 | K32: 16961.25 | L32: 9.1340944 | M32: -0.98308415 | N32: 31.59777 | O32: SOLD | P32: — | Q32: Sold | R32: 90 | S32: Held since 2011 → Q1-26: ABEL FULLY EXITED with V. Combs-era payments exposure ended entirely
A33: 28 | B33: RF | C33: Regions Financial | D33: Banks - Regional | E33: 27.2 | F33: 0.11658454 | G33: 23.172483 | H33: 0.052 | I33: 0 | J33: 11.102041 | K33: — | L33: 10.270064 | M33: -0.55679917 | N33: — | O33: — | P33: — | Q33: — | R33: — | S33: —
A34: 29 | B34: MSCI | C34: MSCI | D34: Financial Data & Stock Exchanges | E34: 563.49 | F34: 0.042804837 | G34: 40.965722 | H34: 0.122 | I34: 0.82975 | J34: 30.791803 | K34: 1194.7059 | L34: — | M34: — | N34: 34.289378 | O34: — | P34: — | Q34: — | R34: — | S34: —
A35: 30 | B35: AVGO | C35: Broadcom | D35: Semiconductors | E35: 334.59 | F35: -0.023551047 | G35: 1597.2088 | H35: 0.855 | I35: 0.75515 | J35: 42.7318 | K35: 30596.499 | L35: 331.55864 | M35: -0.79241371 | N35: 52.202338 | O35: — | P35: — | Q35: — | R35: — | S35: —
A36: 31 | B36: PNC | C36: PNC Financial Services Gr | D36: Banks - Regional | E36: 216.21 | F36: 0.18855476 | G36: 86.255616 | H36: 0.109 | I36: 0 | J36: 11.574411 | K36: — | L36: 41.313085 | M36: -0.5210389 | N36: — | O36: — | P36: — | Q36: — | R36: — | S36: —
A37: 32 | B37: SBAC | C37: SBA Communications | D37: REIT - Specialty | E37: 183.09 | F37: -0.07375932 | G37: 19.423672 | H37: 0.023 | I37: 0.742 | J37: 19.750807 | K37: 752.05638 | L37: — | M37: — | N37: 25.827415 | O37: — | P37: — | Q37: — | R37: — | S37: —
A38: 33 | B38: TXN | C38: Texas Instruments | D38: Semiconductors | E38: 276.15 | F38: 0.5270405 | G38: 252.19334 | H38: 0.228 | I38: 0.58325 | J38: 42.031963 | K38: 3545.25 | L38: 41.247468 | M38: -0.83644505 | N38: 71.13556 | O38: — | P38: — | Q38: — | R38: — | S38: —
A39: 34 | B39: BXP | C39: Boston Properties | D39: REIT - Office | E39: 57.94 | F39: -0.19494236 | G39: 10.480038 | H39: 0.037 | I39: 0.56452 | J39: 31.150537 | K39: 880.63686 | L39: 1.3389336 | M39: -0.87223962 | N39: 10.50466 | O39: — | P39: — | Q39: — | R39: — | S39: —
A40: 35 | B40: SPGI | C40: S&P Global | D40: Financial Data & Stock Exchanges | E40: 427.83 | F40: -0.06526321 | G40: 126.12428 | H40: 0.104 | I40: 0.70903 | J40: 26.135 | K40: 5448.2499 | L40: 23.841224 | M40: -0.81097038 | N40: 23.149504 | O40: — | P40: — | Q40: — | R40: — | S40: —
A41: 36 | B41: NVDA | C41: NVIDIA | D41: Semiconductors | E41: 217.09 | F41: 0.1983329 | G41: 5242.0721 | H41: 1.059 | I41: 0.74674004 | J41: 27.445007 | K41: 41809.875 | L41: 472.9762 | M41: -0.90977305 | N41: 125.37881 | O41: — | P41: — | Q41: — | R41: — | S41: —
A42: 37 | B42: UDR | C42: UDR | D42: REIT - Residential | E42: 33.84 | F42: -0.075157166 | G42: 12.538249 | H42: -0.001 | I42: 0.66581 | J42: 21.41772 | K42: 779.82778 | L42: 1.9670042 | M42: -0.8431197 | N42: 14.099454 | O42: — | P42: — | Q42: — | R42: — | S42: —
A43: 38 | B43: ABBV | C43: AbbVie | D43: Drug Manufacturers - General | E43: 282.68 | F43: 0.22166038 | G43: 499.5287 | H43: 0.102 | I43: 0.72792 | J43: 79.8531 | K43: 16870.25 | L43: 207.41014 | M43: -0.58478833 | N43: 29.610035 | O43: — | P43: — | Q43: — | R43: — | S43: —
A44: 39 | B44: MO | C44: Altria Group | D44: Tobacco | E44: 74.09 | F44: 0.16219604 | G44: 123.71132 | H44: 0.012 | I44: 0.8717 | J44: 15.597894 | K44: 9054.0001 | L44: 57.141013 | M44: -0.53811006 | N44: 13.663721 | O44: — | P44: — | Q44: — | R44: — | S44: —
A45: 40 | B45: AXP | C45: American Express | D45: Credit Services | E45: 316.41 | F45: -0.10925621 | G45: 213.67479 | H45: 0.128 | I45: 0.62338 | J45: 19.199636 | K45: — | L45: 56.330539 | M45: -0.73637255 | N45: — | O45: YES | P45: 45.86 | Q45: Hold | R45: 8.49 | S45: 151.6M sh, 17.4% of portfolio, 22.2% of AXP outstanding. Q1-26: UNCHANGED. Drop from $56.1B is price ($370→$302). "Core four" forever
A46: 41 | B46: NTRS | C46: Northern Trust | D46: Asset Management | E46: 164.46 | F46: 0.2796452 | G46: 30.088886 | H46: 0.364 | I46: 0 | J46: 14.128866 | K46: — | L46: 11.452337 | M46: -0.61938316 | N46: — | O46: — | P46: — | Q46: — | R46: — | S46: —
A47: 42 | B47: GILD | C47: Gilead Sciences | D47: Drug Manufacturers - General | E47: 153.07 | F47: 0.2336396 | G47: 189.79996 | H47: 0.102 | I47: 0.79603994 | J47: 15.379083 | K47: 9768.875 | L47: 120.86826 | M47: -0.36318078 | N47: 19.429047 | O47: — | P47: — | Q47: — | R47: — | S47: —
A48: 43 | B48: ADBE | C48: Adobe | D48: Software - Infrastructure | E48: 247.09 | F48: -0.30893582 | G48: 96.167428 | H48: 0.129 | I48: 0.89252996 | J48: 13.796204 | K48: 9345.1254 | L48: 111.04901 | M48: 0.1547466 | N48: 10.290651 | O48: — | P48: — | Q48: — | R48: — | S48: —
A49: 44 | B49: AMGN | C49: Amgen | D49: Drug Manufacturers - General | E49: 424.94 | F49: 0.41110444 | G49: 229.73617 | H49: 0.095 | I49: 0.71891 | J49: 26.39379 | K49: 8645.6248 | L49: 110.08259 | M49: -0.52083038 | N49: 26.572535 | O49: — | P49: — | Q49: — | R49: — | S49: —
A50: 45 | B50: AMT | C50: American Tower | D50: REIT - Specialty | E50: 183.03 | F50: -0.048552275 | G50: 85.284667 | H50: 0.047 | I50: 0.73774004 | J50: 25.176065 | K50: 2920.0125 | L50: 5.4556466 | M50: -0.93603016 | N50: 29.206952 | O50: — | P50: — | Q50: — | R50: — | S50: —
A51: 46 | B51: ICE | C51: Intercontinental Exchange | D51: Financial Data & Stock Exchanges | E51: 158.4 | F51: 0.010268569 | G51: 88.924881 | H51: 0.048 | I51: 1 | J51: 22.341324 | K51: 3633.6251 | L51: 22.113584 | M51: -0.75132287 | N51: 24.472774 | O51: — | P51: — | Q51: — | R51: — | S51: —
A52: 47 | B52: VRTX | C52: Vertex Pharmaceuticals | D52: Biotechnology | E52: 501.95 | F52: 0.17754006 | G52: 127.14394 | H52: 0.125 | I52: 0.54957 | J52: 29.234129 | K52: 2627.8876 | L52: 31.713941 | M52: -0.75056662 | N52: 48.382562 | O52: — | P52: — | Q52: — | R52: — | S52: —
A53: 48 | B53: MTB | C53: M&T Bank | D53: Banks - Regional | E53: 213.74 | F53: 0.17633462 | G53: 30.977978 | H53: 0.005 | I53: 0 | J53: 11.29704 | K53: — | L53: 13.409153 | M53: -0.56713917 | N53: — | O53: — | P53: — | Q53: — | R53: — | S53: —
A54: 49 | B54: ADI | C54: Analog Devices | D54: Semiconductors | E54: 394.35 | F54: 0.60064137 | G54: 191.08839 | H54: 0.396 | I54: 0.65800005 | J54: 46.83492 | K54: 4147.339 | L54: 44.322936 | M54: -0.76805009 | N54: 46.074939 | O54: — | P54: — | Q54: — | R54: — | S54: —
A55: 50 | B55: MCO | C55: Moody's | D55: Financial Data & Stock Exchanges | E55: 481.26 | F55: -0.007547617 | G55: 83.345089 | H55: 0.151 | I55: 0.74974996 | J55: 30.536802 | K55: 2579.125 | L55: 4.9684841 | M55: -0.9403866 | N55: 32.315254 | O55: YES | P55: 11.97 | Q55: Hold | R55: 10.05 | S55: 24.67M sh since 2000. Q1-26: UNCHANGED. ~$485/sh value. "Core four" forever
A56: 51 | B56: FTNT | C56: Fortinet | D56: Software - Infrastructure | E56: 171.5 | F56: 1.0228827 | G56: 125.8319 | H56: 0.256 | I56: 0.80204004 | J56: 62.82051 | K56: 2265.5875 | L56: 29.603204 | M56: -0.76474007 | N56: 55.540514 | O56: — | P56: — | Q56: — | R56: — | S56: —
A57: 52 | B57: EA | C57: Electronic Arts | D57: Electronic Gaming & Multimedia | E57: 209.7 | F57: 0.2005496 | G57: 52.925641 | H57: 0.189 | I57: 0.79875 | J57: 59.743587 | K57: 1692.5 | L57: 23.198579 | M57: -0.56167599 | N57: 31.270689 | O57: — | P57: — | Q57: — | R57: — | S57: —
A58: 53 | B58: HBAN | C58: Huntington Bancshares | D58: Banks - Regional | E58: 15.23 | F58: -0.044542015 | G58: 30.770917 | H58: 0.476 | I58: 0 | J58: 11.715385 | K58: — | L58: 13.236214 | M58: -0.56984661 | N58: — | O58: — | P58: — | Q58: — | R58: — | S58: —
A59: 54 | B59: ORCL | C59: Oracle | D59: Software - Infrastructure | E59: 129.59 | F59: -0.52902055 | G59: 392.85221 | H59: 0.296 | I59: 0.63957 | J59: 20.31191 | K59: -45853.626 | L59: — | M59: — | N59: -8.5675281 | O59: — | P59: — | Q59: — | R59: — | S59: —
A60: 55 | B60: PM | C60: Philip Morris Intl | D60: Tobacco | E60: 201.05 | F60: 0.3226974 | G60: 313.35924 | H60: 0.104 | I60: 0.67481005 | J60: 28.886494 | K60: 9714.3747 | L60: 100.17429 | M60: -0.68032124 | N60: 32.257273 | O60: — | P60: — | Q60: — | R60: — | S60: —
A61: 56 | B61: PRU | C61: Prudential Financial | D61: Insurance - Life | E61: 113.67 | F61: 0.11594343 | G61: 39.216148 | H61: 0.141 | I61: 0.29015 | J61: 10.296196 | K61: 7527.7501 | L61: 28.83348 | M61: -0.26475493 | N61: 5.2095446 | O61: — | P61: — | Q61: — | R61: — | S61: —
A62: 57 | B62: MSFT | C62: Microsoft | D62: Software - Infrastructure | E62: 533.52 | F62: 0.03063786 | G62: 3961.6774 | H62: 0.177 | I62: 0.67944 | J62: 29.722563 | K62: 16545.5 | L62: 248.70586 | M62: -0.93722208 | N62: 239.44136 | O62: — | P62: — | Q62: — | R62: — | S62: —
A63: 58 | B63: BKNG | C63: Booking Holdings | D63: Travel Services | E63: 162.6 | F63: -0.23098749 | G63: 125.99525 | H63: 0.081 | I63: 0.87227994 | J63: 18.026608 | K63: 7725.8752 | L63: 64.585589 | M63: -0.48739662 | N63: 16.308215 | O63: — | P63: — | Q63: — | R63: — | S63: —
A64: 59 | B64: INTU | C64: Intuit | D64: Software - Application | E64: 325.62 | F64: -0.51762855 | G64: 87.017382 | H64: 0.137 | I64: 0.80982 | J64: 19.782503 | K64: 6353.6251 | L64: 80.11254 | M64: -0.079350147 | N64: 13.695707 | O64: — | P64: — | Q64: — | R64: — | S64: —
A65: 60 | B65: WELL | C65: Welltower | D65: REIT - Healthcare Facilities | E65: 233.51 | F65: 0.3334285 | G65: 168.26076 | H65: 0.391 | I65: 0.39560002 | J65: 104.713 | K65: 2756.1644 | L65: 6.6061653 | M65: -0.96073853 | N65: 61.048889 | O65: — | P65: — | Q65: — | R65: — | S65: —
A66: 61 | B66: INCY | C66: Incyte | D66: Biotechnology | E66: 113.25 | F66: 0.29725087 | G66: 22.95552 | H66: 0.377 | I66: 0.55659 | J66: 14.426752 | K66: 1180.6646 | L66: 15.8712 | M66: -0.30861076 | N66: 19.44288 | O66: — | P66: — | Q66: — | R66: — | S66: —
A67: 62 | B67: GL | C67: Globe Life | D67: Insurance - Life | E67: 167.85 | F67: 0.23410046 | G67: 12.899181 | H67: 0.08 | I67: 0.33905998 | J67: 11.042764 | K67: 1163.5034 | L67: 11.497888 | M67: -0.10863425 | N67: 11.0865 | O67: — | P67: — | Q67: — | R67: — | S67: —
A68: 63 | B68: CSCO | C68: Cisco Systems | D68: Communication Equipment | E68: 106.5 | F68: 0.5059389 | G68: 419.88551 | H68: 0.176 | I68: 0.64524 | J68: 31.981983 | K68: 11182.625 | L68: 132.20532 | M68: -0.6851396 | N68: 37.548027 | O68: — | P68: — | Q68: — | R68: — | S68: —
A69: 64 | B69: QCOM | C69: Qualcomm | D69: Semiconductors | E69: 173.53 | F69: 0.027838707 | G69: 185.30219 | H69: -0.04 | I69: 0.54226 | J69: 20.08449 | K69: 10241 | L69: 49.983336 | M69: -0.73026041 | N69: 18.094149 | O69: — | P69: — | Q69: — | R69: — | S69: —
A70: 65 | B70: TTWO | C70: Take-Two Interactive | D70: Electronic Gaming & Multimedia | E70: 204.92 | F70: -0.21269405 | G70: 38.316032 | H70: 0.02 | I70: 0.57126 | J70: 19.910282 | K70: 1256.1375 | L70: 10.229491 | M70: -0.7330232 | N70: 30.503057 | O70: — | P70: — | Q70: — | R70: — | S70: —
A71: 66 | B71: PAYX | C71: Paychex | D71: Staffing & Employment Services | E71: 110.75 | F71: -0.13164496 | G71: 39.42484 | H71: 0.059 | I71: 0.74391997 | J71: 21.974207 | K71: 1887.1124 | L71: 15.685458 | M71: -0.60214277 | N71: 20.891621 | O71: — | P71: — | Q71: — | R71: — | S71: —
... A85: 80 | B85: AFL | C85: Aflac | D85: Insurance - Life | E85: 118.67 | F85: 0.096968055 | G85: 59.494408 | H85: -0.01 | I85: 0.50888 | J85: 12.760215 | K85: 5152.2499 | L85: 43.551672 | M85: -0.26797034 | N85: 11.547268 | O85: — | P85: — | Q85: — | R85: — | S85: —
A86: 81 | B86: JNJ | C86: Johnson & Johnson | D86: Drug Manufacturers - General | E86: 253.79 | F86: 0.3226496 | G86: 611.6081 | H86: 0.059 | I86: 0.67754996 | J86: 38.51138 | K86: — | L86: — | M86: — | N86: — | O86: — | P86: — | Q86: — | R86: — | S86: —
A87: 82 | B87: LRCX | C87: Lam Research | D87: Semiconductor Equipment & Materials | E87: 272.2 | F87: 0.87672365 | G87: 340.63775 | H87: 0.3 | I87: 0.50469 | J87: 47.256947 | K87: 3090.4845 | L87: 39.306245 | M87: -0.88460984 | N87: 110.22146 | O87: — | P87: — | Q87: — | R87: — | S87: —
A88: 83 | B88: QRVO | C88: Qorvo | D88: Semiconductors | E88: 114.17 | F88: 0.2993058 | G88: 10.07185 | H88: -0.042 | I88: 0.48535 | J88: 26.48956 | K88: 476.14202 | L88: 2.955626 | M88: -0.70654587 | N88: 21.153037 | O88: — | P88: — | Q88: — | R88: — | S88: —
A89: 84 | B89: AAPL | C89: Apple | D89: Consumer Electronics | E89: 342.94 | F89: 0.30509567 | G89: 5004.9282 | H89: 0.164 | I89: 0.48653 | J89: 39.32798 | K89: 107721.88 | L89: 1212.6009 | M89: -0.75771863 | N89: 46.461576 | O89: YES | P89: 57.93 | Q89: Hold | R89: 39 | S89: 227.9M sh, ~22.0% of portfolio. Q1-26 13F: UNCHANGED — Abel paused the trim. Drop from $61.96B is price (Q4 $271→Q1 $254). "Core four" — untouchable
A90: 85 | B90: CF | C90: CF Industries Holdings | D90: Agricultural Inputs | E90: 118.51 | F90: 0.4228599 | G90: 17.935081 | H90: 0.176 | I90: 0.42486 | J90: 8.791543 | K90: 1276.75 | L90: 16.358265 | M90: -0.087917971 | N90: 14.047451 | O90: — | P90: — | Q90: — | R90: — | S90: —
A91: 86 | B91: MNST | C91: Monster Beverage | D91: Beverages - Non-Alcoholic | E91: 46.8 | F91: 0.3584906 | G91: 91.683619 | H91: 0.202 | I91: 0.55546004 | J91: 43.333332 | K91: 1681.2311 | L91: 21.645852 | M91: -0.76390709 | N91: 54.533623 | O91: — | P91: — | Q91: — | R91: — | S91: —
A92: 87 | B92: EBAY | C92: eBay | D92: Internet Retail | E92: 120.47 | F92: 0.2683723 | G92: 53.609153 | H92: 0.148 | I92: 0.72052 | J92: 25.362106 | K92: 1579.625 | L92: 17.418381 | M92: -0.67508568 | N92: 33.937898 | O92: — | P92: — | Q92: — | R92: — | S92: —
A93: 88 | B93: UNP | C93: Union Pacific | D93: Railroads | E93: 287.01 | F93: 0.26692855 | G93: 170.50562 | H93: 0.115 | I93: 0.56285 | J93: 23.258509 | K93: 4720.7501 | L93: 43.226831 | M93: -0.74647855 | N93: 36.11833 | O93: — | P93: — | Q93: — | R93: — | S93: —
A94: 89 | B94: KLAC | C94: KLA | D94: Semiconductor Equipment & Materials | E94: 166.4 | F94: 0.45019734 | G94: 217.15306 | H94: 0.152 | I94: 0.61301 | J94: 45.464478 | K94: 2624.5875 | L94: 33.493299 | M94: -0.84576179 | N94: 82.737984 | O94: — | P94: — | Q94: — | R94: — | S94: —
A95: 90 | B95: TROW | C95: T. Rowe Price Group | D95: Asset Management | E95: 100.1 | F95: -0.039808154 | G95: 21.352917 | H95: 0.107 | I95: 0.51614 | J95: 10.0502 | K95: 2023.9124 | L95: 11.511489 | M95: -0.46089386 | N95: 10.550316 | O95: — | P95: — | Q95: — | R95: — | S95: —
A96: 91 | B96: KO | C96: Coca-Cola | D96: Beverages - Non-Alcoholic | E96: 93.42 | F96: 0.31171024 | G96: 401.94412 | H96: 0.067 | I96: 0.61888003 | J96: 28.054054 | K96: 5218.75 | L96: 53.820032 | M96: -0.86610071 | N96: 77.019239 | O96: YES | P96: 30.41 | Q96: Hold | R96: 3.25 | S96: 400M sh (9.3% of KO), 11.6% of portfolio. Q1-26: UNCHANGED. Held since 1988. "Core four" forever
A97: 92 | B97: CFG | C97: Citizens Financial Group | D97: Banks - Regional | E97: 62.76 | F97: 0.2347039 | G97: 26.433055 | H97: 0.119 | I97: 0 | J97: 13.673202 | K97: — | L97: 10.085804 | M97: -0.61843971 | N97: — | O97: — | P97: — | Q97: — | R97: — | S97: —
A98: 93 | B98: PYPL | C98: PayPal Holdings | D98: Credit Services | E98: 56.51 | F98: -0.19329053 | G98: 48.711619 | H98: 0.048 | I98: 0.40477002 | J98: 10.68242 | K98: 4423.125 | L98: 26.419148 | M98: -0.45764176 | N98: 11.012942 | O98: — | P98: — | Q98: — | R98: — | S98: —
A99: 94 | B99: CRM | C99: Salesforce | D99: Software - Application | E99: 242.45 | F99: -0.07957178 | G99: 199.53635 | H99: 0.108 | I99: 0.77282 | J99: 22.182066 | K99: 17731.875 | L99: 190.25661 | M99: -0.046506473 | N99: 11.252975 | O99: — | P99: — | Q99: — | R99: — | S99: —
A100: 95 | B100: MDT | C100: Medtronic | D100: Medical Devices | E100: 92.77 | F100: -0.03193152 | G100: 118.66562 | H100: 0.137 | I100: 0.65271 | J100: 22.79361 | K100: 5412.5 | L100: 77.741669 | M100: -0.34486778 | N100: 21.924364 | O100: — | P100: — | Q100: — | R100: — | S100: —
A101: 96 | B101: MRK | C101: Merck & Co | D101: Drug Manufacturers - General | E101: 143.63 | F101: 0.63923764 | G101: 354.35987 | H101: 0.051 | I101: 0.759 | J101: 113.99206 | K101: 15171.5 | L101: 144.36981 | M101: -0.59258985 | N101: 23.356943 | O101: — | P101: — | Q101: — | R101: — | S101: —
A102: 97 | B102: SNPS | C102: Synopsys | D102: Software - Infrastructure | E102: 454.58 | F102: -0.009715915 | G102: 87.114179 | H102: 0.424 | I102: 0.82921 | J102: 80.31448 | K102: 3425.5424 | L102: 43.003298 | M102: -0.50635707 | N102: 25.430772 | O102: — | P102: — | Q102: — | R102: — | S102: —
A103: 98 | B103: USB | C103: U.S. Bancorp | D103: Banks - Regional | E103: 57.85 | F103: 0.21508086 | G103: 90.133275 | H103: 0.084 | I103: 0 | J103: 11.254864 | K103: — | L103: 38.518477 | M103: -0.57264975 | N103: — | O103: — | P103: — | Q103: — | R103: — | S103: —
A104: 99 | B104: ZTS | C104: Zoetis | D104: Drug Manufacturers - Specialty & Generic | E104: 79.59 | F104: -0.45519882 | G104: 32.888465 | H104: -0.002 | I104: 0.71738 | J104: 13.09046 | K104: 2016.9999 | L104: 15.159745 | M104: -0.53905587 | N104: 16.305636 | O104: — | P104: — | Q104: — | R104: — | S104: —
A105: 100 | B105: EW | C105: Edwards Lifesciences | D105: Medical Devices | E105: 87.22 | F105: 0.14732969 | G105: 50.221277 | H105: 0.136 | I105: 0.77839 | J105: 51.916668 | K105: 1232.4125 | L105: 19.295273 | M105: -0.61579486 | N105: 40.750377 | O105: — | P105: — | Q105: — | R105: — | S105: —
A106: 101 | B106: FITB | C106: Fifth Third Bancorp | D106: Banks - Regional | E106: 50.51 | F106: 0.19777095 | G106: 45.790999 | H106: 0.518 | I106: 0 | J106: 16.949663 | K106: — | L106: 11.367987 | M106: -0.75174189 | N106: — | O106: — | P106: — | Q106: — | R106: — | S106: —
A107: 102 | B107: MSI | C107: Motorola Solutions | D107: Communication Equipment | E107: 458.9 | F107: 0.024101734 | G107: 75.945099 | H107: 0.133 | I107: 0.52112 | J107: 36.133858 | K107: 1979.0001 | L107: 21.229092 | M107: -0.72046791 | N107: 38.375491 | O107: — | P107: — | Q107: — | R107: — | S107: —
A108: 103 | B108: YUM | C108: Yum Brands | D108: Restaurants | E108: 149.83 | F108: 0.008752465 | G108: 40.888771 | H108: 0.122 | I108: 0.45311 | J108: 18.870277 | K108: 833.24998 | L108: 8.1650371 | M108: -0.80031101 | N108: 49.071432 | O108: — | P108: — | Q108: — | R108: — | S108: —
A109: 104 | B109: AMAT | C109: Applied Materials | D109: Semiconductor Equipment & Materials | E109: 413.11 | F109: 0.8279203 | G109: 327.84302 | H109: 0.248 | I109: 0.49398 | J109: 35.643658 | K109: 3075.3751 | L109: 41.635635 | M109: -0.87300131 | N109: 106.60262 | O109: — | P109: — | Q109: — | R109: — | S109: —
A110: 105 | B110: MET | C110: MetLife | D110: Insurance - Life | E110: 99.58 | F110: 0.26018727 | G110: 63.280796 | H110: 0.105 | I110: 0.23951 | J110: 19.07663 | K110: -20953.999 | L110: 28.162072 | M110: -0.55496653 | N110: -3.0199864 | O110: — | P110: — | Q110: — | R110: — | S110: —
A111: 106 | B111: WAT | C111: Waters | D111: Diagnostics & Research | E111: 434.27 | F111: 0.24350715 | G111: 42.639172 | H111: 1.134 | I111: 0.56337 | J111: 109.94177 | K111: -142.06763 | L111: — | M111: — | N111: -300.13291 | O111: — | P111: — | Q111: — | R111: — | S111: —
A112: 107 | B112: AME | C112: AMETEK | D112: Specialty Industrial Machinery | E112: 247.22 | F112: 0.31290495 | G112: 56.663568 | H112: 0.15 | I112: 0.36905998 | J112: 36.143272 | K112: 1492.2213 | L112: 15.718969 | M112: -0.72259126 | N112: 37.972629 | O112: — | P112: — | Q112: — | R112: — | S112: —
A113: 108 | B113: NDAQ | C113: Nasdaq | D113: Financial Data & Stock Exchanges | E113: 93.2 | F113: 0.031772375 | G113: 52.096688 | H113: 0.149 | I113: 1 | J113: 27.17201 | K113: 1691.5 | L113: 10.544737 | M113: -0.79759296 | N113: 30.799107 | O113: — | P113: — | Q113: — | R113: — | S113: —
...

Sheet Все компании
A1: № | B1: Company | D1: Ticker | E1: Share price | F1: 1 year change | G1: Market Cap | H1: IV | I1: Discount | J1: Growth annual | K1: Margin (gross) | L1: P/E | M1: Beta | N1: Tangible book value/share | O1: USD/RUB | P1: HKD/USD
E2: $ | F2: % | G2: mkn $ | H2: mln $ | J2: % | K2: % | O2: 77 | P2: 0.13
A3: =A2+1 | B3: =HYPERLINK("https://finance.yahoo.com/quote/"&D3, C3) | C3: Severstal' PAO | D3: SVST | E3: =IFERROR(__xludf.DUMMYFUNCTION("iferror(googlefinance(D3,""price""),"""")"),"") | F3: =IFERROR(__xludf.DUMMYFUNCTION("IFERROR(GOOGLEFINANCE(D3,""price"") / index(GOOGLEFINANCE(D3,""price"", datevalue(today()-365) ) , 2,2) - 1,"""")"),"") | G3: =IFERROR(__xludf.DUMMYFUNCTION("iferror(googlefinance(D3,""marketcap""),"""")/10^6"),0) | H3: =IFERROR(__xludf.DUMMYFUNCTION("IMPORTRANGE(""https://docs.google.com/spreadsheets/d/1dlfFsw9YFF_dEa-0WVRTnvUf7PBFwRrC6Y6BImZdJ_g/edit#gid=412432278"",""Summary!C30"")"),985803.888993602) | I3: =(H3-G3)/G3 | J3: =IFERROR(__xludf.DUMMYFUNCTION("IMPORTRANGE(""https://docs.google.com/spreadsheets/d/1dlfFsw9YFF_dEa-0WVRTnvUf7PBFwRrC6Y6BImZdJ_g/edit#gid=412432278"",""Summary!H2"")"),-0.157778595071717) | K3: =IFERROR(__xludf.DUMMYFUNCTION("IMPORTRANGE(""https://docs.google.com/spreadsheets/d/1dlfFsw9YFF_dEa-0WVRTnvUf7PBFwRrC6Y6BImZdJ_g/edit#gid=412432278"",""Summary!B16"")"),0.280931586608442) | L3: =IFERROR(__xludf.DUMMYFUNCTION("IFERROR(googlefinance(D3,""pe""),"""")"),"") | M3: =IFERROR(__xludf.DUMMYFUNCTION("IFERROR(googlefinance(D3,""beta""),"""")"),"")
A4: =A3+1 | B4: =HYPERLINK("https://finance.yahoo.com/quote/"&D4, C4) | C4: Sberbank Rossii PAO | D4: SBRCY | E4: =IFERROR(__xludf.DUMMYFUNCTION("iferror(googlefinance(D4,""price""),"""")"),"") | F4: =IFERROR(__xludf.DUMMYFUNCTION("IFERROR(GOOGLEFINANCE(D4,""price"") / index(GOOGLEFINANCE(D4,""price"", datevalue(today()-365) ) , 2,2) - 1,"""")"),"") | G4: =IFERROR(__xludf.DUMMYFUNCTION("iferror(googlefinance(D4,""marketcap""),"""")/10^6"),0) | H4: =IFERROR(__xludf.DUMMYFUNCTION("IMPORTRANGE(""https://docs.google.com/spreadsheets/d/1qkyVDQA4KrhGN7P_pvU-cCYRhkeObohXrHMSpHSzFaY/edit#gid=1866964818"",""Summary!C34"")"),9333100.82858735) | I4: =(H4-G4)/G4 | J4: =IFERROR(__xludf.DUMMYFUNCTION("IMPORTRANGE(""https://docs.google.com/spreadsheets/d/1qkyVDQA4KrhGN7P_pvU-cCYRhkeObohXrHMSpHSzFaY/edit#gid=1866964818"",""Summary!I2"")"),0.0894187779433681) | K4: =IFERROR(__xludf.DUMMYFUNCTION("IMPORTRANGE(""https://docs.google.com/spreadsheets/d/1qkyVDQA4KrhGN7P_pvU-cCYRhkeObohXrHMSpHSzFaY/edit#gid=1866964818"",""Summary!H20"")"),0.347013223894208) | L4: =IFERROR(__xludf.DUMMYFUNCTION("IFERROR(googlefinance(D4,""pe""),"""")"),"") | M4: =IFERROR(__xludf.DUMMYFUNCTION("IFERROR(googlefinance(D4,""beta""),"""")"),"")
A5: =A4+1 | B5: =HYPERLINK("https://finance.yahoo.com/quote/"&D5, C5) | C5: DouYu International Holdings Ltd | D5: DOYU | E5: =IFERROR(__xludf.DUMMYFUNCTION("iferror(googlefinance(D5,""price""),"""")"),5.28) | F5: =IFERROR(__xludf.DUMMYFUNCTION("IFERROR(GOOGLEFINANCE(D5,""price"") / index(GOOGLEFINANCE(D5,""price"", datevalue(today()-365) ) , 2,2) - 1,"""")"),-0.218934911242603) | G5: =IFERROR(__xludf.DUMMYFUNCTION("iferror(googlefinance(D5,""marketcap""),"""")/10^6"),163.952824) | H5: =IFERROR(__xludf.DUMMYFUNCTION("IMPORTRANGE(""https://docs.google.com/spreadsheets/d/1LupNll8EBZR0CxUoQzkZLRitp2lxm5UXiwXAxqniEg4/edit#gid=1537202402"",""DOYU!E29"")"),58.701638056861) | I5: =(H5-G5)/G5 | J5: =IFERROR(__xludf.DUMMYFUNCTION("IMPORTRANGE(""https://docs.google.com/spreadsheets/d/1LupNll8EBZR0CxUoQzkZLRitp2lxm5UXiwXAxqniEg4/edit#gid=1537202402"",""DOYU!I6"")"),5530) | K5: =IFERROR(__xludf.DUMMYFUNCTION("IMPORTRANGE(""https://docs.google.com/spreadsheets/d/1LupNll8EBZR0CxUoQzkZLRitp2lxm5UXiwXAxqniEg4/edit#gid=1537202402"",""DOYU!F23"")"),0.16248307467972) | L5: =IFERROR(__xludf.DUMMYFUNCTION("IFERROR(googlefinance(D5,""pe""),"""")"),"") | M5: =IFERROR(__xludf.DUMMYFUNCTION("IFERROR(googlefinance(D5,""beta""),"""")"),"")
A6: =A5+1 | B6: =HYPERLINK("https://finance.yahoo.com/quote/"&D6, C6) | C6: TCS Group Holding PLC | D6: TCSG | E6: =IFERROR(__xludf.DUMMYFUNCTION("iferror(googlefinance(D6,""price""),"""")"),"") | F6: =IFERROR(__xludf.DUMMYFUNCTION("IFERROR(GOOGLEFINANCE(D6,""price"") / index(GOOGLEFINANCE(D6,""price"", datevalue(today()-365) ) , 2,2) - 1,"""")"),"") | G6: =IFERROR(__xludf.DUMMYFUNCTION("iferror(googlefinance(D6,""marketcap""),"""")/10^6"),0) | H6: =IFERROR(__xludf.DUMMYFUNCTION("importrange(""https://docs.google.com/spreadsheets/d/1dcdnXtSf0zvBGYPG5ZVxziOJBBQiAwWkEZT-UAXL40I/edit#gid=1344089490"",""Summary!C36"")/#REF!*1000"),"#REF!") | I6: 0 | J6: =IFERROR(__xludf.DUMMYFUNCTION("importrange(""https://docs.google.com/spreadsheets/d/1dcdnXtSf0zvBGYPG5ZVxziOJBBQiAwWkEZT-UAXL40I/edit#gid=1344089490"",""Summary!J2"")"),0.78) | K6: =IFERROR(__xludf.DUMMYFUNCTION("importrange(""https://docs.google.com/spreadsheets/d/1dcdnXtSf0zvBGYPG5ZVxziOJBBQiAwWkEZT-UAXL40I/edit#gid=1344089490"",""Summary!I22"")"),0.351235955056179) | L6: =IFERROR(__xludf.DUMMYFUNCTION("IFERROR(googlefinance(D6,""pe""),"""")"),"") | M6: =IFERROR(__xludf.DUMMYFUNCTION("IFERROR(googlefinance(D6,""beta""),"""")"),"")
A7: =A6+1 | B7: =HYPERLINK("https://finance.yahoo.com/quote/"&D7, C7) | C7: Boeing Co | D7: BA | E7: =IFERROR(__xludf.DUMMYFUNCTION("iferror(googlefinance(D7,""price""),"""")"),227.53) | F7: =IFERROR(__xludf.DUMMYFUNCTION("IFERROR(GOOGLEFINANCE(D7,""price"") / index(GOOGLEFINANCE(D7,""price"", datevalue(today()-365) ) , 2,2) - 1,"""")"),0.337939550746795) | G7: =IFERROR(__xludf.DUMMYFUNCTION("iferror(googlefinance(D7,""marketcap""),"""")/10^6"),178690.024704) | H7: =IFERROR(__xludf.DUMMYFUNCTION("importrange(""https://docs.google.com/spreadsheets/d/1NdaSGlewe3S15DWFefRKHC-Z0tqbjFNPLDNlxW-5Kck/edit#gid=314785295"",""Financials!B41"")*1000"),63766.7712618821) | I7: =(H7-G7)/G7 | J7: =IFERROR(__xludf.DUMMYFUNCTION("importrange(""https://docs.google.com/spreadsheets/d/1NdaSGlewe3S15DWFefRKHC-Z0tqbjFNPLDNlxW-5Kck/edit#gid=314785295"",""Financials!F2"")"),-0.368018065699869) | K7: =IFERROR(__xludf.DUMMYFUNCTION("importrange(""https://docs.google.com/spreadsheets/d/1NdaSGlewe3S15DWFefRKHC-Z0tqbjFNPLDNlxW-5Kck/edit#gid=314785295"",""Financials!D19"")"),-0.0563899279772207) | L7: =IFERROR(__xludf.DUMMYFUNCTION("IFERROR(googlefinance(D7,""pe""),"""")"),"") | M7: =IFERROR(__xludf.DUMMYFUNCTION("IFERROR(googlefinance(D7,""beta""),"""")"),"")
A8: 1 | B8: =HYPERLINK("https://finance.yahoo.com/quote/"&D8, C8) | C8: GameStop Corp. | D8: GME | E8: =IFERROR(__xludf.DUMMYFUNCTION("iferror(googlefinance(D8,""price""),"""")"),24.03) | F8: =IFERROR(__xludf.DUMMYFUNCTION("IFERROR(GOOGLEFINANCE(D8,""price"") / index(GOOGLEFINANCE(D8,""price"", datevalue(today()-365) ) , 2,2) - 1,"""")"),-0.0151639344262294) | G8: =IFERROR(__xludf.DUMMYFUNCTION("iferror(googlefinance(D8,""marketcap""),"""")/10^6"),10765.668592) | H8: =IFERROR(__xludf.DUMMYFUNCTION("IMPORTRANGE(""https://docs.google.com/spreadsheets/d/1L4yfv89QVUE9L_HHdbGE4xVtgtA9FIdzCOWtDZY6v_8/edit#gid=469363836"",""Summary!B34"")"),4338.4200830816) | I8: =(H8-G8)/G8 | J8: =IFERROR(__xludf.DUMMYFUNCTION("IMPORTRANGE(""https://docs.google.com/spreadsheets/d/1L4yfv89QVUE9L_HHdbGE4xVtgtA9FIdzCOWtDZY6v_8/edit#gid=469363836"",""Summary!I3"")"),-0.247560964024813) | K8: =IFERROR(__xludf.DUMMYFUNCTION("IMPORTRANGE(""https://docs.google.com/spreadsheets/d/1L4yfv89QVUE9L_HHdbGE4xVtgtA9FIdzCOWtDZY6v_8/edit#gid=469363836"",""Summary!H11"")"),0.377315136288459) | L8: =IFERROR(__xludf.DUMMYFUNCTION("IFERROR(googlefinance(D8,""pe""),"""")"),"") | M8: =IFERROR(__xludf.DUMMYFUNCTION("IFERROR(googlefinance(D8,""beta""),"""")"),"")
A9: =A8+1 | B9: =HYPERLINK("https://finance.yahoo.com/quote/"&D9, C9) | C9: Baidu Inc | D9: BIDU | E9: =IFERROR(__xludf.DUMMYFUNCTION("iferror(googlefinance(D9,""price""),"""")"),124.44) | F9: =IFERROR(__xludf.DUMMYFUNCTION("IFERROR(GOOGLEFINANCE(D9,""price"") / index(GOOGLEFINANCE(D9,""price"", datevalue(today()-365) ) , 2,2) - 1,"""")"),0.475806451612903) | G9: =IFERROR(__xludf.DUMMYFUNCTION("iferror(googlefinance(D9,""marketcap""),"""")/10^6"),42778.851635) | H9: =IFERROR(__xludf.DUMMYFUNCTION("IMPORTRANGE(""https://docs.google.com/spreadsheets/d/1IVS0z4Rl2pa89mr25nlgvj339ilU2tVdVu3j7nFXQIc/edit#gid=300601680"",""Summary!B87"")*1000"),68732.0998158358) | I9: =(H9-G9)/G9 | J9: =IFERROR(__xludf.DUMMYFUNCTION("IMPORTRANGE(""https://docs.google.com/spreadsheets/d/1IVS0z4Rl2pa89mr25nlgvj339ilU2tVdVu3j7nFXQIc/edit#gid=300601680"",""Summary!N2"")"),-0.028912676056338) | K9: =IFERROR(__xludf.DUMMYFUNCTION("IMPORTRANGE(""https://docs.google.com/spreadsheets/d/1IVS0z4Rl2pa89mr25nlgvj339ilU2tVdVu3j7nFXQIc/edit#gid=300601680"",""Summary!G38"")"),0.239090343630986) | L9: =IFERROR(__xludf.DUMMYFUNCTION("IFERROR(googlefinance(D9,""pe""),"""")"),"") | M9: =IFERROR(__xludf.DUMMYFUNCTION("IFERROR(googlefinance(D9,""beta""),"""")"),"")
A10: =A9+1 | B10: =HYPERLINK("https://finance.yahoo.com/quote/"&#REF!, C10) | C10: Southwest Airlines Co | E10: =IFERROR(__xludf.DUMMYFUNCTION("iferror(googlefinance(#REF!,""price""),"""")"),"") | F10: =IFERROR(__xludf.DUMMYFUNCTION("IFERROR(GOOGLEFINANCE(#REF!,""price"") / index(GOOGLEFINANCE(#REF!,""price"", datevalue(today()-365) ) , 2,2) - 1,"""")"),"") | G10: =IFERROR(__xludf.DUMMYFUNCTION("iferror(googlefinance(#REF!,""marketcap""),"""")/10^6"),0) | H10: =IFERROR(__xludf.DUMMYFUNCTION("importrange(""https://docs.google.com/spreadsheets/d/134U-14NIeFgI3O-C1JHtY0ItSiJlwkxRAneHpKC9G-c/edit#gid=893603675"",""Financials!B49"")*1000"),31298.0232402297) | I10: =(H10-G10)/G10 | K10: =IFERROR(__xludf.DUMMYFUNCTION("importrange(""https://docs.google.com/spreadsheets/d/134U-14NIeFgI3O-C1JHtY0ItSiJlwkxRAneHpKC9G-c/edit#gid=893603675"",""Financials!H16"")"),0.0984871957621025) | L10: =IFERROR(__xludf.DUMMYFUNCTION("IFERROR(googlefinance(#REF!,""pe""),"""")"),"") | M10: =IFERROR(__xludf.DUMMYFUNCTION("IFERROR(googlefinance(#REF!,""beta""),"""")"),"")
A11: =A10+1 | B11: =HYPERLINK("https://finance.yahoo.com/quote/"&D11, C11) | C11: American Airlines Group Inc | D11: AAL | E11: =IFERROR(__xludf.DUMMYFUNCTION("iferror(googlefinance(D11,""price""),"""")"),13.07) | F11: =IFERROR(__xludf.DUMMYFUNCTION("IFERROR(GOOGLEFINANCE(D11,""price"") / index(GOOGLEFINANCE(D11,""price"", datevalue(today()-365) ) , 2,2) - 1,"""")"),-0.0576784426820474) | G11: =IFERROR(__xludf.DUMMYFUNCTION("iferror(googlefinance(D11,""marketcap""),"""")/10^6"),8630.179613) | H11: =IFERROR(__xludf.DUMMYFUNCTION("importrange(""https://docs.google.com/spreadsheets/d/1Y-0VcPnHxxHb4ZZr1UWvNQuaZIkoxtvWgysgmaSL9Gs/edit#gid=1635501517"",""Financials!B48"")*1000"),14832.1796340825) | I11: =(H11-G11)/G11 | J11: =IFERROR(__xludf.DUMMYFUNCTION("importrange(""https://docs.google.com/spreadsheets/d/1Y-0VcPnHxxHb4ZZr1UWvNQuaZIkoxtvWgysgmaSL9Gs/edit#gid=1635501517"",""Financials!Q3"")"),0.0116950434413679) | K11: =IFERROR(__xludf.DUMMYFUNCTION("importrange(""https://docs.google.com/spreadsheets/d/1Y-0VcPnHxxHb4ZZr1UWvNQuaZIkoxtvWgysgmaSL9Gs/edit#gid=1635501517"",""Financials!M16"")"),0) | L11: =IFERROR(__xludf.DUMMYFUNCTION("IFERROR(googlefinance(D11,""pe""),"""")"),"") | M11: =IFERROR(__xludf.DUMMYFUNCTION("IFERROR(googlefinance(D11,""beta""),"""")"),"") | N11: =IFERROR(__xludf.DUMMYFUNCTION("IMPORTRANGE(""https://docs.google.com/spreadsheets/d/1zPx-sYL2WZELC72hI-Xc5oMEa-YaHSyQySKfbmi4y7s/edit#gid=303626986"",""Summary!I13"")"),32.23)
A12: =A11+1 | B12: =HYPERLINK("https://finance.yahoo.com/quote/"&D12, C12) | C12: Synchrony | D12: SYF | E12: =IFERROR(__xludf.DUMMYFUNCTION("iferror(googlefinance(D12,""price""),"""")"),69.11) | F12: =IFERROR(__xludf.DUMMYFUNCTION("IFERROR(GOOGLEFINANCE(D12,""price"") / index(GOOGLEFINANCE(D12,""price"", datevalue(today()-365) ) , 2,2) - 1,"""")"),0.191140985866942) | G12: =IFERROR(__xludf.DUMMYFUNCTION("iferror(googlefinance(D12,""marketcap""),"""")/10^6"),24022.373594) | H12: =IFERROR(__xludf.DUMMYFUNCTION("IMPORTRANGE(""https://docs.google.com/spreadsheets/d/1iemsJA0zDOHQP6QC15q0vMx_VbJPUq1by9erqpBNeOY/edit#gid=1736956277"",""SYF!C28"")"),47018.17007173) | I12: =(H12-G12)/G12 | J12: =IFERROR(__xludf.DUMMYFUNCTION("IMPORTRANGE(""https://docs.google.com/spreadsheets/d/1iemsJA0zDOHQP6QC15q0vMx_VbJPUq1by9erqpBNeOY/edit#gid=1736956277"",""SYF!M2"")"),20759) | K12: =IFERROR(__xludf.DUMMYFUNCTION("IMPORTRANGE(""https://docs.google.com/spreadsheets/d/1iemsJA0zDOHQP6QC15q0vMx_VbJPUq1by9erqpBNeOY/edit#gid=1736956277"",""SYF!I17"")"),0.111844152610941) | L12: =IFERROR(__xludf.DUMMYFUNCTION("IFERROR(googlefinance(D12,""pe""),"""")"),"") | M12: =IFERROR(__xludf.DUMMYFUNCTION("IFERROR(googlefinance(D12,""beta""),"""")"),"")
A13: =A12+1 | B13: =HYPERLINK("https://finance.yahoo.com/quote/"&D13, C13) | C13: JPMorgan Chase & Co. | D13: JPM | E13: =IFERROR(__xludf.DUMMYFUNCTION("iferror(googlefinance(D13,""price""),"""")"),300.3) | F13: =IFERROR(__xludf.DUMMYFUNCTION("IFERROR(GOOGLEFINANCE(D13,""price"") / index(GOOGLEFINANCE(D13,""price"", datevalue(today()-365) ) , 2,2) - 1,"""")"),0.15225232138746) | G13: =IFERROR(__xludf.DUMMYFUNCTION("iferror(googlefinance(D13,""marketcap""),"""")/10^6"),809918.676677) | H13: =IFERROR(__xludf.DUMMYFUNCTION("IMPORTRANGE(""https://docs.google.com/spreadsheets/d/18ffdmQve-35mEbb2ekY2flpF2A2bw2ki4JoC3jzdg1I/edit#gid=650781654"",""JPM!B1"")*1000"),426806.632058656) | I13: =(H13-G13)/G13 | J13: =IFERROR(__xludf.DUMMYFUNCTION("IMPORTRANGE(""https://docs.google.com/spreadsheets/d/18ffdmQve-35mEbb2ekY2flpF2A2bw2ki4JoC3jzdg1I/edit#gid=650781654"",""JPM!I53"")"),0.0265768375898362) | K13: =IFERROR(__xludf.DUMMYFUNCTION("IMPORTRANGE(""https://docs.google.com/spreadsheets/d/18ffdmQve-35mEbb2ekY2flpF2A2bw2ki4JoC3jzdg1I/edit#gid=650781654"",""JPM!H65"")"),0.262535804549283) | L13: =IFERROR(__xludf.DUMMYFUNCTION("G13/IMPORTRANGE(""https://docs.google.com/spreadsheets/d/18ffdmQve-35mEbb2ekY2flpF2A2bw2ki4JoC3jzdg1I/edit#gid=650781654"",""JPM!H55"")"),33.3423357077518) | M13: =IFERROR(__xludf.DUMMYFUNCTION("IFERROR(googlefinance(D13,""beta""),"""")"),"")
A14: =A13+1 | B14: =HYPERLINK("https://finance.yahoo.com/quote/"&D14, C14) | C14: United Airlines Holdings Inc | D14: UAL | E14: =IFERROR(__xludf.DUMMYFUNCTION("iferror(googlefinance(D14,""price""),"""")"),106.3) | F14: =IFERROR(__xludf.DUMMYFUNCTION("IFERROR(GOOGLEFINANCE(D14,""price"") / index(GOOGLEFINANCE(D14,""price"", datevalue(today()-365) ) , 2,2) - 1,"""")"),0.159594196574669) | G14: =IFERROR(__xludf.DUMMYFUNCTION("iferror(googlefinance(D14,""marketcap""),"""")/10^6"),34380.641877) | H14: =IFERROR(__xludf.DUMMYFUNCTION("importrange(""https://docs.google.com/spreadsheets/d/1E88W75oZAuEU3j_FKIjWcy8x6xr33WZ1jtcDeEarqCM/edit#gid=1816187640"",""Summary!B27"")"),21653.5369773099) | I14: =(H14-G14)/G14 | J14: =IFERROR(__xludf.DUMMYFUNCTION("importrange(""https://docs.google.com/spreadsheets/d/1E88W75oZAuEU3j_FKIjWcy8x6xr33WZ1jtcDeEarqCM/edit#gid=1816187640"",""Summary!F2"")"),-0.352566585956416) | K14: =IFERROR(__xludf.DUMMYFUNCTION("importrange(""https://docs.google.com/spreadsheets/d/1E88W75oZAuEU3j_FKIjWcy8x6xr33WZ1jtcDeEarqCM/edit#gid=1816187640"",""Summary!D14"")"),0.0994243972352574) | L14: =IFERROR(__xludf.DUMMYFUNCTION("IFERROR(googlefinance(D14,""pe""),"""")"),"") | M14: =IFERROR(__xludf.DUMMYFUNCTION("IFERROR(googlefinance(D14,""beta""),"""")"),"")
A15: =A14+1 | B15: =HYPERLINK("https://finance.yahoo.com/quote/"&D15, C15) | C15: U.S. Bancorp | D15: USB | E15: =IFERROR(__xludf.DUMMYFUNCTION("iferror(googlefinance(D15,""price""),"""")"),54.66) | F15: =IFERROR(__xludf.DUMMYFUNCTION("IFERROR(GOOGLEFINANCE(D15,""price"") / index(GOOGLEFINANCE(D15,""price"", datevalue(today()-365) ) , 2,2) - 1,"""")"),0.182093425605536) | G15: =IFERROR(__xludf.DUMMYFUNCTION("iferror(googlefinance(D15,""marketcap""),"""")/10^6"),84924.968462) | H15: =IFERROR(__xludf.DUMMYFUNCTION("IMPORTRANGE(""https://docs.google.com/spreadsheets/d/1BkE_9jEXhHz4aashYd9x7c-jGM6MGTH38F1LR9rqUwQ/edit#gid=467477759"",""Summary!C29"")"),120236.19642455) | I15: =(H15-G15)/G15 | J15: =IFERROR(__xludf.DUMMYFUNCTION("IMPORTRANGE(""https://docs.google.com/spreadsheets/d/1BkE_9jEXhHz4aashYd9x7c-jGM6MGTH38F1LR9rqUwQ/edit#gid=467477759"",""Summary!M2"")"),0.225660439470002) | K15: =IFERROR(__xludf.DUMMYFUNCTION("IMPORTRANGE(""https://docs.google.com/spreadsheets/d/1BkE_9jEXhHz4aashYd9x7c-jGM6MGTH38F1LR9rqUwQ/edit#gid=467477759"",""Summary!I19"")"),0.212604501607717) | L15: =IFERROR(__xludf.DUMMYFUNCTION("IFERROR(googlefinance(D15,""pe""),"""")"),"") | M15: =IFERROR(__xludf.DUMMYFUNCTION("IFERROR(googlefinance(D15,""beta""),"""")"),"") | N15: =IFERROR(__xludf.DUMMYFUNCTION("IMPORTRANGE(""https://docs.google.com/spreadsheets/d/18ffdmQve-35mEbb2ekY2flpF2A2bw2ki4JoC3jzdg1I/edit#gid=650781654"",""JPM!H72"")"),61.76)
A16: =A15+1 | B16: =HYPERLINK("https://finance.yahoo.com/quote/"&D16, C16) | C16: Bank of America Corp | D16: BAC | E16: =IFERROR(__xludf.DUMMYFUNCTION("iferror(googlefinance(D16,""price""),"""")"),49.83) | F16: =IFERROR(__xludf.DUMMYFUNCTION("IFERROR(GOOGLEFINANCE(D16,""price"") / index(GOOGLEFINANCE(D16,""price"", datevalue(today()-365) ) , 2,2) - 1,"""")"),0.0937225636523264) | G16: =IFERROR(__xludf.DUMMYFUNCTION("iferror(googlefinance(D16,""marketcap""),"""")/10^6"),357614.0772) | H16: =IFERROR(__xludf.DUMMYFUNCTION("IMPORTRANGE(""https://docs.google.com/spreadsheets/d/1ajry6MlMHVl1AsbljgX5BXpRLc8MVU1N9Z23HIyADoU/edit#gid=1672282254"",""Summary!B73"")"),258602.069066145) | I16: =(H16-G16)/G16 | J16: =IFERROR(__xludf.DUMMYFUNCTION("IMPORTRANGE(""https://docs.google.com/spreadsheets/d/1ajry6MlMHVl1AsbljgX5BXpRLc8MVU1N9Z23HIyADoU/edit#gid=1672282254"",""Summary!K48"")"),-0.01889645632832) | K16: =IFERROR(__xludf.DUMMYFUNCTION("IMPORTRANGE(""https://docs.google.com/spreadsheets/d/1ajry6MlMHVl1AsbljgX5BXpRLc8MVU1N9Z23HIyADoU/edit#gid=1672282254"",""Summary!I64"")"),0.21958338706085) | L16: =IFERROR(__xludf.DUMMYFUNCTION("IFERROR(googlefinance(D16,""pe""),"""")"),"") | M16: =IFERROR(__xludf.DUMMYFUNCTION("IFERROR(googlefinance(D16,""beta""),"""")"),"") | N16: =IFERROR(__xludf.DUMMYFUNCTION("IMPORTRANGE(""https://docs.google.com/spreadsheets/d/1BkE_9jEXhHz4aashYd9x7c-jGM6MGTH38F1LR9rqUwQ/edit#gid=467477759"",""Summary!I21"")"),30.24)
A17: =A16+1 | B17: =HYPERLINK("https://finance.yahoo.com/quote/"&D17, C17) | C17: Delta Air Lines, Inc. | D17: DAL | E17: =IFERROR(__xludf.DUMMYFUNCTION("iferror(googlefinance(D17,""price""),"""")"),65.7) | F17: =IFERROR(__xludf.DUMMYFUNCTION("IFERROR(GOOGLEFINANCE(D17,""price"") / index(GOOGLEFINANCE(D17,""price"", datevalue(today()-365) ) , 2,2) - 1,"""")"),0.124037639007698) | G17: =IFERROR(__xludf.DUMMYFUNCTION("iferror(googlefinance(D17,""marketcap""),"""")/10^6"),42910.684996) | H17: =IFERROR(__xludf.DUMMYFUNCTION("IMPORTRANGE(""https://docs.google.com/spreadsheets/d/1Z6RobysQCGMiI-pRQ6lMweET1m6J6B9TgwscNtCNb1g/edit#gid=428240719"",""Financials!B46"")*1000"),3385.90206884782) | I17: =(H17-G17)/G17 | J17: =IFERROR(__xludf.DUMMYFUNCTION("IMPORTRANGE(""https://docs.google.com/spreadsheets/d/1Z6RobysQCGMiI-pRQ6lMweET1m6J6B9TgwscNtCNb1g/edit#gid=428240719"",""Financials!I3"")"),-0.636330759248622) | K17: =IFERROR(__xludf.DUMMYFUNCTION("IMPORTRANGE(""https://docs.google.com/spreadsheets/d/1Z6RobysQCGMiI-pRQ6lMweET1m6J6B9TgwscNtCNb1g/edit#gid=428240719"",""Financials!H16"")"),-0.72939455981281) | L17: =IFERROR(__xludf.DUMMYFUNCTION("IFERROR(googlefinance(D17,""pe""),"""")"),"") | M17: =IFERROR(__xludf.DUMMYFUNCTION("IFERROR(googlefinance(D17,""beta""),"""")"),"") | N17: =IFERROR(__xludf.DUMMYFUNCTION("IMPORTRANGE(""https://docs.google.com/spreadsheets/d/1ajry6MlMHVl1AsbljgX5BXpRLc8MVU1N9Z23HIyADoU/edit#gid=1672282254"",""Summary!I59"")"),19.9)
A18: =A17+1 | B18: =HYPERLINK("https://finance.yahoo.com/quote/"&D18, C18) | C18: Kraft Heinz Co | D18: KHC | E18: =IFERROR(__xludf.DUMMYFUNCTION("iferror(googlefinance(D18,""price""),"""")"),24.61) | F18: =IFERROR(__xludf.DUMMYFUNCTION("IFERROR(GOOGLEFINANCE(D18,""price"") / index(GOOGLEFINANCE(D18,""price"", datevalue(today()-365) ) , 2,2) - 1,"""")"),-0.214240102171136) | G18: =IFERROR(__xludf.DUMMYFUNCTION("iferror(googlefinance(D18,""marketcap""),"""")/10^6"),29131.940562) | H18: =IFERROR(__xludf.DUMMYFUNCTION("IMPORTRANGE(""https://docs.google.com/spreadsheets/d/1QoccdSVrkp1XvlXW4dlFxIR8583ws9aFmqE3W8dNEWw/edit#gid=254823806"",""Summary!B25"")"),38077.3874469667) | I18: =(H18-G18)/G18 | J18: =IFERROR(__xludf.DUMMYFUNCTION("IMPORTRANGE(""https://docs.google.com/spreadsheets/d/1QoccdSVrkp1XvlXW4dlFxIR8583ws9aFmqE3W8dNEWw/edit#gid=254823806"",""Summary!H2"")"),0.0362039335497422) | K18: =IFERROR(__xludf.DUMMYFUNCTION("IMPORTRANGE(""https://docs.google.com/spreadsheets/d/1QoccdSVrkp1XvlXW4dlFxIR8583ws9aFmqE3W8dNEWw/edit#gid=254823806"",""Summary!F18"")"),0.0812679014703074) | L18: =IFERROR(__xludf.DUMMYFUNCTION("IFERROR(googlefinance(D18,""pe""),"""")"),"") | M18: =IFERROR(__xludf.DUMMYFUNCTION("IFERROR(googlefinance(D18,""beta""),"""")"),"")
A19: =A18+1 | B19: =HYPERLINK("https://finance.yahoo.com/quote/"&D19, C19) | C19: VANGUARD IX FUN/S&P 500 ETF SHS NEW | D19: VOO | E19: =IFERROR(__xludf.DUMMYFUNCTION("iferror(googlefinance(D19,""price""),"""")"),631.04) | F19: =IFERROR(__xludf.DUMMYFUNCTION("IFERROR(GOOGLEFINANCE(D19,""price"") / index(GOOGLEFINANCE(D19,""price"", datevalue(today()-365) ) , 2,2) - 1,"""")"),0.175296133502197) | G19: =IFERROR(__xludf.DUMMYFUNCTION("iferror(googlefinance(D19,""marketcap""),"""")/10^6"),0) | I19: 0 | L19: =IFERROR(__xludf.DUMMYFUNCTION("IFERROR(googlefinance(D19,""pe""),"""")"),"") | M19: =IFERROR(__xludf.DUMMYFUNCTION("IFERROR(googlefinance(D19,""beta""),"""")"),"")
A20: =A19+1 | B20: =HYPERLINK("https://finance.yahoo.com/quote/"&D20, C20) | C20: Wells Fargo & Co | D20: WFC | E20: =IFERROR(__xludf.DUMMYFUNCTION("iferror(googlefinance(D20,""price""),"""")"),81.45) | F20: =IFERROR(__xludf.DUMMYFUNCTION("IFERROR(GOOGLEFINANCE(D20,""price"") / index(GOOGLEFINANCE(D20,""price"", datevalue(today()-365) ) , 2,2) - 1,"""")"),0.0573802414643644) | G20: =IFERROR(__xludf.DUMMYFUNCTION("iferror(googlefinance(D20,""marketcap""),"""")/10^6"),251324.879883) | H20: =IFERROR(__xludf.DUMMYFUNCTION("IMPORTRANGE(""https://docs.google.com/spreadsheets/d/1zPx-sYL2WZELC72hI-Xc5oMEa-YaHSyQySKfbmi4y7s/edit#gid=303626986"",""Summary!C31"")"),263669.218435059) | I20: =(H20-G20)/G20 | J20: =IFERROR(__xludf.DUMMYFUNCTION("IMPORTRANGE(""https://docs.google.com/spreadsheets/d/1zPx-sYL2WZELC72hI-Xc5oMEa-YaHSyQySKfbmi4y7s/edit#gid=303626986"",""Summary!K2"")"),0.0510920652474426) | K20: =IFERROR(__xludf.DUMMYFUNCTION("IMPORTRANGE(""https://docs.google.com/spreadsheets/d/1zPx-sYL2WZELC72hI-Xc5oMEa-YaHSyQySKfbmi4y7s/edit#gid=303626986"",""Summary!I18"")"),0.00803151783245783) | L20: =IFERROR(__xludf.DUMMYFUNCTION("IFERROR(googlefinance(D20,""pe""),"""")"),"") | M20: =IFERROR(__xludf.DUMMYFUNCTION("IFERROR(googlefinance(D20,""beta""),"""")"),"")
A21: =A20+1 | B21: =HYPERLINK("https://finance.yahoo.com/quote/"&D21, C21) | C21: Berkshire Hathaway Inc. Class B | D21: BRK.B | E21: =IFERROR(__xludf.DUMMYFUNCTION("iferror(googlefinance(D21,""price""),"""")"),504.95) | F21: =IFERROR(__xludf.DUMMYFUNCTION("IFERROR(GOOGLEFINANCE(D21,""price"") / index(GOOGLEFINANCE(D21,""price"", datevalue(today()-365) ) , 2,2) - 1,"""")"),-0.0100572459222082) | G21: =IFERROR(__xludf.DUMMYFUNCTION("iferror(googlefinance(D21,""marketcap""),"""")/10^6"),1089429.737) | H21: =IFERROR(__xludf.DUMMYFUNCTION("IMPORTRANGE(""https://docs.google.com/spreadsheets/d/1tZBWcuxGf2na1a_8BX668tEyP4ZXHcAPPbDukT46GvY/edit#gid=105525789"",""Summary!B41"")"),808581.73454059) | I21: =(H21-G21)/G21 | J21: =IFERROR(__xludf.DUMMYFUNCTION("IMPORTRANGE(""https://docs.google.com/spreadsheets/d/1tZBWcuxGf2na1a_8BX668tEyP4ZXHcAPPbDukT46GvY/edit#gid=105525789"",""Summary!L2"")"),365632) | K21: =IFERROR(__xludf.DUMMYFUNCTION("IMPORTRANGE(""https://docs.google.com/spreadsheets/d/1tZBWcuxGf2na1a_8BX668tEyP4ZXHcAPPbDukT46GvY/edit#gid=105525789"",""Summary!H29"")"),0.0892020691621522) | L21: =IFERROR(__xludf.DUMMYFUNCTION("IFERROR(googlefinance(D21,""pe""),"""")"),"") | M21: =IFERROR(__xludf.DUMMYFUNCTION("IFERROR(googlefinance(D21,""beta""),"""")"),"")
A22: =A21+1 | B22: =HYPERLINK("https://finance.yahoo.com/quote/"&D22, C22) | C22: Apple Inc. | D22: AAPL | E22: =IFERROR(__xludf.DUMMYFUNCTION("iferror(googlefinance(D22,""price""),"""")"),264.18) | F22: =IFERROR(__xludf.DUMMYFUNCTION("IFERROR(GOOGLEFINANCE(D22,""price"") / index(GOOGLEFINANCE(D22,""price"", datevalue(today()-365) ) , 2,2) - 1,"""")"),0.109860101667857) | G22: =IFERROR(__xludf.DUMMYFUNCTION("iferror(googlefinance(D22,""marketcap""),"""")/10^6"),3884159.178314) | H22: =IFERROR(__xludf.DUMMYFUNCTION("IMPORTRANGE(""https://docs.google.com/spreadsheets/d/1NuuuuRncvZrOMOsu3B716qUsqv19xrPgc9ljJgJ3oUU/edit#gid=1975317421"",""Summary!B34"")"),1020704.71323773) | I22: =(H22-G22)/G22 | J22: =IFERROR(__xludf.DUMMYFUNCTION("IMPORTRANGE(""https://docs.google.com/spreadsheets/d/1NuuuuRncvZrOMOsu3B716qUsqv19xrPgc9ljJgJ3oUU/edit#gid=1975317421"",""Summary!F2"")"),0.0525917270749575) | K22: =IFERROR(__xludf.DUMMYFUNCTION("IMPORTRANGE(""https://docs.google.com/spreadsheets/d/1NuuuuRncvZrOMOsu3B716qUsqv19xrPgc9ljJgJ3oUU/edit#gid=1975317421"",""Summary!E20"")"),0.249462310621966) | L22: =IFERROR(__xludf.DUMMYFUNCTION("IFERROR(googlefinance(D22,""pe""),"""")"),"") | M22: =IFERROR(__xludf.DUMMYFUNCTION("IFERROR(googlefinance(D22,""beta""),"""")"),"")
A23: =A22+1 | B23: =HYPERLINK("https://finance.yahoo.com/quote/"&D23, C23) | C23: TotalEnergies SE | D23: TTE | E23: =IFERROR(__xludf.DUMMYFUNCTION("iferror(googlefinance(D23,""price""),"""")"),80.34) | F23: =IFERROR(__xludf.DUMMYFUNCTION("IFERROR(GOOGLEFINANCE(D23,""price"") / index(GOOGLEFINANCE(D23,""price"", datevalue(today()-365) ) , 2,2) - 1,"""")"),0.337439653737306) | G23: =IFERROR(__xludf.DUMMYFUNCTION("iferror(googlefinance(D23,""marketcap""),"""")/10^6"),177141.336565) | H23: =IFERROR(__xludf.DUMMYFUNCTION("IMPORTRANGE(""https://docs.google.com/spreadsheets/d/1mU5D8jxgWAnX--xBp56WIFjKkjv6_AK_aK6kbd_IxYE/edit#gid=1186441318"",""Summary!C58"")"),103710.452849875) | I23: =(H23-G23)/G23 | J23: =IFERROR(__xludf.DUMMYFUNCTION("IMPORTRANGE(""https://docs.google.com/spreadsheets/d/1mU5D8jxgWAnX--xBp56WIFjKkjv6_AK_aK6kbd_IxYE/edit#gid=1186441318"",""Summary!I26"")"),184630) | K23: =IFERROR(__xludf.DUMMYFUNCTION("IMPORTRANGE(""https://docs.google.com/spreadsheets/d/1mU5D8jxgWAnX--xBp56WIFjKkjv6_AK_aK6kbd_IxYE/edit#gid=1186441318"",""Summary!G48"")"),-0.05147670327327) | L23: =IFERROR(__xludf.DUMMYFUNCTION("IFERROR(googlefinance(D23,""pe""),"""")"),"") | M23: =IFERROR(__xludf.DUMMYFUNCTION("IFERROR(googlefinance(D23,""beta""),"""")"),"")
A24: =A23+1 | B24: =HYPERLINK("https://finance.yahoo.com/quote/"&D24, C24) | C24: Capital Product Partners L.P. | D24: CPLP | E24: =IFERROR(__xludf.DUMMYFUNCTION("iferror(googlefinance(D24,""price""),"""")"),"") | F24: =IFERROR(__xludf.DUMMYFUNCTION("IFERROR(GOOGLEFINANCE(D24,""price"") / index(GOOGLEFINANCE(D24,""price"", datevalue(today()-365) ) , 2,2) - 1,"""")"),"") | G24: =IFERROR(__xludf.DUMMYFUNCTION("iferror(googlefinance(D24,""marketcap""),"""")/10^6"),0) | H24: =IFERROR(__xludf.DUMMYFUNCTION("IMPORTRANGE(""https://docs.google.com/spreadsheets/d/1kl2650HmVB8eKAI4aW3PYUJGx0ZK4DWMgpwRB8Fac_c/edit#gid=87393437"",""Summary!B28"")"),842.853988286684) | I24: =(H24-G24)/G24 | J24: =IFERROR(__xludf.DUMMYFUNCTION("IMPORTRANGE(""https://docs.google.com/spreadsheets/d/1kl2650HmVB8eKAI4aW3PYUJGx0ZK4DWMgpwRB8Fac_c/edit#gid=87393437"",""Summary!J2"")"),342.692) | K24: =IFERROR(__xludf.DUMMYFUNCTION("IMPORTRANGE(""https://docs.google.com/spreadsheets/d/1kl2650HmVB8eKAI4aW3PYUJGx0ZK4DWMgpwRB8Fac_c/edit#gid=87393437"",""Summary!E16"")"),0.211613956625137) | L24: =IFERROR(__xludf.DUMMYFUNCTION("IFERROR(googlefinance(D24,""pe""),"""")"),"") | M24: =IFERROR(__xludf.DUMMYFUNCTION("IFERROR(googlefinance(D24,""beta""),"""")"),"")
A25: =A24+1 | B25: =HYPERLINK("https://finance.yahoo.com/quote/"&D25, C25) | C25: Occidental Petroleum Corporation | D25: OXY | E25: =IFERROR(__xludf.DUMMYFUNCTION("iferror(googlefinance(D25,""price""),"""")"),53.08) | F25: =IFERROR(__xludf.DUMMYFUNCTION("IFERROR(GOOGLEFINANCE(D25,""price"") / index(GOOGLEFINANCE(D25,""price"", datevalue(today()-365) ) , 2,2) - 1,"""")"),0.142734122712594) | G25: =IFERROR(__xludf.DUMMYFUNCTION("iferror(googlefinance(D25,""marketcap""),"""")/10^6"),52351.038241) | H25: =IFERROR(__xludf.DUMMYFUNCTION("importrange(""https://docs.google.com/spreadsheets/d/11j3ALnRBR3BKHGi2K9B3sAM9ODJYyy8euIH2EYSIsnI/edit#gid=1513331917"",""OXY!B50"")*1000"),56267.2195148696) | I25: =(H25-G25)/G25 | J25: =IFERROR(__xludf.DUMMYFUNCTION("importrange(""https://docs.google.com/spreadsheets/d/11j3ALnRBR3BKHGi2K9B3sAM9ODJYyy8euIH2EYSIsnI/edit#gid=1513331917"",""OXY!M2"")"),21593) | K25: =IFERROR(__xludf.DUMMYFUNCTION("importrange(""https://docs.google.com/spreadsheets/d/11j3ALnRBR3BKHGi2K9B3sAM9ODJYyy8euIH2EYSIsnI/edit#gid=1513331917"",""OXY!H26"")"),-0.000881857487787074) | L25: =IFERROR(__xludf.DUMMYFUNCTION("IFERROR(googlefinance(D25,""pe""),"""")"),"") | M25: =IFERROR(__xludf.DUMMYFUNCTION("IFERROR(googlefinance(D25,""beta""),"""")"),"")
A26: =A25+1 | B26: =HYPERLINK("https://finance.yahoo.com/quote/"&D26, C26) | C26: Suncor Energy Inc. | D26: SU | E26: =IFERROR(__xludf.DUMMYFUNCTION("iferror(googlefinance(D26,""price""),"""")"),56.52) | F26: =IFERROR(__xludf.DUMMYFUNCTION("IFERROR(GOOGLEFINANCE(D26,""price"") / index(GOOGLEFINANCE(D26,""price"", datevalue(today()-365) ) , 2,2) - 1,"""")"),0.561757391544625) | G26: =IFERROR(__xludf.DUMMYFUNCTION("iferror(googlefinance(D26,""marketcap""),"""")/10^6"),67272.591424) | H26: =IFERROR(__xludf.DUMMYFUNCTION("importrange(""https://docs.google.com/spreadsheets/d/10OMzBR1Fr-0UWX4RkucmriJ6cc8Zs05zUfFXAYGqaYg/edit#gid=1507715394"",""Financials!B42"")*1000"),19070.5553148654) | I26: =(H26-G26)/G26 | J26: =IFERROR(__xludf.DUMMYFUNCTION("importrange(""https://docs.google.com/spreadsheets/d/10OMzBR1Fr-0UWX4RkucmriJ6cc8Zs05zUfFXAYGqaYg/edit#gid=1507715394"",""Financials!I5"")"),-0.666666666666666) | K26: =IFERROR(__xludf.DUMMYFUNCTION("importrange(""https://docs.google.com/spreadsheets/d/10OMzBR1Fr-0UWX4RkucmriJ6cc8Zs05zUfFXAYGqaYg/edit#gid=1507715394"",""Financials!G22"")"),0.158738642437199) | L26: =IFERROR(__xludf.DUMMYFUNCTION("IFERROR(googlefinance(D26,""pe""),"""")"),"") | M26: =IFERROR(__xludf.DUMMYFUNCTION("IFERROR(googlefinance(D26,""beta""),"""")"),"")
A27: =A26+1 | B27: =HYPERLINK("https://finance.yahoo.com/quote/"&D27, C27) | C27: Western Midstream Partners LP | D27: WES | E27: =IFERROR(__xludf.DUMMYFUNCTION("iferror(googlefinance(D27,""price""),"""")"),41.59) | F27: =IFERROR(__xludf.DUMMYFUNCTION("IFERROR(GOOGLEFINANCE(D27,""price"") / index(GOOGLEFINANCE(D27,""price"", datevalue(today()-365) ) , 2,2) - 1,"""")"),0.0537116797567773) | G27: =IFERROR(__xludf.DUMMYFUNCTION("iferror(googlefinance(D27,""marketcap""),"""")/10^6"),16372.627226) | H27: =IFERROR(__xludf.DUMMYFUNCTION("importrange(""https://docs.google.com/spreadsheets/d/1TVqA7MehmxEyS2xPogFAxn7w_OiM0llWV7V7QxYNm1Y/edit#gid=692269516"",""WES!B37"")*1000"),1173.9724833648) | I27: =(H27-G27)/G27 | J27: =IFERROR(__xludf.DUMMYFUNCTION("importrange(""https://docs.google.com/spreadsheets/d/1TVqA7MehmxEyS2xPogFAxn7w_OiM0llWV7V7QxYNm1Y/edit#gid=692269516"",""WES!H2"")"),0.296682972612843) | K27: =IFERROR(__xludf.DUMMYFUNCTION("importrange(""https://docs.google.com/spreadsheets/d/1TVqA7MehmxEyS2xPogFAxn7w_OiM0llWV7V7QxYNm1Y/edit#gid=692269516"",""WES!B17"")"),0.245419464133973) | L27: =IFERROR(__xludf.DUMMYFUNCTION("IFERROR(googlefinance(D27,""pe""),"""")"),"") | M27: =IFERROR(__xludf.DUMMYFUNCTION("IFERROR(googlefinance(D27,""beta""),"""")"),"")
A28: =A27+1 | B28: =HYPERLINK("https://finance.yahoo.com/quote/"&D28, C28) | C28: PNC Financial Services Group Inc | D28: PNC | E28: =IFERROR(__xludf.DUMMYFUNCTION("iferror(googlefinance(D28,""price""),"""")"),212.35) | F28: =IFERROR(__xludf.DUMMYFUNCTION("IFERROR(GOOGLEFINANCE(D28,""price"") / index(GOOGLEFINANCE(D28,""price"", datevalue(today()-365) ) , 2,2) - 1,"""")"),0.120639611589002) | G28: =IFERROR(__xludf.DUMMYFUNCTION("iferror(googlefinance(D28,""marketcap""),"""")/10^6"),85655.813076) | H28: =IFERROR(__xludf.DUMMYFUNCTION("importrange(""https://docs.google.com/spreadsheets/d/1reQ8upYIYmCrro_8afTKwl6jD0hb8jsQOtumLTkmqvM/edit#gid=544878967"",""Financials!B24"")*1000"),85346.4025626145) | I28: =(H28-G28)/G28 | J28: =IFERROR(__xludf.DUMMYFUNCTION("importrange(""https://docs.google.com/spreadsheets/d/1reQ8upYIYmCrro_8afTKwl6jD0hb8jsQOtumLTkmqvM/edit#gid=544878967"",""Financials!H28"")"),0.0203062769955685) | K28: =IFERROR(__xludf.DUMMYFUNCTION("importrange(""https://docs.google.com/spreadsheets/d/1reQ8upYIYmCrro_8afTKwl6jD0hb8jsQOtumLTkmqvM/edit#gid=544878967"",""Financials!G44"")"),0.0343614272362416) | L28: =IFERROR(__xludf.DUMMYFUNCTION("IFERROR(googlefinance(D28,""pe""),"""")"),"") | M28: =IFERROR(__xludf.DUMMYFUNCTION("IFERROR(googlefinance(D28,""beta""),"""")"),"") | N28: =IFERROR(__xludf.DUMMYFUNCTION("importrange(""https://docs.google.com/spreadsheets/d/1reQ8upYIYmCrro_8afTKwl6jD0hb8jsQOtumLTkmqvM/edit#gid=544878967"",""Financials!G42"")"),93.54)
A29: =A28+1 | B29: =HYPERLINK("https://finance.yahoo.com/quote/"&D29, C29) | C29: Silvergate Capital Corporation | D29: SI | E29: =IFERROR(__xludf.DUMMYFUNCTION("iferror(googlefinance(D29,""price""),"""")"),13.56) | F29: =IFERROR(__xludf.DUMMYFUNCTION("IFERROR(GOOGLEFINANCE(D29,""price"") / index(GOOGLEFINANCE(D29,""price"", datevalue(today()-365) ) , 2,2) - 1,"""")"),"") | G29: =IFERROR(__xludf.DUMMYFUNCTION("iferror(googlefinance(D29,""marketcap""),"""")/10^6"),279.358789) | H29: =IFERROR(__xludf.DUMMYFUNCTION("importrange(""https://docs.google.com/spreadsheets/d/1YFzudXBMN9O6LHJPHlI2Fee6KTcJLlI_a4y-R0kc6D8/edit#gid=429640807"",""Si!B36"")"),309.646082557911) | I29: =(H29-G29)/G29 | J29: =IFERROR(__xludf.DUMMYFUNCTION("importrange(""https://docs.google.com/spreadsheets/d/1YFzudXBMN9O6LHJPHlI2Fee6KTcJLlI_a4y-R0kc6D8/edit#gid=429640807"",""Si!I2"")"),-0.318425925925925) | K29: =IFERROR(__xludf.DUMMYFUNCTION("importrange(""https://docs.google.com/spreadsheets/d/1YFzudXBMN9O6LHJPHlI2Fee6KTcJLlI_a4y-R0kc6D8/edit#gid=429640807"",""Si!B18"")"),0.0686048091291944) | L29: =IFERROR(__xludf.DUMMYFUNCTION("IFERROR(googlefinance(D29,""pe""),"""")"),"") | M29: =IFERROR(__xludf.DUMMYFUNCTION("IFERROR(googlefinance(D29,""beta""),"""")"),"")
A30: =A29+1 | B30: =HYPERLINK("https://finance.yahoo.com/quote/"&D30, C30) | C30: Alphabet Inc Class A | D30: GOOGL | E30: =IFERROR(__xludf.DUMMYFUNCTION("iferror(googlefinance(D30,""price""),"""")"),311.76) | F30: =IFERROR(__xludf.DUMMYFUNCTION("IFERROR(GOOGLEFINANCE(D30,""price"") / index(GOOGLEFINANCE(D30,""price"", datevalue(today()-365) ) , 2,2) - 1,"""")"),0.86671456798994) | G30: =IFERROR(__xludf.DUMMYFUNCTION("iferror(googlefinance(D30,""marketcap""),"""")/10^6"),3772448.880568) | H30: =IFERROR(__xludf.DUMMYFUNCTION("importrange(""https://docs.google.com/spreadsheets/d/1iAF7jMo93TaexbWSxBYGJ0tOkaL3h1mOkFPQL7_eiwc/edit?usp=sharing"",""Summary!B38"")"),2954821.64786503) | I30: =(H30-G30)/G30 | J30: =IFERROR(__xludf.DUMMYFUNCTION("importrange(""https://docs.google.com/spreadsheets/d/1iAF7jMo93TaexbWSxBYGJ0tOkaL3h1mOkFPQL7_eiwc/edit?usp=sharing"",""Summary!Q2"")"),0.143049786011005) | L30: =IFERROR(__xludf.DUMMYFUNCTION("IFERROR(googlefinance(D30,""pe""),"""")"),"") | M30: =IFERROR(__xludf.DUMMYFUNCTION("IFERROR(googlefinance(D30,""beta""),"""")"),"")
A31: =A30+1 | B31: =HYPERLINK("https://finance.yahoo.com/quote/"&D31, C31) | C31: Amazon.com, Inc. | D31: AMZN | E31: =IFERROR(__xludf.DUMMYFUNCTION("iferror(googlefinance(D31,""price""),"""")"),210) | F31: =IFERROR(__xludf.DUMMYFUNCTION("IFERROR(GOOGLEFINANCE(D31,""price"") / index(GOOGLEFINANCE(D31,""price"", datevalue(today()-365) ) , 2,2) - 1,"""")"),0.0242903131401814) | G31: =IFERROR(__xludf.DUMMYFUNCTION("iferror(googlefinance(D31,""marketcap""),"""")/10^6"),2254333.2) | H31: =IFERROR(__xludf.DUMMYFUNCTION("importrange(""https://docs.google.com/spreadsheets/d/17ZFyNeH7OiIizNcbhItyGFR-iS15ex-5EH0Bkr_P-5Y/edit#gid=2037953563"",""Summary!C20"")"),308018.29857362) | I31: =(H31-G31)/G31 | J31: =IFERROR(__xludf.DUMMYFUNCTION("importrange(""https://docs.google.com/spreadsheets/d/17ZFyNeH7OiIizNcbhItyGFR-iS15ex-5EH0Bkr_P-5Y/edit#gid=2037953563"",""Summary!S21"")"),0.0939951726398508) | K31: =IFERROR(__xludf.DUMMYFUNCTION("importrange(""https://docs.google.com/spreadsheets/d/17ZFyNeH7OiIizNcbhItyGFR-iS15ex-5EH0Bkr_P-5Y/edit#gid=2037953563"",""Summary!P41"")"),0.0552524969953168) | L31: =IFERROR(__xludf.DUMMYFUNCTION("IFERROR(googlefinance(D31,""pe""),"""")"),"") | M31: =IFERROR(__xludf.DUMMYFUNCTION("IFERROR(googlefinance(D31,""beta""),"""")"),"")
A32: =A31+1 | B32: =HYPERLINK("https://finance.yahoo.com/quote/"&D32, C32) | C32: Microsoft Corporation | D32: MSFT | E32: =IFERROR(__xludf.DUMMYFUNCTION("iferror(googlefinance(D32,""price""),"""")"),392.74) | F32: =IFERROR(__xludf.DUMMYFUNCTION("IFERROR(GOOGLEFINANCE(D32,""price"") / index(GOOGLEFINANCE(D32,""price"", datevalue(today()-365) ) , 2,2) - 1,"""")"),0.0109397925300522) | G32: =IFERROR(__xludf.DUMMYFUNCTION("iferror(googlefinance(D32,""marketcap""),"""")/10^6"),2916341.460944) | H32: =IFERROR(__xludf.DUMMYFUNCTION("importrange(""https://docs.google.com/spreadsheets/d/1-0wE4FJcTwa8HIXiUmKh_2bax-86FCPaaGwzK8mYxjE/edit#gid=644621603"",""MSFT!B37"")*1000"),1430442.87045515) | I32: =(H32-G32)/G32 | J32: =IFERROR(__xludf.DUMMYFUNCTION("importrange(""https://docs.google.com/spreadsheets/d/1-0wE4FJcTwa8HIXiUmKh_2bax-86FCPaaGwzK8mYxjE/edit#gid=644621603"",""MSFT!J2"")"),0.114645316924798) | K32: =IFERROR(__xludf.DUMMYFUNCTION("importrange(""https://docs.google.com/spreadsheets/d/1-0wE4FJcTwa8HIXiUmKh_2bax-86FCPaaGwzK8mYxjE/edit#gid=644621603"",""MSFT!H16"")"),0.370303814285214) | L32: =IFERROR(__xludf.DUMMYFUNCTION("IFERROR(googlefinance(D32,""pe""),"""")"),"") | M32: =IFERROR(__xludf.DUMMYFUNCTION("IFERROR(googlefinance(D32,""beta""),"""")"),"")
A33: =A32+1 | B33: =HYPERLINK("https://finance.yahoo.com/quote/"&D33, C33) | C33: Meta Platforms, Inc. | D33: META | E33: =IFERROR(__xludf.DUMMYFUNCTION("iferror(googlefinance(D33,""price""),"""")"),648.18) | F33: =IFERROR(__xludf.DUMMYFUNCTION("IFERROR(GOOGLEFINANCE(D33,""price"") / index(GOOGLEFINANCE(D33,""price"", datevalue(today()-365) ) , 2,2) - 1,"""")"),-0.0104877490267918) | G33: =IFERROR(__xludf.DUMMYFUNCTION("iferror(googlefinance(D33,""marketcap""),"""")/10^6"),1639606.941372) | H33: =IFERROR(__xludf.DUMMYFUNCTION("importrange(""https://docs.google.com/spreadsheets/d/17uqhWqgxDFZCVvpEWDzsuYjUy_GuQnhH4-9GU95cukk/edit#gid=150498026"",""Summary!B29"")"),240226.174847726) | I33: =(H33-G33)/G33 | J33: =IFERROR(__xludf.DUMMYFUNCTION("importrange(""https://docs.google.com/spreadsheets/d/17uqhWqgxDFZCVvpEWDzsuYjUy_GuQnhH4-9GU95cukk/edit#gid=150498026"",""Summary!J2"")"),-0.0111931755547829) | K33: =IFERROR(__xludf.DUMMYFUNCTION("importrange(""https://docs.google.com/spreadsheets/d/17uqhWqgxDFZCVvpEWDzsuYjUy_GuQnhH4-9GU95cukk/edit#gid=150498026"",""Summary!G16"")"),0.380050020357122) | L33: =IFERROR(__xludf.DUMMYFUNCTION("IFERROR(googlefinance(D33,""pe""),"""")"),"") | M33: =IFERROR(__xludf.DUMMYFUNCTION("IFERROR(googlefinance(D33,""beta""),"""")"),"")
A34: =A33+1 | B34: =HYPERLINK("https://finance.yahoo.com/quote/"&D34, C34) | C34: Park Hotels & Resorts Inc. | D34: PK | E34: =IFERROR(__xludf.DUMMYFUNCTION("iferror(googlefinance(D34,""price""),"""")"),11.31) | F34: =IFERROR(__xludf.DUMMYFUNCTION("IFERROR(GOOGLEFINANCE(D34,""price"") / index(GOOGLEFINANCE(D34,""price"", datevalue(today()-365) ) , 2,2) - 1,"""")"),-0.0582847626977518) | G34: =IFERROR(__xludf.DUMMYFUNCTION("iferror(googlefinance(D34,""marketcap""),"""")/10^6"),2277.815988) | I34: 0 | L34: =IFERROR(__xludf.DUMMYFUNCTION("IFERROR(googlefinance(D34,""pe""),"""")"),"") | M34: =IFERROR(__xludf.DUMMYFUNCTION("IFERROR(googlefinance(D34,""beta""),"""")"),"")
A35: =A34+1 | B35: =HYPERLINK("https://finance.yahoo.com/quote/"&D35, C35) | C35: The Howard Hughes Corporation | D35: HHC | E35: =IFERROR(__xludf.DUMMYFUNCTION("iferror(googlefinance(D35,""price""),"""")"),0) | F35: =IFERROR(__xludf.DUMMYFUNCTION("IFERROR(GOOGLEFINANCE(D35,""price"") / index(GOOGLEFINANCE(D35,""price"", datevalue(today()-365) ) , 2,2) - 1,"""")"),"") | G35: =IFERROR(__xludf.DUMMYFUNCTION("iferror(googlefinance(D35,""marketcap""),"""")/10^6"),4315.882813) | I35: 0 | L35: =IFERROR(__xludf.DUMMYFUNCTION("IFERROR(googlefinance(D35,""pe""),"""")"),"") | M35: =IFERROR(__xludf.DUMMYFUNCTION("IFERROR(googlefinance(D35,""beta""),"""")"),"")
A36: =A35+1 | B36: =HYPERLINK("https://finance.yahoo.com/quote/"&D36, C36) | C36: Charles Schwab Corp. | D36: SCHW | E36: =IFERROR(__xludf.DUMMYFUNCTION("iferror(googlefinance(D36,""price""),"""")"),95.2) | F36: =IFERROR(__xludf.DUMMYFUNCTION("IFERROR(GOOGLEFINANCE(D36,""price"") / index(GOOGLEFINANCE(D36,""price"", datevalue(today()-365) ) , 2,2) - 1,"""")"),0.218637992831541) | G36: =IFERROR(__xludf.DUMMYFUNCTION("iferror(googlefinance(D36,""marketcap""),"""")/10^6"),166810.386652) | H36: =IFERROR(__xludf.DUMMYFUNCTION("importrange(""https://docs.google.com/spreadsheets/d/1F8tm1olP0GJTuf6jBnMAafmh7af_8JW2W4-P4xhp35s/edit#gid=644621603"",""SCHW!B31"")*1000"),103739.317847309) | I36: =(H36-G36)/G36 | J36: =IFERROR(__xludf.DUMMYFUNCTION("importrange(""https://docs.google.com/spreadsheets/d/1F8tm1olP0GJTuf6jBnMAafmh7af_8JW2W4-P4xhp35s/edit#gid=644621603"",""SCHW!I2"")"),0.184415362244461) | K36: =IFERROR(__xludf.DUMMYFUNCTION("importrange(""https://docs.google.com/spreadsheets/d/1F8tm1olP0GJTuf6jBnMAafmh7af_8JW2W4-P4xhp35s/edit#gid=644621603"",""SCHW!H16"")"),0.394479464350194) | L36: =IFERROR(__xludf.DUMMYFUNCTION("IFERROR(googlefinance(D36,""pe""),"""")"),"") | M36: =IFERROR(__xludf.DUMMYFUNCTION("IFERROR(googlefinance(D36,""beta""),"""")"),"")
A37: =A36+1 | B37: =HYPERLINK("https://finance.yahoo.com/quote/"&D37, C37) | C37: Restaurant Brands International Inc. | D37: QSR | E37: =IFERROR(__xludf.DUMMYFUNCTION("iferror(googlefinance(D37,""price""),"""")"),71.71) | F37: =IFERROR(__xludf.DUMMYFUNCTION("IFERROR(GOOGLEFINANCE(D37,""price"") / index(GOOGLEFINANCE(D37,""price"", datevalue(today()-365) ) , 2,2) - 1,"""")"),0.106123708159802) | G37: =IFERROR(__xludf.DUMMYFUNCTION("iferror(googlefinance(D37,""marketcap""),"""")/10^6"),24847.815864) | I37: 0 | L37: =IFERROR(__xludf.DUMMYFUNCTION("IFERROR(googlefinance(D37,""pe""),"""")"),"") | M37: =IFERROR(__xludf.DUMMYFUNCTION("IFERROR(googlefinance(D37,""beta""),"""")"),"")
A38: =A37+1 | B38: =HYPERLINK("https://finance.yahoo.com/quote/"&D38, C38) | C38: Xilinx Inc. | D38: XLNX | E38: =IFERROR(__xludf.DUMMYFUNCTION("iferror(googlefinance(D38,""price""),"""")"),"") | F38: 0 | G38: =IFERROR(__xludf.DUMMYFUNCTION("iferror(googlefinance(D38,""marketcap""),"""")/10^6"),0) | I38: 0 | L38: =IFERROR(__xludf.DUMMYFUNCTION("IFERROR(googlefinance(D38,""pe""),"""")"),"") | M38: =IFERROR(__xludf.DUMMYFUNCTION("IFERROR(googlefinance(D38,""beta""),"""")"),"")
A39: =A38+1 | B39: =HYPERLINK("https://finance.yahoo.com/quote/"&D39, C39) | C39: Walt Disney Co. | D39: DIS | E39: =IFERROR(__xludf.DUMMYFUNCTION("iferror(googlefinance(D39,""price""),"""")"),106.04) | F39: =IFERROR(__xludf.DUMMYFUNCTION("IFERROR(GOOGLEFINANCE(D39,""price"") / index(GOOGLEFINANCE(D39,""price"", datevalue(today()-365) ) , 2,2) - 1,"""")"),-0.0598457310045217) | G39: =IFERROR(__xludf.DUMMYFUNCTION("iferror(googlefinance(D39,""marketcap""),"""")/10^6"),187851.876381) | H39: =IFERROR(__xludf.DUMMYFUNCTION("importrange(""https://docs.google.com/spreadsheets/d/1L4FKQtUpj3I5jkPXYxo00-bMwvduNEaET-STfup6mZo/edit#gid=644621603"",""DIS!B32"")*1000"),117528.235825075) | I39: =(H39-G39)/G39 | J39: =IFERROR(__xludf.DUMMYFUNCTION("importrange(""https://docs.google.com/spreadsheets/d/1L4FKQtUpj3I5jkPXYxo00-bMwvduNEaET-STfup6mZo/edit#gid=644621603"",""DIS!I2"")*1000"),39.380081300813) | K39: =IFERROR(__xludf.DUMMYFUNCTION("importrange(""https://docs.google.com/spreadsheets/d/1L4FKQtUpj3I5jkPXYxo00-bMwvduNEaET-STfup6mZo/edit#gid=644621603"",""DIS!H15"")*1000"),230.69986714016) | L39: =IFERROR(__xludf.DUMMYFUNCTION("IFERROR(googlefinance(D39,""pe""),"""")"),"") | M39: =IFERROR(__xludf.DUMMYFUNCTION("IFERROR(googlefinance(D39,""beta""),"""")"),"")
A40: =A39+1 | B40: =HYPERLINK("https://finance.yahoo.com/quote/"&D40, C40) | C40: TD Ameritrade | D40: AMTD | E40: =IFERROR(__xludf.DUMMYFUNCTION("iferror(googlefinance(D40,""price""),"""")"),"") | F40: =IFERROR(__xludf.DUMMYFUNCTION("IFERROR(GOOGLEFINANCE(D40,""price"") / index(GOOGLEFINANCE(D40,""price"", datevalue(today()-365) ) , 2,2) - 1,"""")"),"") | G40: =IFERROR(__xludf.DUMMYFUNCTION("iferror(googlefinance(D40,""marketcap""),"""")/10^6"),0) | H40: =IFERROR(__xludf.DUMMYFUNCTION("importrange(""https://docs.google.com/spreadsheets/d/1vtcCV4JW-Qg5Z2YuuMjmX7GPYTyQzX2iEzo7hKgj-j8/edit#gid=644621603"",""AMTD!B31"")*1000"),19943.9520305236) | I40: =(H40-G40)/G40 | J40: =IFERROR(__xludf.DUMMYFUNCTION("importrange(""https://docs.google.com/spreadsheets/d/1vtcCV4JW-Qg5Z2YuuMjmX7GPYTyQzX2iEzo7hKgj-j8/edit#gid=644621603"",""AMTD!I2"")"),0.0372956403269754) | K40: =IFERROR(__xludf.DUMMYFUNCTION("importrange(""https://docs.google.com/spreadsheets/d/1vtcCV4JW-Qg5Z2YuuMjmX7GPYTyQzX2iEzo7hKgj-j8/edit#gid=644621603"",""AMTD!H16"")"),0.447731957811457) | L40: =IFERROR(__xludf.DUMMYFUNCTION("IFERROR(googlefinance(D40,""pe""),"""")"),"") | M40: =IFERROR(__xludf.DUMMYFUNCTION("IFERROR(googlefinance(D40,""beta""),"""")"),"")
A41: =A40+1 | B41: =HYPERLINK("https://finance.yahoo.com/quote/"&D41, C41) | C41: Mail.ru Group Ltd GDR | D41: MLRYY | E41: =IFERROR(__xludf.DUMMYFUNCTION("iferror(googlefinance(D41,""price""),"""")"),0) | F41: 0 | G41: =IFERROR(__xludf.DUMMYFUNCTION("iferror(googlefinance(D41,""marketcap""),"""")/10^6"),125.739851) | H41: =IFERROR(__xludf.DUMMYFUNCTION("importrange(""https://docs.google.com/spreadsheets/d/1POuxvulNjw70dgr4wRAoUiHRR0maG6qOrFcFl7BShmU/edit#gid=1344089490"",""Summary!C33"")*1000"),1622.66051906179) | I41: =(H41-G41)/G41 | J41: =IFERROR(__xludf.DUMMYFUNCTION("importrange(""https://docs.google.com/spreadsheets/d/1POuxvulNjw70dgr4wRAoUiHRR0maG6qOrFcFl7BShmU/edit#gid=1344089490"",""Summary!H2"")"),0.115925155925155) | K41: =IFERROR(__xludf.DUMMYFUNCTION("importrange(""https://docs.google.com/spreadsheets/d/1POuxvulNjw70dgr4wRAoUiHRR0maG6qOrFcFl7BShmU/edit#gid=1344089490"",""Summary!G19"")"),0.307399955287279) | L41: =IFERROR(__xludf.DUMMYFUNCTION("IFERROR(googlefinance(D41,""pe""),"""")"),"") | M41: =IFERROR(__xludf.DUMMYFUNCTION("IFERROR(googlefinance(D41,""beta""),"""")"),"")
A42: =A41+1 | B42: =HYPERLINK("https://finance.yahoo.com/quote/"&D42, C42) | C42: American Express Co | D42: AXP | E42: =IFERROR(__xludf.DUMMYFUNCTION("iferror(googlefinance(D42,""price""),"""")"),308.9) | F42: =IFERROR(__xludf.DUMMYFUNCTION("IFERROR(GOOGLEFINANCE(D42,""price"") / index(GOOGLEFINANCE(D42,""price"", datevalue(today()-365) ) , 2,2) - 1,"""")"),0.0453822464381197) | G42: =IFERROR(__xludf.DUMMYFUNCTION("iferror(googlefinance(D42,""marketcap""),"""")/10^6"),212095.029519) | H42: =IFERROR(__xludf.DUMMYFUNCTION("importrange(""https://docs.google.com/spreadsheets/d/1pPtPZdU5W0LctnDqTA4epwxgxp6IRPtePwNDmucu_Fs/edit#gid=1023062230"",""Summary!C27"")"),96956.5069582258) | I42: =(H42-G42)/G42 | J42: =IFERROR(__xludf.DUMMYFUNCTION("importrange(""https://docs.google.com/spreadsheets/d/1pPtPZdU5W0LctnDqTA4epwxgxp6IRPtePwNDmucu_Fs/edit#gid=1023062230"",""Summary!J2"")"),-0.00247956653503535) | K42: =IFERROR(__xludf.DUMMYFUNCTION("importrange(""https://docs.google.com/spreadsheets/d/1pPtPZdU5W0LctnDqTA4epwxgxp6IRPtePwNDmucu_Fs/edit#gid=1023062230"",""Summary!I14"")"),0.101109372122997) | L42: =IFERROR(__xludf.DUMMYFUNCTION("IFERROR(googlefinance(D42,""pe""),"""")"),"") | M42: =IFERROR(__xludf.DUMMYFUNCTION("IFERROR(googlefinance(D42,""beta""),"""")"),"")
A43: =A42+1 | B43: =HYPERLINK("https://finance.yahoo.com/quote/"&D43, C43) | C43: Bank of New York Mellon Corp | D43: BK | E43: =IFERROR(__xludf.DUMMYFUNCTION("iferror(googlefinance(D43,""price""),"""")"),119.1) | F43: =IFERROR(__xludf.DUMMYFUNCTION("IFERROR(GOOGLEFINANCE(D43,""price"") / index(GOOGLEFINANCE(D43,""price"", datevalue(today()-365) ) , 2,2) - 1,"""")"),0.348047538200339) | G43: =IFERROR(__xludf.DUMMYFUNCTION("iferror(googlefinance(D43,""marketcap""),"""")/10^6"),81810.670291) | H43: =IFERROR(__xludf.DUMMYFUNCTION("importrange(""https://docs.google.com/spreadsheets/d/1RDmGZo9Acgc7RPfWGhcWjGvuUfMMhJaYtkT38IdjaG8/edit#gid=892062421"",""BK!B32"")"),44754.6996211422) | I43: =(H43-G43)/G43 | J43: =IFERROR(__xludf.DUMMYFUNCTION("importrange(""https://docs.google.com/spreadsheets/d/1RDmGZo9Acgc7RPfWGhcWjGvuUfMMhJaYtkT38IdjaG8/edit#gid=892062421"",""BK!J3"")"),-0.0295152004584886) | K43: =IFERROR(__xludf.DUMMYFUNCTION("importrange(""https://docs.google.com/spreadsheets/d/1RDmGZo9Acgc7RPfWGhcWjGvuUfMMhJaYtkT38IdjaG8/edit#gid=892062421"",""BK!H24"")"),0.282641700404858) | L43: =IFERROR(__xludf.DUMMYFUNCTION("IFERROR(googlefinance(D43,""pe""),"""")"),"") | M43: =IFERROR(__xludf.DUMMYFUNCTION("IFERROR(googlefinance(D43,""beta""),"""")"),"")
A44: =A43+1 | B44: =HYPERLINK("https://finance.yahoo.com/quote/"&D44, C44) | C44: Tesla Inc | D44: TSLA | E44: =IFERROR(__xludf.DUMMYFUNCTION("iferror(googlefinance(D44,""price""),"""")"),402.51) | F44: =IFERROR(__xludf.DUMMYFUNCTION("IFERROR(GOOGLEFINANCE(D44,""price"") / index(GOOGLEFINANCE(D44,""price"", datevalue(today()-365) ) , 2,2) - 1,"""")"),0.414052344985069) | G44: =IFERROR(__xludf.DUMMYFUNCTION("iferror(googlefinance(D44,""marketcap""),"""")/10^6"),1261253.0403) | H44: =IFERROR(__xludf.DUMMYFUNCTION("importrange(""https://docs.google.com/spreadsheets/d/1s0WAt5f5uINzrh-BFNyDhLtn62N1pGkxpCpJuOZLxdU/edit#gid=1887439665"",""Summary!B4"")*1000"),24725.0400745573) | I44: =(H44-G44)/G44 | J44: =IFERROR(__xludf.DUMMYFUNCTION("importrange(""https://docs.google.com/spreadsheets/d/1s0WAt5f5uINzrh-BFNyDhLtn62N1pGkxpCpJuOZLxdU/edit#gid=1887439665"",""Summary!B1"")"),0.145386766076421) | K44: =IFERROR(__xludf.DUMMYFUNCTION("importrange(""https://docs.google.com/spreadsheets/d/1s0WAt5f5uINzrh-BFNyDhLtn62N1pGkxpCpJuOZLxdU/edit#gid=1887439665"",""Summary!B10"")"),0.03228285933897) | L44: =IFERROR(__xludf.DUMMYFUNCTION("IFERROR(googlefinance(D44,""pe""),"""")"),"") | M44: =IFERROR(__xludf.DUMMYFUNCTION("IFERROR(googlefinance(D44,""beta""),"""")"),"")
A45: =A44+1 | B45: =HYPERLINK("https://finance.yahoo.com/quote/"&D45, C45) | C45: Bristol-Myers Squibb Company | D45: BMY | E45: =IFERROR(__xludf.DUMMYFUNCTION("iferror(googlefinance(D45,""price""),"""")"),62.37) | F45: =IFERROR(__xludf.DUMMYFUNCTION("IFERROR(GOOGLEFINANCE(D45,""price"") / index(GOOGLEFINANCE(D45,""price"", datevalue(today()-365) ) , 2,2) - 1,"""")"),0.0417571404710206) | G45: =IFERROR(__xludf.DUMMYFUNCTION("iferror(googlefinance(D45,""marketcap""),"""")/10^6"),127014.756464) | H45: =IFERROR(__xludf.DUMMYFUNCTION("importrange(""https://docs.google.com/spreadsheets/d/1PKkvs4NFYwl4R4yvsfSA-VcPcz_8gWCI9jloSK2IhP0/edit#gid=254823806"",""Summary!B25"")*1000"),60721.1126872985) | I45: =(H45-G45)/G45 | J45: =IFERROR(__xludf.DUMMYFUNCTION("importrange(""https://docs.google.com/spreadsheets/d/1PKkvs4NFYwl4R4yvsfSA-VcPcz_8gWCI9jloSK2IhP0/edit#gid=254823806"",""Summary!H2"")"),0.62623828647925) | K45: =IFERROR(__xludf.DUMMYFUNCTION("importrange(""https://docs.google.com/spreadsheets/d/1PKkvs4NFYwl4R4yvsfSA-VcPcz_8gWCI9jloSK2IhP0/edit#gid=254823806"",""Summary!G18"")"),-0.161602144973893) | L45: =IFERROR(__xludf.DUMMYFUNCTION("IFERROR(googlefinance(D45,""pe""),"""")"),"") | M45: =IFERROR(__xludf.DUMMYFUNCTION("IFERROR(googlefinance(D45,""beta""),"""")"),"")
A46: =A45+1 | B46: =HYPERLINK("https://finance.yahoo.com/quote/"&D46, C46) | C46: T-Mobile US, Inc. | D46: TMUS | E46: =IFERROR(__xludf.DUMMYFUNCTION("iferror(googlefinance(D46,""price""),"""")"),217.09) | F46: =IFERROR(__xludf.DUMMYFUNCTION("IFERROR(GOOGLEFINANCE(D46,""price"") / index(GOOGLEFINANCE(D46,""price"", datevalue(today()-365) ) , 2,2) - 1,"""")"),-0.204303045852728) | G46: =IFERROR(__xludf.DUMMYFUNCTION("iferror(googlefinance(D46,""marketcap""),"""")/10^6"),239203.217544) | L46: =IFERROR(__xludf.DUMMYFUNCTION("IFERROR(googlefinance(D46,""pe""),"""")"),"") | M46: =IFERROR(__xludf.DUMMYFUNCTION("IFERROR(googlefinance(D46,""beta""),"""")"),"")
A47: =A46+1 | B47: =HYPERLINK("https://finance.yahoo.com/quote/"&D47, C47) | C47: Pfizer Inc. | D47: PFE | E47: =IFERROR(__xludf.DUMMYFUNCTION("iferror(googlefinance(D47,""price""),"""")"),27.65) | F47: =IFERROR(__xludf.DUMMYFUNCTION("IFERROR(GOOGLEFINANCE(D47,""price"") / index(GOOGLEFINANCE(D47,""price"", datevalue(today()-365) ) , 2,2) - 1,"""")"),0.0533333333333332) | G47: =IFERROR(__xludf.DUMMYFUNCTION("iferror(googlefinance(D47,""marketcap""),"""")/10^6"),157209.824031) | H47: =IFERROR(__xludf.DUMMYFUNCTION("importrange(""https://docs.google.com/spreadsheets/d/11SV-exCGxMmladm_kNssrzP_5btf3-nnwAh3xCyaL_g/edit#gid=254823806"",""Summary!B27"")*1000"),134501.097187239) | I47: =(H47-G47)/G47 | J47: =IFERROR(__xludf.DUMMYFUNCTION("importrange(""https://docs.google.com/spreadsheets/d/1oN8uGVHIkDbEs0vjYAQFVmfq4DbVF1dUmjRufJfa5kE/edit#gid=254823806"",""Summary!H2"")"),-0.0493333333333332) | K47: =IFERROR(__xludf.DUMMYFUNCTION("importrange(""https://docs.google.com/spreadsheets/d/1oN8uGVHIkDbEs0vjYAQFVmfq4DbVF1dUmjRufJfa5kE/edit#gid=254823806"",""Summary!G18"")"),0.346708132609711) | L47: =IFERROR(__xludf.DUMMYFUNCTION("IFERROR(googlefinance(D47,""pe""),"""")"),"") | M47: =IFERROR(__xludf.DUMMYFUNCTION("IFERROR(googlefinance(D47,""beta""),"""")"),"")
A48: =A47+1 | B48: =HYPERLINK("https://finance.yahoo.com/quote/"&D48, C48) | C48: AbbVie Inc. | D48: ABBV | E48: =IFERROR(__xludf.DUMMYFUNCTION("iferror(googlefinance(D48,""price""),"""")"),232.08) | F48: =IFERROR(__xludf.DUMMYFUNCTION("IFERROR(GOOGLEFINANCE(D48,""price"") / index(GOOGLEFINANCE(D48,""price"", datevalue(today()-365) ) , 2,2) - 1,"""")"),0.0974087384149802) | G48: =IFERROR(__xludf.DUMMYFUNCTION("iferror(googlefinance(D48,""marketcap""),"""")/10^6"),410356.664757) | H48: =IFERROR(__xludf.DUMMYFUNCTION("importrange(""https://docs.google.com/spreadsheets/d/1Lmha0aFigcxfAAQHBnl381BiKV2pruikPErrfchf7bM/edit#gid=254823806"",""Summary!B25"")*1000"),78350.5041602617) | I48: =(H48-G48)/G48 | J48: =IFERROR(__xludf.DUMMYFUNCTION("importrange(""https://docs.google.com/spreadsheets/d/1Lmha0aFigcxfAAQHBnl381BiKV2pruikPErrfchf7bM/edit#gid=254823806"",""Summary!H2"")"),0.221968376119761) | K48: =IFERROR(__xludf.DUMMYFUNCTION("importrange(""https://docs.google.com/spreadsheets/d/1Lmha0aFigcxfAAQHBnl381BiKV2pruikPErrfchf7bM/edit#gid=254823806"",""Summary!G18"")"),0.196285362853628) | L48: =IFERROR(__xludf.DUMMYFUNCTION("IFERROR(googlefinance(D48,""pe""),"""")"),"") | M48: =IFERROR(__xludf.DUMMYFUNCTION("IFERROR(googlefinance(D48,""beta""),"""")"),"")
A49: =A48+1 | B49: =HYPERLINK("https://finance.yahoo.com/quote/"&D49, C49) | C49: Merck & Co., Inc. | D49: MRK | E49: =IFERROR(__xludf.DUMMYFUNCTION("iferror(googlefinance(D49,""price""),"""")"),123.82) | F49: =IFERROR(__xludf.DUMMYFUNCTION("IFERROR(GOOGLEFINANCE(D49,""price"") / index(GOOGLEFINANCE(D49,""price"", datevalue(today()-365) ) , 2,2) - 1,"""")"),0.329253891572732) | G49: =IFERROR(__xludf.DUMMYFUNCTION("iferror(googlefinance(D49,""marketcap""),"""")/10^6"),306131.576685) | H49: =IFERROR(__xludf.DUMMYFUNCTION("importrange(""https://docs.google.com/spreadsheets/d/14Gn_cN5n5NHpurg7-PTOOMSPh6udDbRDZOjcOd1G0L0/edit#gid=254823806"",""Summary!B27"")*1000"),129175.142804748) | I49: =(H49-G49)/G49 | J49: =IFERROR(__xludf.DUMMYFUNCTION("importrange(""https://docs.google.com/spreadsheets/d/14Gn_cN5n5NHpurg7-PTOOMSPh6udDbRDZOjcOd1G0L0/edit#gid=254823806"",""Summary!I2"")"),0.00194310093564531) | K49: =IFERROR(__xludf.DUMMYFUNCTION("importrange(""https://docs.google.com/spreadsheets/d/14Gn_cN5n5NHpurg7-PTOOMSPh6udDbRDZOjcOd1G0L0/edit#gid=254823806"",""Summary!G18"")"),0.286712991319407) | L49: =IFERROR(__xludf.DUMMYFUNCTION("IFERROR(googlefinance(D49,""pe""),"""")"),"") | M49: =IFERROR(__xludf.DUMMYFUNCTION("IFERROR(googlefinance(D49,""beta""),"""")"),"")
A50: =A49+1 | B50: =HYPERLINK("https://finance.yahoo.com/quote/"&D50, C50) | C50: The Kroger Co. | D50: KR | E50: =IFERROR(__xludf.DUMMYFUNCTION("iferror(googlefinance(D50,""price""),"""")"),68.24) | F50: =IFERROR(__xludf.DUMMYFUNCTION("IFERROR(GOOGLEFINANCE(D50,""price"") / index(GOOGLEFINANCE(D50,""price"", datevalue(today()-365) ) , 2,2) - 1,"""")"),0.085069168389251) | G50: =IFERROR(__xludf.DUMMYFUNCTION("iferror(googlefinance(D50,""marketcap""),"""")/10^6"),43185.614408) | H50: =IFERROR(__xludf.DUMMYFUNCTION("importrange(""https://docs.google.com/spreadsheets/d/1j2x-RO8OrHlQoHZHO1fDKUUR3lcU5qiurqfM2Tagy3g/edit#gid=254823806"",""Summary!B25"")*1000"),30024.0645122656) | I50: =(H50-G50)/G50 | J50: =IFERROR(__xludf.DUMMYFUNCTION("importrange(""https://docs.google.com/spreadsheets/d/1j2x-RO8OrHlQoHZHO1fDKUUR3lcU5qiurqfM2Tagy3g/edit#gid=254823806"",""Summary!H2"")"),0.127586150499648) | K50: =IFERROR(__xludf.DUMMYFUNCTION("importrange(""https://docs.google.com/spreadsheets/d/1j2x-RO8OrHlQoHZHO1fDKUUR3lcU5qiurqfM2Tagy3g/edit#gid=254823806"",""Summary!G18"")"),0.0252161174286377) | L50: =IFERROR(__xludf.DUMMYFUNCTION("IFERROR(googlefinance(D50,""pe""),"""")"),"") | M50: =IFERROR(__xludf.DUMMYFUNCTION("IFERROR(googlefinance(D50,""beta""),"""")"),"")
A51: =A50+1 | B51: =HYPERLINK("https://finance.yahoo.com/quote/"&D51, C51) | C51: General Motors Company | D51: GME | E51: =IFERROR(__xludf.DUMMYFUNCTION("iferror(googlefinance(D51,""price""),"""")"),24.03) | F51: =IFERROR(__xludf.DUMMYFUNCTION("IFERROR(GOOGLEFINANCE(D51,""price"") / index(GOOGLEFINANCE(D51,""price"", datevalue(today()-365) ) , 2,2) - 1,"""")"),-0.0151639344262294) | G51: =IFERROR(__xludf.DUMMYFUNCTION("iferror(googlefinance(D51,""marketcap""),"""")/10^6"),10765.668592) | I51: 0 | L51: =IFERROR(__xludf.DUMMYFUNCTION("IFERROR(googlefinance(D51,""pe""),"""")"),"") | M51: =IFERROR(__xludf.DUMMYFUNCTION("IFERROR(googlefinance(D51,""beta""),"""")"),"")
A52: =A51+1 | B52: =HYPERLINK("https://finance.yahoo.com/quote/"&D52, C52) | C52: Globe Life Inc | D52: GL | E52: =IFERROR(__xludf.DUMMYFUNCTION("iferror(googlefinance(D52,""price""),"""")"),145.26) | F52: =IFERROR(__xludf.DUMMYFUNCTION("IFERROR(GOOGLEFINANCE(D52,""price"") / index(GOOGLEFINANCE(D52,""price"", datevalue(today()-365) ) , 2,2) - 1,"""")"),0.129636830235632) | G52: =IFERROR(__xludf.DUMMYFUNCTION("iferror(googlefinance(D52,""marketcap""),"""")/10^6"),11422.826166) | I52: 0 | L52: =IFERROR(__xludf.DUMMYFUNCTION("IFERROR(googlefinance(D52,""pe""),"""")"),"") | M52: =IFERROR(__xludf.DUMMYFUNCTION("IFERROR(googlefinance(D52,""beta""),"""")"),"")
A53: =A52+1 | B53: =HYPERLINK("https://finance.yahoo.com/quote/"&D53, C53) | C53: Snowflake Inc | D53: SNOW | E53: =IFERROR(__xludf.DUMMYFUNCTION("iferror(googlefinance(D53,""price""),"""")"),168.41) | F53: =IFERROR(__xludf.DUMMYFUNCTION("IFERROR(GOOGLEFINANCE(D53,""price"") / index(GOOGLEFINANCE(D53,""price"", datevalue(today()-365) ) , 2,2) - 1,"""")"),-0.030175640656493) | G53: =IFERROR(__xludf.DUMMYFUNCTION("iferror(googlefinance(D53,""marketcap""),"""")/10^6"),57629.886412) | I53: 0 | L53: =IFERROR(__xludf.DUMMYFUNCTION("IFERROR(googlefinance(D53,""pe""),"""")"),"") | M53: =IFERROR(__xludf.DUMMYFUNCTION("IFERROR(googlefinance(D53,""beta""),"""")"),"")
A54: =A53+1 | B54: =HYPERLINK("https://finance.yahoo.com/quote/"&D54, C54) | C54: AirBNB | D54: ABNB | E54: =IFERROR(__xludf.DUMMYFUNCTION("iferror(googlefinance(D54,""price""),"""")"),135.11) | F54: =IFERROR(__xludf.DUMMYFUNCTION("IFERROR(GOOGLEFINANCE(D54,""price"") / index(GOOGLEFINANCE(D54,""price"", datevalue(today()-365) ) , 2,2) - 1,"""")"),-0.0416371116470419) | G54: =IFERROR(__xludf.DUMMYFUNCTION("iferror(googlefinance(D54,""marketcap""),"""")/10^6"),82243.3354) | H54: =IFERROR(__xludf.DUMMYFUNCTION("importrange(""https://docs.google.com/spreadsheets/d/1LupNll8EBZR0CxUoQzkZLRitp2lxm5UXiwXAxqniEg4/edit#gid=1608086994"",""ABNB!B34"")*1000"),-2820.06535744982) | I54: =(H54-G54)/G54 | J54: =IFERROR(__xludf.DUMMYFUNCTION("importrange(""https://docs.google.com/spreadsheets/d/1LupNll8EBZR0CxUoQzkZLRitp2lxm5UXiwXAxqniEg4/edit#gid=1608086994"",""ABNB!F2"")"),-0.486235694401484) | K54: =IFERROR(__xludf.DUMMYFUNCTION("importrange(""https://docs.google.com/spreadsheets/d/1LupNll8EBZR0CxUoQzkZLRitp2lxm5UXiwXAxqniEg4/edit#gid=1608086994"",""ABNB!D18"")"),-0.0526534859521332) | L54: =IFERROR(__xludf.DUMMYFUNCTION("IFERROR(googlefinance(D54,""pe""),"""")"),"") | M54: =IFERROR(__xludf.DUMMYFUNCTION("IFERROR(googlefinance(D54,""beta""),"""")"),"")
A55: =A54+1 | B55: =HYPERLINK("https://finance.yahoo.com/quote/"&D55, C55) | C55: Nano-X Imaging Ltd | D55: NNOX | E55: =IFERROR(__xludf.DUMMYFUNCTION("iferror(googlefinance(D55,""price""),"""")"),2.37) | F55: =IFERROR(__xludf.DUMMYFUNCTION("IFERROR(GOOGLEFINANCE(D55,""price"") / index(GOOGLEFINANCE(D55,""price"", datevalue(today()-365) ) , 2,2) - 1,"""")"),-0.584938704028021) | G55: =IFERROR(__xludf.DUMMYFUNCTION("iferror(googlefinance(D55,""marketcap""),"""")/10^6"),164.0263) | I55: 0 | L55: =IFERROR(__xludf.DUMMYFUNCTION("IFERROR(googlefinance(D55,""pe""),"""")"),"") | M55: =IFERROR(__xludf.DUMMYFUNCTION("IFERROR(googlefinance(D55,""beta""),"""")"),"")
A56: =A55+1 | B56: =HYPERLINK("https://finance.yahoo.com/quote/"&D56, C56) | C56: Ozon Holdings | D56: OZON | E56: =IFERROR(__xludf.DUMMYFUNCTION("iferror(googlefinance(D56,""price""),"""")"),"") | F56: =IFERROR(__xludf.DUMMYFUNCTION("IFERROR(GOOGLEFINANCE(D56,""price"") / index(GOOGLEFINANCE(D56,""price"", datevalue(today()-365) ) , 2,2) - 1,"""")"),"") | G56: =IFERROR(__xludf.DUMMYFUNCTION("iferror(googlefinance(D56,""marketcap""),"""")/10^6"),0) | H56: =IFERROR(__xludf.DUMMYFUNCTION("importrange(""https://docs.google.com/spreadsheets/d/1LupNll8EBZR0CxUoQzkZLRitp2lxm5UXiwXAxqniEg4/edit#gid=865153574"",""OZON!B34"")*1000"),3382.20113289964) | I56: =(H56-G56)/G56 | J56: =IFERROR(__xludf.DUMMYFUNCTION("importrange(""https://docs.google.com/spreadsheets/d/1LupNll8EBZR0CxUoQzkZLRitp2lxm5UXiwXAxqniEg4/edit#gid=865153574"",""OZON!F2"")"),0.378247984009924) | K56: =IFERROR(__xludf.DUMMYFUNCTION("importrange(""https://docs.google.com/spreadsheets/d/1LupNll8EBZR0CxUoQzkZLRitp2lxm5UXiwXAxqniEg4/edit#gid=865153574"",""OZON!E18"")"),-0.183858294851471) | L56: =IFERROR(__xludf.DUMMYFUNCTION("IFERROR(googlefinance(D56,""pe""),"""")"),"") | M56: =IFERROR(__xludf.DUMMYFUNCTION("IFERROR(googlefinance(D56,""beta""),"""")"),"")
A57: =A56+1 | B57: =HYPERLINK("https://finance.yahoo.com/quote/"&D57, C57) | C57: DoorDash, Inc. | D57: DD | E57: =IFERROR(__xludf.DUMMYFUNCTION("iferror(googlefinance(D57,""price""),"""")"),50.04) | F57: =IFERROR(__xludf.DUMMYFUNCTION("IFERROR(GOOGLEFINANCE(D57,""price"") / index(GOOGLEFINANCE(D57,""price"", datevalue(today()-365) ) , 2,2) - 1,"""")"),0.517743403093721) | G57: =IFERROR(__xludf.DUMMYFUNCTION("iferror(googlefinance(D57,""marketcap""),"""")/10^6"),20462.55233) | H57: =IFERROR(__xludf.DUMMYFUNCTION("importrange(""https://docs.google.com/spreadsheets/d/1LupNll8EBZR0CxUoQzkZLRitp2lxm5UXiwXAxqniEg4/edit#gid=1126927364"",""DD!B30"")*1000"),-11995.5634010475) | I57: =(H57-G57)/G57 | J57: =IFERROR(__xludf.DUMMYFUNCTION("importrange(""https://docs.google.com/spreadsheets/d/1LupNll8EBZR0CxUoQzkZLRitp2lxm5UXiwXAxqniEg4/edit#gid=1126927364"",""DD!F2"")"),0.861448711716091) | K57: =IFERROR(__xludf.DUMMYFUNCTION("importrange(""https://docs.google.com/spreadsheets/d/1LupNll8EBZR0CxUoQzkZLRitp2lxm5UXiwXAxqniEg4/edit#gid=1126927364"",""DD!E18"")"),0.0717873926430076) | L57: =IFERROR(__xludf.DUMMYFUNCTION("IFERROR(googlefinance(D57,""pe""),"""")"),"") | M57: =IFERROR(__xludf.DUMMYFUNCTION("IFERROR(googlefinance(D57,""beta""),"""")"),"")
A58: =A57+1 | B58: =HYPERLINK("https://finance.yahoo.com/quote/"&D58, C58) | C58: Alibaba Group Holding Ltd ADR | D58: BABA | E58: =IFERROR(__xludf.DUMMYFUNCTION("iferror(googlefinance(D58,""price""),"""")"),144.11) | F58: =IFERROR(__xludf.DUMMYFUNCTION("IFERROR(GOOGLEFINANCE(D58,""price"") / index(GOOGLEFINANCE(D58,""price"", datevalue(today()-365) ) , 2,2) - 1,"""")"),0.101674183930892) | G58: =IFERROR(__xludf.DUMMYFUNCTION("E58*importrange(""https://docs.google.com/spreadsheets/d/18wXnZnXLelWNP84oOajcjx739bSr2i1dqUwcRDFtaMk/edit#gid=1602544562"",""Summary!J9"")"),389909.7804) | H58: =IFERROR(__xludf.DUMMYFUNCTION("importrange(""https://docs.google.com/spreadsheets/d/18wXnZnXLelWNP84oOajcjx739bSr2i1dqUwcRDFtaMk/edit#gid=1602544562"",""Summary!B32"")"),353530.194421304) | I58: =(H58-G58)/G58 | J58: =IFERROR(__xludf.DUMMYFUNCTION("importrange(""https://docs.google.com/spreadsheets/d/18wXnZnXLelWNP84oOajcjx739bSr2i1dqUwcRDFtaMk/edit#gid=1602544562"",""Summary!M2"")"),941.168) | K58: =IFERROR(__xludf.DUMMYFUNCTION("importrange(""https://docs.google.com/spreadsheets/d/18wXnZnXLelWNP84oOajcjx739bSr2i1dqUwcRDFtaMk/edit#gid=1602544562"",""Summary!K14"")"),0.0816329879891496) | L58: =IFERROR(__xludf.DUMMYFUNCTION("IFERROR(googlefinance(D58,""pe""),"""")"),"") | M58: =IFERROR(__xludf.DUMMYFUNCTION("IFERROR(googlefinance(D58,""beta""),"""")"),"")
A59: =A58+1 | B59: =HYPERLINK("https://finance.yahoo.com/quote/"&D59, C59) | C59: Verizon Communications Inc | D59: VZ | E59: =IFERROR(__xludf.DUMMYFUNCTION("iferror(googlefinance(D59,""price""),"""")"),50.14) | F59: =IFERROR(__xludf.DUMMYFUNCTION("IFERROR(GOOGLEFINANCE(D59,""price"") / index(GOOGLEFINANCE(D59,""price"", datevalue(today()-365) ) , 2,2) - 1,"""")"),0.142922270344198) | G59: =IFERROR(__xludf.DUMMYFUNCTION("iferror(googlefinance(D59,""marketcap""),"""")/10^6"),211474.673185) | H59: =IFERROR(__xludf.DUMMYFUNCTION("importrange(""https://docs.google.com/spreadsheets/d/1s2M_ltAGS6izvtgc6SVn4ngI84PWAhIzn_dv0RMInIU/edit#gid=1579911573"",""Summary!C18"")"),197185.256804111) | I59: =(H59-G59)/G59 | J59: =IFERROR(__xludf.DUMMYFUNCTION("importrange(""https://docs.google.com/spreadsheets/d/1s2M_ltAGS6izvtgc6SVn4ngI84PWAhIzn_dv0RMInIU/edit#gid=1579911573"",""Summary!H44"")"),0.00971053647240455) | K59: =IFERROR(__xludf.DUMMYFUNCTION("importrange(""https://docs.google.com/spreadsheets/d/1s2M_ltAGS6izvtgc6SVn4ngI84PWAhIzn_dv0RMInIU/edit#gid=1579911573"",""Summary!G54"")"),0.231493631802392) | L59: =IFERROR(__xludf.DUMMYFUNCTION("IFERROR(googlefinance(D59,""pe""),"""")"),"")
A60: =A59+1 | B60: =HYPERLINK("https://finance.yahoo.com/quote/"&D60, C60) | C60: POSCO | D60: PKX | E60: =IFERROR(__xludf.DUMMYFUNCTION("iferror(googlefinance(D60,""price""),"""")"),69.59) | F60: =IFERROR(__xludf.DUMMYFUNCTION("IFERROR(GOOGLEFINANCE(D60,""price"") / index(GOOGLEFINANCE(D60,""price"", datevalue(today()-365) ) , 2,2) - 1,"""")"),0.521425448185395) | G60: =IFERROR(__xludf.DUMMYFUNCTION("iferror(googlefinance(D60,""marketcap""),"""")/10^6"),23114.212898) | I60: 0
A61: =A60+1 | B61: =HYPERLINK("https://finance.yahoo.com/quote/"&D61, C61) | C61: Chevron Corp | D61: CVX | E61: =IFERROR(__xludf.DUMMYFUNCTION("iferror(googlefinance(D61,""price""),"""")"),186.76) | F61: =IFERROR(__xludf.DUMMYFUNCTION("IFERROR(GOOGLEFINANCE(D61,""price"") / index(GOOGLEFINANCE(D61,""price"", datevalue(today()-365) ) , 2,2) - 1,"""")"),0.219935985368084) | G61: =IFERROR(__xludf.DUMMYFUNCTION("iferror(googlefinance(D61,""marketcap""),"""")/10^6"),372658.091639) | H61: =IFERROR(__xludf.DUMMYFUNCTION("importrange(""https://docs.google.com/spreadsheets/d/1D0UrAGo7_Xn5F11kLcw58eM9AUUwte6YDSCpw6-idzw/edit?gid=1513331917"",""Summary!B43"")*1000"),151973.109689238) | I61: =(H61-G61)/G61 | J61: =IFERROR(__xludf.DUMMYFUNCTION("importrange(""https://docs.google.com/spreadsheets/d/1D0UrAGo7_Xn5F11kLcw58eM9AUUwte6YDSCpw6-idzw/edit?gid=1513331917"",""Summary!H19"")"),0.112538019601216) | L61: =IFERROR(__xludf.DUMMYFUNCTION("IFERROR(googlefinance(D61,""pe""),"""")"),"") | M61: =IFERROR(__xludf.DUMMYFUNCTION("IFERROR(googlefinance(D61,""beta""),"""")"),"")
A62: =A61+1 | B62: =HYPERLINK("https://finance.yahoo.com/quote/"&D62, C62) | C62: The E W Scripps Co Class A | D62: SSP | E62: =IFERROR(__xludf.DUMMYFUNCTION("iferror(googlefinance(D62,""price""),"""")"),4.15) | F62: =IFERROR(__xludf.DUMMYFUNCTION("IFERROR(GOOGLEFINANCE(D62,""price"") / index(GOOGLEFINANCE(D62,""price"", datevalue(today()-365) ) , 2,2) - 1,"""")"),1.84246575342465) | G62: =IFERROR(__xludf.DUMMYFUNCTION("iferror(googlefinance(D62,""marketcap""),"""")/10^6"),368.528889) | I62: 0 | M62: =IFERROR(__xludf.DUMMYFUNCTION("IFERROR(googlefinance(D62,""beta""),"""")"),"")
A63: =A62+1 | B63: =HYPERLINK("https://finance.yahoo.com/quote/"&D63, C63) | C63: Marsh & McLennan Companies Inc | D63: MMC | E63: =IFERROR(__xludf.DUMMYFUNCTION("iferror(googlefinance(D63,""price""),"""")"),"") | F63: =IFERROR(__xludf.DUMMYFUNCTION("IFERROR(GOOGLEFINANCE(D63,""price"") / index(GOOGLEFINANCE(D63,""price"", datevalue(today()-365) ) , 2,2) - 1,"""")"),"") | G63: =IFERROR(__xludf.DUMMYFUNCTION("iferror(googlefinance(D63,""marketcap""),"""")/10^6"),0) | I63: 0 | M63: =IFERROR(__xludf.DUMMYFUNCTION("IFERROR(googlefinance(D63,""beta""),"""")"),"")
A64: =A63+1 | B64: =HYPERLINK("https://finance.yahoo.com/quote/"&D64, C64) | C64: Segezha Group | E64: =IFERROR(__xludf.DUMMYFUNCTION("iferror(googlefinance(D64,""price""),"""")"),"") | F64: =IFERROR(__xludf.DUMMYFUNCTION("IFERROR(GOOGLEFINANCE(D64,""price"") / index(GOOGLEFINANCE(D64,""price"", datevalue(today()-365) ) , 2,2) - 1,"""")"),"") | G64: =IFERROR(__xludf.DUMMYFUNCTION("importrange(""https://docs.google.com/spreadsheets/d/1jU-MirNEtnSxLLg8W-onD3ZzFvcJwcUyUn9TIvxZtjU/edit#gid=134408949"",""Summary!C34"")"),122.384999999999) | H64: =IFERROR(__xludf.DUMMYFUNCTION("importrange(""https://docs.google.com/spreadsheets/d/1jU-MirNEtnSxLLg8W-onD3ZzFvcJwcUyUn9TIvxZtjU/edit#gid=134408949"",""Summary!C32"")"),167.071626396776) | I64: =(H64-G64)/G64 | J64: =IFERROR(__xludf.DUMMYFUNCTION("importrange(""https://docs.google.com/spreadsheets/d/1jU-MirNEtnSxLLg8W-onD3ZzFvcJwcUyUn9TIvxZtjU/edit#gid=134408949"",""Summary!J2"")"),0.179487179487179) | K64: =IFERROR(__xludf.DUMMYFUNCTION("importrange(""https://docs.google.com/spreadsheets/d/1jU-MirNEtnSxLLg8W-onD3ZzFvcJwcUyUn9TIvxZtjU/edit#gid=134408949"",""Summary!I16"")"),0.161826086956521) | M64: =IFERROR(__xludf.DUMMYFUNCTION("IFERROR(googlefinance(D64,""beta""),"""")"),"")
A65: =A64+1 | B65: =HYPERLINK("https://finance.yahoo.com/quote/"&D65, C65) | C65: Elaton Group Plc | D65: ETLN | E65: =IFERROR(__xludf.DUMMYFUNCTION("iferror(googlefinance(D65,""price""),"""")"),0) | F65: =IFERROR(__xludf.DUMMYFUNCTION("IFERROR(GOOGLEFINANCE(D65,""price"") / index(GOOGLEFINANCE(D65,""price"", datevalue(today()-365) ) , 2,2) - 1,"""")"),"") | I65: 0 | M65: =IFERROR(__xludf.DUMMYFUNCTION("IFERROR(googlefinance(D65,""beta""),"""")"),"")
A66: =A65+1 | B66: =HYPERLINK("https://finance.yahoo.com/quote/"&D66, C66) | C66: Wise plc | D66: WISE.L | E66: =IFERROR(__xludf.DUMMYFUNCTION("iferror(googlefinance(D66,""price""),"""")"),"") | F66: =IFERROR(__xludf.DUMMYFUNCTION("IFERROR(GOOGLEFINANCE(D66,""price"") / index(GOOGLEFINANCE(D66,""price"", datevalue(today()-365) ) , 2,2) - 1,"""")"),"") | G66: =IFERROR(__xludf.DUMMYFUNCTION("importrange(""https://docs.google.com/spreadsheets/d/11C3zL8Lqn71AMKui3dRgPghYoFUIcpycZSsaYmD_Gsg/edit#gid=254823806"",""Summary!B26"")"),7.7044) | H66: =IFERROR(__xludf.DUMMYFUNCTION("importrange(""https://docs.google.com/spreadsheets/d/11C3zL8Lqn71AMKui3dRgPghYoFUIcpycZSsaYmD_Gsg/edit#gid=254823806"",""Summary!B25"")"),11.4522079949057) | I66: =(H66-G66)/G66 | J66: =IFERROR(__xludf.DUMMYFUNCTION("importrange(""https://docs.google.com/spreadsheets/d/11C3zL8Lqn71AMKui3dRgPghYoFUIcpycZSsaYmD_Gsg/edit#gid=254823806"",""Summary!H2"")"),0.253128689492325) | K66: =IFERROR(__xludf.DUMMYFUNCTION("importrange(""https://docs.google.com/spreadsheets/d/11C3zL8Lqn71AMKui3dRgPghYoFUIcpycZSsaYmD_Gsg/edit#gid=254823806"",""Summary!D18"")"),0.0976247030878859) | M66: =IFERROR(__xludf.DUMMYFUNCTION("IFERROR(googlefinance(D66,""beta""),"""")"),"")
A67: =A66+1 | B67: =HYPERLINK("https://finance.yahoo.com/quote/"&D67, C67) | C67: Coinbase Global Inc Ordinary Shares - Class A - Stock Quote | D67: COIN | E67: =IFERROR(__xludf.DUMMYFUNCTION("iferror(googlefinance(D67,""price""),"""")"),175.85) | F67: =IFERROR(__xludf.DUMMYFUNCTION("IFERROR(GOOGLEFINANCE(D67,""price"") / index(GOOGLEFINANCE(D67,""price"", datevalue(today()-365) ) , 2,2) - 1,"""")"),-0.145321992709599) | G67: =IFERROR(__xludf.DUMMYFUNCTION("iferror(googlefinance(D67,""marketcap""),"""")/10^6"),46437.607946) | H67: =IFERROR(__xludf.DUMMYFUNCTION("importrange(""https://docs.google.com/spreadsheets/d/1Su6GwjWTshoYV5M4DYz6MZVzzpMhsogTV4mioI8emKc/edit#gid=254823806"",""Summary!B25"")*1000"),0) | I67: =(H67-G67)/G67 | J67: =IFERROR(__xludf.DUMMYFUNCTION("importrange(""https://docs.google.com/spreadsheets/d/1Su6GwjWTshoYV5M4DYz6MZVzzpMhsogTV4mioI8emKc/edit#gid=254823806"",""Summary!F2"")"),3.108) | K67: =IFERROR(__xludf.DUMMYFUNCTION("importrange(""https://docs.google.com/spreadsheets/d/1Su6GwjWTshoYV5M4DYz6MZVzzpMhsogTV4mioI8emKc/edit#gid=254823806"",""Summary!E18"")"),-0.556525046963055) | L67: =IFERROR(__xludf.DUMMYFUNCTION("IFERROR(googlefinance(D67,""pe""),"""")"),"") | M67: =IFERROR(__xludf.DUMMYFUNCTION("IFERROR(googlefinance(D67,""beta""),"""")"),"")
A68: =A67+1 | B68: =HYPERLINK("https://finance.yahoo.com/quote/"&D68, C68) | C68: Ally Financial Inc. | D68: ALLY | E68: =IFERROR(__xludf.DUMMYFUNCTION("iferror(googlefinance(D68,""price""),"""")"),39.44) | F68: =IFERROR(__xludf.DUMMYFUNCTION("IFERROR(GOOGLEFINANCE(D68,""price"") / index(GOOGLEFINANCE(D68,""price"", datevalue(today()-365) ) , 2,2) - 1,"""")"),0.120136324907696) | G68: =IFERROR(__xludf.DUMMYFUNCTION("iferror(googlefinance(D68,""marketcap""),"""")/10^6"),12190.576223) | H68: =IFERROR(__xludf.DUMMYFUNCTION("importrange(""https://docs.google.com/spreadsheets/d/1f_Jzu9pXiiSiiKEQUwtTFdX08DOB9GKdGgfSvPnCqxM/edit#gid=254823806"",""Summary!B25"")*1000"),27766.701002473) | I68: =(H68-G68)/G68 | J68: =IFERROR(__xludf.DUMMYFUNCTION("importrange(""https://docs.google.com/spreadsheets/d/1f_Jzu9pXiiSiiKEQUwtTFdX08DOB9GKdGgfSvPnCqxM/edit#gid=254823806"",""Summary!H2"")"),0.0282307130688731) | K68: =IFERROR(__xludf.DUMMYFUNCTION("importrange(""https://docs.google.com/spreadsheets/d/1f_Jzu9pXiiSiiKEQUwtTFdX08DOB9GKdGgfSvPnCqxM/edit#gid=254823806"",""Summary!G18"")"),0.437159763313609) | L68: =IFERROR(__xludf.DUMMYFUNCTION("IFERROR(googlefinance(D68,""pe""),"""")"),"") | M68: =IFERROR(__xludf.DUMMYFUNCTION("IFERROR(googlefinance(D68,""beta""),"""")"),"")
A69: =A68+1 | B69: =HYPERLINK("https://finance.yahoo.com/quote/"&D69, C69) | C69: Celanese Corporation | D69: CE | E69: =IFERROR(__xludf.DUMMYFUNCTION("iferror(googlefinance(D69,""price""),"""")"),49.94) | F69: =IFERROR(__xludf.DUMMYFUNCTION("IFERROR(GOOGLEFINANCE(D69,""price"") / index(GOOGLEFINANCE(D69,""price"", datevalue(today()-365) ) , 2,2) - 1,"""")"),0.0621012335176518) | G69: =IFERROR(__xludf.DUMMYFUNCTION("iferror(googlefinance(D69,""marketcap""),"""")/10^6"),5472.020535) | H69: =IFERROR(__xludf.DUMMYFUNCTION("importrange(""https://docs.google.com/spreadsheets/d/1Fanf8gqdVakniENbQR3f6zZtBUSq0HtMFYxPGHvZhhI/edit#gid=254823806"",""Summary!B25"")*1000"),10978.4910926615) | I69: =(H69-G69)/G69 | J69: =IFERROR(__xludf.DUMMYFUNCTION("importrange(""https://docs.google.com/spreadsheets/d/1Fanf8gqdVakniENbQR3f6zZtBUSq0HtMFYxPGHvZhhI/edit#gid=254823806"",""Summary!H2"")"),0.0866815040412321) | K69: =IFERROR(__xludf.DUMMYFUNCTION("importrange(""https://docs.google.com/spreadsheets/d/1Fanf8gqdVakniENbQR3f6zZtBUSq0HtMFYxPGHvZhhI/edit#gid=254823806"",""Summary!G18"")"),0.264632963242427) | L69: =IFERROR(__xludf.DUMMYFUNCTION("IFERROR(googlefinance(D69,""pe""),"""")"),"") | M69: =IFERROR(__xludf.DUMMYFUNCTION("IFERROR(googlefinance(D69,""beta""),"""")"),"")
A70: =A69+1 | B70: =HYPERLINK("https://finance.yahoo.com/quote/"&D70, C70) | C70: Paramount Global | D70: PARA | E70: =IFERROR(__xludf.DUMMYFUNCTION("iferror(googlefinance(D70,""price""),"""")"),"") | F70: =IFERROR(__xludf.DUMMYFUNCTION("IFERROR(GOOGLEFINANCE(D70,""price"") / index(GOOGLEFINANCE(D70,""price"", datevalue(today()-365) ) , 2,2) - 1,"""")"),"") | G70: =IFERROR(__xludf.DUMMYFUNCTION("iferror(googlefinance(D70,""marketcap""),"""")/10^6"),0) | H70: =IFERROR(__xludf.DUMMYFUNCTION("importrange(""https://docs.google.com/spreadsheets/d/1wvZQWyHqlMg08UNd26ujkZyRTp2yIJKEq1fCghrvFHM/edit#gid=254823806"",""Summary!B25"")*1000"),25485.3454126241) | I70: =(H70-G70)/G70 | J70: =IFERROR(__xludf.DUMMYFUNCTION("importrange(""https://docs.google.com/spreadsheets/d/1wvZQWyHqlMg08UNd26ujkZyRTp2yIJKEq1fCghrvFHM/edit#gid=254823806"",""Summary!H2"")"),-0.0476849289798931) | K70: =IFERROR(__xludf.DUMMYFUNCTION("importrange(""https://docs.google.com/spreadsheets/d/1wvZQWyHqlMg08UNd26ujkZyRTp2yIJKEq1fCghrvFHM/edit#gid=254823806"",""Summary!G18"")"),0.437869249394673) | L70: =IFERROR(__xludf.DUMMYFUNCTION("IFERROR(googlefinance(D70,""pe""),"""")"),"") | M70: =IFERROR(__xludf.DUMMYFUNCTION("IFERROR(googlefinance(D70,""beta""),"""")"),"")
A71: =A70+1 | B71: =HYPERLINK("https://finance.yahoo.com/quote/"&D71, C71) | C71: Markel Corporation | D71: MKL | E71: =IFERROR(__xludf.DUMMYFUNCTION("iferror(googlefinance(D71,""price""),"""")"),2072.47) | F71: =IFERROR(__xludf.DUMMYFUNCTION("IFERROR(GOOGLEFINANCE(D71,""price"") / index(GOOGLEFINANCE(D71,""price"", datevalue(today()-365) ) , 2,2) - 1,"""")"),0.080221624551747) | G71: =IFERROR(__xludf.DUMMYFUNCTION("iferror(googlefinance(D71,""marketcap""),"""")/10^6"),26092.376206) | H71: =IFERROR(__xludf.DUMMYFUNCTION("importrange(""https://docs.google.com/spreadsheets/d/1PbR9WKj3KQAFiIxPRhAZBzf_n1_MWKzDvgKboQnr7bU/edit#gid=254823806"",""Summary!B25"")*1000"),8029.07295558409) | I71: =(H71-G71)/G71 | J71: =IFERROR(__xludf.DUMMYFUNCTION("importrange(""https://docs.google.com/spreadsheets/d/1PbR9WKj3KQAFiIxPRhAZBzf_n1_MWKzDvgKboQnr7bU/edit#gid=254823806"",""Summary!H2"")"),-0.0205562345398528) | K71: =IFERROR(__xludf.DUMMYFUNCTION("importrange(""https://docs.google.com/spreadsheets/d/1PbR9WKj3KQAFiIxPRhAZBzf_n1_MWKzDvgKboQnr7bU/edit#gid=254823806"",""Summary!G18"")"),0.184729417200254) | L71: =IFERROR(__xludf.DUMMYFUNCTION("IFERROR(googlefinance(D71,""pe""),"""")"),"") | M71: =IFERROR(__xludf.DUMMYFUNCTION("IFERROR(googlefinance(D71,""beta""),"""")"),"")
A72: =A71+1 | B72: =HYPERLINK("https://finance.yahoo.com/quote/"&D72, C72) | C72: McKesson Corporation | D72: MCK | E72: =IFERROR(__xludf.DUMMYFUNCTION("iferror(googlefinance(D72,""price""),"""")"),987.37) | F72: =IFERROR(__xludf.DUMMYFUNCTION("IFERROR(GOOGLEFINANCE(D72,""price"") / index(GOOGLEFINANCE(D72,""price"", datevalue(today()-365) ) , 2,2) - 1,"""")"),0.5319224861527) | G72: =IFERROR(__xludf.DUMMYFUNCTION("iferror(googlefinance(D72,""marketcap""),"""")/10^6"),120940.383539) | H72: =IFERROR(__xludf.DUMMYFUNCTION("importrange(""https://docs.google.com/spreadsheets/d/1zt6-MZSWh25h7jG4V610KioqWf37FAqPrfKMpjCURpw/edit#gid=254823806"",""Summary!B25"")*1000"),38484.7001090052) | I72: =(H72-G72)/G72 | J72: =IFERROR(__xludf.DUMMYFUNCTION("importrange(""https://docs.google.com/spreadsheets/d/1zt6-MZSWh25h7jG4V610KioqWf37FAqPrfKMpjCURpw/edit#gid=254823806"",""Summary!G2"")"),0.108039357254394) | K72: =IFERROR(__xludf.DUMMYFUNCTION("importrange(""https://docs.google.com/spreadsheets/d/1zt6-MZSWh25h7jG4V610KioqWf37FAqPrfKMpjCURpw/edit#gid=254823806"",""Summary!F18"")"),0.00730397096595773) | L72: =IFERROR(__xludf.DUMMYFUNCTION("IFERROR(googlefinance(D72,""pe""),"""")"),"") | M72: =IFERROR(__xludf.DUMMYFUNCTION("IFERROR(googlefinance(D72,""beta""),"""")"),"")
A73: =A72+1 | B73: =HYPERLINK("https://finance.yahoo.com/quote/"&D73, C73) | C73: NVDIA | D73: NVDA | E73: =IFERROR(__xludf.DUMMYFUNCTION("iferror(googlefinance(D73,""price""),"""")"),177.19) | F73: =IFERROR(__xludf.DUMMYFUNCTION("IFERROR(GOOGLEFINANCE(D73,""price"") / index(GOOGLEFINANCE(D73,""price"", datevalue(today()-365) ) , 2,2) - 1,"""")"),0.553480624232859) | G73: =IFERROR(__xludf.DUMMYFUNCTION("iferror(googlefinance(D73,""marketcap""),"""")/10^6"),4305717) | H73: =IFERROR(__xludf.DUMMYFUNCTION("importrange(""https://docs.google.com/spreadsheets/d/1xz4QVVw6eAJJPxzKhqgOCGtx5P_w0ajl78rdYcFlRZM/edit?usp=sharing"",""Summary!C28"")"),3169036.9422701) | I73: =(H73-G73)/G73 | J73: =IFERROR(__xludf.DUMMYFUNCTION("importrange(""https://docs.google.com/spreadsheets/d/1xz4QVVw6eAJJPxzKhqgOCGtx5P_w0ajl78rdYcFlRZM/edit?usp=sharing"",""Summary!J7"")"),1.14203407635993) | L73: =IFERROR(__xludf.DUMMYFUNCTION("IFERROR(googlefinance(D73,""pe""),"""")"),"") | M73: =IFERROR(__xludf.DUMMYFUNCTION("IFERROR(googlefinance(D73,""beta""),"""")"),"")
A74: =A73+1 | B74: =HYPERLINK("https://finance.yahoo.com/quote/"&D74, C74) | C74: STZ | D74: STZ | E74: =IFERROR(__xludf.DUMMYFUNCTION("iferror(googlefinance(D74,""price""),"""")"),157.86) | F74: =IFERROR(__xludf.DUMMYFUNCTION("IFERROR(GOOGLEFINANCE(D74,""price"") / index(GOOGLEFINANCE(D74,""price"", datevalue(today()-365) ) , 2,2) - 1,"""")"),-0.0993838429940665) | G74: =IFERROR(__xludf.DUMMYFUNCTION("iferror(googlefinance(D74,""marketcap""),"""")/10^6"),27374.628993) | H74: =IFERROR(__xludf.DUMMYFUNCTION("importrange(""https://docs.google.com/spreadsheets/d/1wXUxPs_ekZAd3ic7Nbhf8YE-qk6wcB7VPJvwAvLgbV8/edit?usp=sharing"",""Summary!C28"")*1000"),20454.9308688541) | I74: =(H74-G74)/G74 | J74: =IFERROR(__xludf.DUMMYFUNCTION("importrange(""https://docs.google.com/spreadsheets/d/1wXUxPs_ekZAd3ic7Nbhf8YE-qk6wcB7VPJvwAvLgbV8/edit?usp=sharing"",""Summary!N6"")"),0.0248995983935742) | L74: =IFERROR(__xludf.DUMMYFUNCTION("IFERROR(googlefinance(D74,""pe""),"""")"),"") | M74: =IFERROR(__xludf.DUMMYFUNCTION("IFERROR(googlefinance(D74,""beta""),"""")"),"")
A75: =A74+1 | B75: =HYPERLINK("https://finance.yahoo.com/quote/"&D75, C75) | C75: POOL | D75: POOL | E75: =IFERROR(__xludf.DUMMYFUNCTION("iferror(googlefinance(D75,""price""),"""")"),227.18) | F75: =IFERROR(__xludf.DUMMYFUNCTION("IFERROR(GOOGLEFINANCE(D75,""price"") / index(GOOGLEFINANCE(D75,""price"", datevalue(today()-365) ) , 2,2) - 1,"""")"),-0.339938404323319) | G75: =IFERROR(__xludf.DUMMYFUNCTION("iferror(googlefinance(D75,""marketcap""),"""")/10^6"),8462.336593) | H75: =IFERROR(__xludf.DUMMYFUNCTION("importrange(""https://docs.google.com/spreadsheets/d/1AjHA3YbkgHW1O9Dt-6Buiwed8NsU2S933D9cwB0cVIg/edit?usp=sharing"",""Summary!C28"")*1000"),5529.19347584864) | I75: =(H75-G75)/G75 | J75: =IFERROR(__xludf.DUMMYFUNCTION("importrange(""https://docs.google.com/spreadsheets/d/1AjHA3YbkgHW1O9Dt-6Buiwed8NsU2S933D9cwB0cVIg/edit?usp=sharing"",""Summary!H6"")"),0.0167576727546602) | L75: =IFERROR(__xludf.DUMMYFUNCTION("IFERROR(googlefinance(D75,""pe""),"""")"),"") | M75: =IFERROR(__xludf.DUMMYFUNCTION("IFERROR(googlefinance(D75,""beta""),"""")"),"")
A76: =A75+1 | B76: =HYPERLINK("https://finance.yahoo.com/quote/"&D76, C76) | C76: CRCL | D76: CRCL | E76: =IFERROR(__xludf.DUMMYFUNCTION("iferror(googlefinance(D76,""price""),"""")"),83.44) | F76: =IFERROR(__xludf.DUMMYFUNCTION("IFERROR(GOOGLEFINANCE(D76,""price"") / index(GOOGLEFINANCE(D76,""price"", datevalue(today()-90) ) , 2,2) - 1,"""")"),0.0774793388429753) | G76: =IFERROR(__xludf.DUMMYFUNCTION("iferror(googlefinance(D76,""marketcap""),"""")/10^6"),19648.084638) | I76: =(H76-G76)/G76 | J76: =IFERROR(__xludf.DUMMYFUNCTION("importrange(""https://docs.google.com/spreadsheets/d/1PbR9WKj3KQAFiIxPRhAZBzf_n1_MWKzDvgKboQnr7bU/edit#gid=254823806"",""Summary!H2"")"),-0.0205562345398528) | K76: =IFERROR(__xludf.DUMMYFUNCTION("importrange(""https://docs.google.com/spreadsheets/d/1PbR9WKj3KQAFiIxPRhAZBzf_n1_MWKzDvgKboQnr7bU/edit#gid=254823806"",""Summary!G18"")"),0.184729417200254) | L76: =IFERROR(__xludf.DUMMYFUNCTION("IFERROR(googlefinance(D76,""pe""),"""")"),"") | M76: =IFERROR(__xludf.DUMMYFUNCTION("IFERROR(googlefinance(D76,""beta""),"""")"),"")
A77: =A76+1 | B77: =HYPERLINK("https://finance.yahoo.com/quote/"&D77, C77) | C77: LEN | D77: LEN | E77: =IFERROR(__xludf.DUMMYFUNCTION("iferror(googlefinance(D77,""price""),"""")"),114.36) | F77: =IFERROR(__xludf.DUMMYFUNCTION("IFERROR(GOOGLEFINANCE(D77,""price"") / index(GOOGLEFINANCE(D77,""price"", datevalue(today()-365) ) , 2,2) - 1,"""")"),-0.0302721953701349) | G77: =IFERROR(__xludf.DUMMYFUNCTION("iferror(googlefinance(D77,""marketcap""),"""")/10^6"),28032.152069) | H77: =IFERROR(__xludf.DUMMYFUNCTION("importrange(""https://docs.google.com/spreadsheets/d/1PSz-z1Lv-gZ1WOwdTZ8qAxUigZaO9b52l0_4wx34KIs/edit?gid=2118916648#gid=2118916648&range=B28"",""Summary!B28"")*1000"),35428.3539557584) | I77: =(H77-G77)/G77 | J77: =IFERROR(__xludf.DUMMYFUNCTION("importrange(""https://docs.google.com/spreadsheets/d/1zt6-MZSWh25h7jG4V610KioqWf37FAqPrfKMpjCURpw/edit#gid=254823806"",""Summary!G2"")"),0.108039357254394) | K77: =IFERROR(__xludf.DUMMYFUNCTION("importrange(""https://docs.google.com/spreadsheets/d/1zt6-MZSWh25h7jG4V610KioqWf37FAqPrfKMpjCURpw/edit#gid=254823806"",""Summary!F18"")"),0.00730397096595773) | L77: =IFERROR(__xludf.DUMMYFUNCTION("IFERROR(googlefinance(D77,""pe""),"""")"),"") | M77: =IFERROR(__xludf.DUMMYFUNCTION("IFERROR(googlefinance(D77,""beta""),"""")"),"")
A78: =A77+1 | B78: =HYPERLINK("https://finance.yahoo.com/quote/"&D78, C78) | C78: DHI | D78: DHI | E78: =IFERROR(__xludf.DUMMYFUNCTION("iferror(googlefinance(D78,""price""),"""")"),160.39) | F78: =IFERROR(__xludf.DUMMYFUNCTION("IFERROR(GOOGLEFINANCE(D78,""price"") / index(GOOGLEFINANCE(D78,""price"", datevalue(today()-365) ) , 2,2) - 1,"""")"),0.276177593889242) | G78: =IFERROR(__xludf.DUMMYFUNCTION("iferror(googlefinance(D78,""marketcap""),"""")/10^6"),46465.528149) | H78: =IFERROR(__xludf.DUMMYFUNCTION("importrange(""https://docs.google.com/spreadsheets/d/1PSz-z1Lv-gZ1WOwdTZ8qAxUigZaO9b52l0_4wx34KIs/edit?gid=2118916648#gid=2118916648&range=B28"",""Summary!B28"")*1000"),35428.3539557584) | L78: =IFERROR(__xludf.DUMMYFUNCTION("IFERROR(googlefinance(D78,""pe""),"""")"),"") | M78: =IFERROR(__xludf.DUMMYFUNCTION("IFERROR(googlefinance(D78,""beta""),"""")"),"")
A79: =A78+1 | B79: =HYPERLINK("https://finance.yahoo.com/quote/"&D79, C79) | C79: NUE | D79: NUE | E79: =IFERROR(__xludf.DUMMYFUNCTION("iferror(googlefinance(D79,""price""),"""")"),176.88) | F79: =IFERROR(__xludf.DUMMYFUNCTION("IFERROR(GOOGLEFINANCE(D79,""price"") / index(GOOGLEFINANCE(D79,""price"", datevalue(today()-365) ) , 2,2) - 1,"""")"),0.319310807786977) | G79: =IFERROR(__xludf.DUMMYFUNCTION("iferror(googlefinance(D79,""marketcap""),"""")/10^6"),40288.77236) | H79: =IFERROR(__xludf.DUMMYFUNCTION("importrange(""https://docs.google.com/spreadsheets/d/1PSz-z1Lv-gZ1WOwdTZ8qAxUigZaO9b52l0_4wx34KIs/edit?gid=2118916648#gid=2118916648&range=B28"",""Summary!B28"")*1000"),35428.3539557584) | L79: =IFERROR(__xludf.DUMMYFUNCTION("IFERROR(googlefinance(D79,""pe""),"""")"),"") | M79: =IFERROR(__xludf.DUMMYFUNCTION("IFERROR(googlefinance(D79,""beta""),"""")"),"")
A80: =A79+1 | B80: =HYPERLINK("https://finance.yahoo.com/quote/"&D80, C80) | C80: UNH | D80: UNH | E80: =IFERROR(__xludf.DUMMYFUNCTION("iferror(googlefinance(D80,""price""),"""")"),293.27) | F80: =IFERROR(__xludf.DUMMYFUNCTION("IFERROR(GOOGLEFINANCE(D80,""price"") / index(GOOGLEFINANCE(D80,""price"", datevalue(today()-365) ) , 2,2) - 1,"""")"),-0.372080077079541) | G80: =IFERROR(__xludf.DUMMYFUNCTION("iferror(googlefinance(D80,""marketcap""),"""")/10^6"),265655.27627) | H80: =IFERROR(__xludf.DUMMYFUNCTION("importrange(""https://docs.google.com/spreadsheets/d/1FjIVEcih8zxcZhJICjNCjhvohqB0dWGFE_KZsagtJAk/edit?gid=2118916648#gid=2118916648&range=B28"",""Summary!B28"")*1000"),263282.372409604) | I80: =(H80-G80)/G80 | L80: =IFERROR(__xludf.DUMMYFUNCTION("IFERROR(googlefinance(D80,""pe""),"""")"),"") | M80: =IFERROR(__xludf.DUMMYFUNCTION("IFERROR(googlefinance(D80,""beta""),"""")"),"")
A81: =A80+1 | B81: =HYPERLINK("https://finance.yahoo.com/quote/"&D81, C81) | C81: DPZ | D81: DPZ | E81: =IFERROR(__xludf.DUMMYFUNCTION("iferror(googlefinance(D81,""price""),"""")"),402.51) | F81: =IFERROR(__xludf.DUMMYFUNCTION("IFERROR(GOOGLEFINANCE(D81,""price"") / index(GOOGLEFINANCE(D81,""price"", datevalue(today()-365) ) , 2,2) - 1,"""")"),-0.168058368814848) | G81: =IFERROR(__xludf.DUMMYFUNCTION("iferror(googlefinance(D81,""marketcap""),"""")/10^6"),13535.964842) | L81: =IFERROR(__xludf.DUMMYFUNCTION("IFERROR(googlefinance(D81,""pe""),"""")"),"") | M81: =IFERROR(__xludf.DUMMYFUNCTION("IFERROR(googlefinance(D81,""beta""),"""")"),"")
A82: =A81+1 | B82: =HYPERLINK("https://finance.yahoo.com/quote/"&D82, C82) | C82: SIRI | D82: SIRI | E82: =IFERROR(__xludf.DUMMYFUNCTION("iferror(googlefinance(D82,""price""),"""")"),21.96) | F82: =IFERROR(__xludf.DUMMYFUNCTION("IFERROR(GOOGLEFINANCE(D82,""price"") / index(GOOGLEFINANCE(D82,""price"", datevalue(today()-365) ) , 2,2) - 1,"""")"),-0.0865224625623959) | G82: =IFERROR(__xludf.DUMMYFUNCTION("iferror(googlefinance(D82,""marketcap""),"""")/10^6"),7351.612577) | H82: =IFERROR(__xludf.DUMMYFUNCTION("importrange(""https://docs.google.com/spreadsheets/d/1PSz-z1Lv-gZ1WOwdTZ8qAxUigZaO9b52l0_4wx34KIs/edit?gid=2118916648#gid=2118916648&range=B28"",""Summary!B28"")*1000"),35428.3539557584) | L82: =IFERROR(__xludf.DUMMYFUNCTION("IFERROR(googlefinance(D82,""pe""),"""")"),"") | M82: =IFERROR(__xludf.DUMMYFUNCTION("IFERROR(googlefinance(D82,""beta""),"""")"),"")
A83: =A82+1 | B83: =HYPERLINK("https://finance.yahoo.com/quote/"&D83, C83) | C83: LAMR | D83: LAMR | E83: =IFERROR(__xludf.DUMMYFUNCTION("iferror(googlefinance(D83,""price""),"""")"),137.74) | F83: =IFERROR(__xludf.DUMMYFUNCTION("IFERROR(GOOGLEFINANCE(D83,""price"") / index(GOOGLEFINANCE(D83,""price"", datevalue(today()-365) ) , 2,2) - 1,"""")"),0.107145727835383) | G83: =IFERROR(__xludf.DUMMYFUNCTION("iferror(googlefinance(D83,""marketcap""),"""")/10^6"),13952.139698) | H83: =IFERROR(__xludf.DUMMYFUNCTION("importrange(""https://docs.google.com/spreadsheets/d/1PSz-z1Lv-gZ1WOwdTZ8qAxUigZaO9b52l0_4wx34KIs/edit?gid=2118916648#gid=2118916648&range=B28"",""Summary!B28"")*1000"),35428.3539557584) | L83: =IFERROR(__xludf.DUMMYFUNCTION("IFERROR(googlefinance(D83,""pe""),"""")"),"") | M83: =IFERROR(__xludf.DUMMYFUNCTION("IFERROR(googlefinance(D83,""beta""),"""")"),"")
A84: =A83+1 | B84: =HYPERLINK("https://finance.yahoo.com/quote/"&D84, C84) | C84: ALLE | D84: ALLE | E84: =IFERROR(__xludf.DUMMYFUNCTION("iferror(googlefinance(D84,""price""),"""")"),161.15) | F84: =IFERROR(__xludf.DUMMYFUNCTION("IFERROR(GOOGLEFINANCE(D84,""price"") / index(GOOGLEFINANCE(D84,""price"", datevalue(today()-365) ) , 2,2) - 1,"""")"),0.27371166613974) | G84: =IFERROR(__xludf.DUMMYFUNCTION("iferror(googlefinance(D84,""marketcap""),"""")/10^6"),13882.346799) | H84: =IFERROR(__xludf.DUMMYFUNCTION("importrange(""https://docs.google.com/spreadsheets/d/1PSz-z1Lv-gZ1WOwdTZ8qAxUigZaO9b52l0_4wx34KIs/edit?gid=2118916648#gid=2118916648&range=B28"",""Summary!B28"")*1000"),35428.3539557584) | L84: =IFERROR(__xludf.DUMMYFUNCTION("IFERROR(googlefinance(D84,""pe""),"""")"),"") | M84: =IFERROR(__xludf.DUMMYFUNCTION("IFERROR(googlefinance(D84,""beta""),"""")"),"")
A85: =A84+1 | B85: =HYPERLINK("https://finance.yahoo.com/quote/"&D85, C85) | C85: CB | D85: CB | E85: =IFERROR(__xludf.DUMMYFUNCTION("iferror(googlefinance(D85,""price""),"""")"),340.86) | F85: =IFERROR(__xludf.DUMMYFUNCTION("IFERROR(GOOGLEFINANCE(D85,""price"") / index(GOOGLEFINANCE(D85,""price"", datevalue(today()-365) ) , 2,2) - 1,"""")"),0.176637094825503) | G85: =IFERROR(__xludf.DUMMYFUNCTION("iferror(googlefinance(D85,""marketcap""),"""")/10^6"),133310.715216) | H85: =IFERROR(__xludf.DUMMYFUNCTION("importrange(""https://docs.google.com/spreadsheets/d/1PSz-z1Lv-gZ1WOwdTZ8qAxUigZaO9b52l0_4wx34KIs/edit?gid=2118916648#gid=2118916648&range=B28"",""Summary!B28"")*1000"),35428.3539557584) | L85: =IFERROR(__xludf.DUMMYFUNCTION("IFERROR(googlefinance(D85,""pe""),"""")"),"") | M85: =IFERROR(__xludf.DUMMYFUNCTION("IFERROR(googlefinance(D85,""beta""),"""")"),"")
A86: =A85+1 | B86: BYD | C86: BYD | D86: 1211 | E86: 97.11 | G86: =IFERROR(__xludf.DUMMYFUNCTION("E86*importrange(""https://docs.google.com/spreadsheets/d/1sj5i_x98T-YjDlenwVw1sMU5c0j62zlaOGR3hVGvzVE/edit?gid=2118916648#gid=2118916648&range=G13"",""Summary!G13"")*1000"),885643.199999999) | H86: =IFERROR(__xludf.DUMMYFUNCTION("importrange(""https://docs.google.com/spreadsheets/d/1sj5i_x98T-YjDlenwVw1sMU5c0j62zlaOGR3hVGvzVE/edit?gid=2118916648#gid=2118916648&range=B28"",""Summary!B28"")*1000"),722603.070173736) | I86: =(H86-G86)/G86 | J86: =IFERROR(__xludf.DUMMYFUNCTION("importrange(""https://docs.google.com/spreadsheets/d/1Cq6JV7ifnjjUQxYb_qlclo8JPOj4y_cw0UWStLqeSrk/edit?gid=2118916648#gid=2118916648&range=G68"",""Summary!G6"")"),0.228852459016393) | L86: =IFERROR(__xludf.DUMMYFUNCTION("IFERROR(googlefinance(D86,""pe""),"""")"),"") | M86: =IFERROR(__xludf.DUMMYFUNCTION("IFERROR(googlefinance(D86,""beta""),"""")"),"")
A87: =A86+1 | B87: XIAOMI | C87: XIAOMI | D87: 1810 | E87: 38.58 | F87: =IFERROR(__xludf.DUMMYFUNCTION("IFERROR(GOOGLEFINANCE(D87,""price"") / index(GOOGLEFINANCE(D87,""price"", datevalue(today()-365) ) , 2,2) - 1,"""")"),"") | G87: =IFERROR(__xludf.DUMMYFUNCTION("E87*importrange(""https://docs.google.com/spreadsheets/d/1Cq6JV7ifnjjUQxYb_qlclo8JPOj4y_cw0UWStLqeSrk/edit?gid=2118916648#gid=2118916648&range=G13"",""Summary!G13"")*1000"),1005009) | H87: =IFERROR(__xludf.DUMMYFUNCTION("importrange(""https://docs.google.com/spreadsheets/d/1Cq6JV7ifnjjUQxYb_qlclo8JPOj4y_cw0UWStLqeSrk/edit?gid=2118916648#gid=2118916648&range=B28"",""Summary!B28"")*1000"),1365415.80785986) | I87: =(H87-G87)/G87 | J87: =IFERROR(__xludf.DUMMYFUNCTION("importrange(""https://docs.google.com/spreadsheets/d/1sj5i_x98T-YjDlenwVw1sMU5c0j62zlaOGR3hVGvzVE/edit?gid=2118916648#gid=2118916648&range=G68"",""Summary!G6"")"),0.0810356941559796) | L87: =IFERROR(__xludf.DUMMYFUNCTION("IFERROR(googlefinance(D87,""pe""),"""")"),"") | M87: =IFERROR(__xludf.DUMMYFUNCTION("IFERROR(googlefinance(D87,""beta""),"""")"),"")

Sheet Venture
A1: Decision | B1: Company | C1: Round | D1: Cap, M$ | E1: ARR, M$ | F1: Growth %/month | G1: Lead | H1: Deal link | I1: P/ARR | J1: ARR/raised
A2: No | B2: Humand | C2: A+ | D2: 120 | E2: 6.25 | F2: =(6.25-5)/5/3 | G2: Pioner+angels | H2: https://venture.angellist.com/v/andrey-a-semenov/i/invest/durovc-humand-series-a-ext | I2: =D2/E2
A3: No | B3: Bios | C3: A | D3: 51 | E3: 3.1 | F3: =(4.6-2.8)/12 | G3: DSN+Ester Dyson | H3: https://venture.angellist.com/v/andrey-a-semenov/i/invest/daniel-gould-bioz-series-a | I3: =D3/E3 | J3: =4.6/20
A4: Yes | B4: Eventeny | C4: Seed+ | D4: 43 | E4: 6 | F4: =(6-4.5)/12 | G4: Zach Coelius | H4: https://venture.angellist.com/v/andrey-a-semenov/i/invest/zach-coelius-eventeny-seed-ext-prorata | I4: =D4/E4 | J4: =E4/3
A5: No | B5: InchFab | C5: Seed | D5: 21 | E5: 0.76 | F5: =260/1200 | G5: Tim Draper | H5: https://venture.angellist.com/v/andrey-a-semenov/i/invest/rv-inchfab-seed | I5: =D5/E5
A6: Yes | B6: Anello Photonics | C6: A+ | D6: 110 | E6: 8.2 | F6: =(8.2-3)/12 | G6: Lockheed Martin | H6: https://venture.angellist.com/v/andrey-a-semenov/i/invest/mana-ventures-anello-photonics-seed | I6: =D6/E6 | J6: =E6/28
B7: Ale's age | C7: Growth
A8: 735 | B8: 5 | C8: 0.096
A9: =A8*(1+C8) | B9: 6 | C9: 0.096
A10: =A9*(1+C9) | B10: 7 | C10: 0.096
A11: =A10*(1+C10) | B11: 8 | C11: 0.096
A12: =A11*(1+C11) | B12: 9 | C12: 0.096
A13: =A12*(1+C12) | B13: 10 | C13: 0.096
A14: =A13*(1+C13) | B14: 11 | C14: 0.096
A15: =A14*(1+C14) | B15: 12 | C15: 0.096
A16: =A15*(1+C15) | B16: 13 | C16: 0.096
A17: =A16*(1+C16) | B17: 14 | C17: 0.096
A18: =A17*(1+C17) | B18: 15 | C18: 0.096
A19: =A18*(1+C18) | B19: 16

Sheet COVID
A1: COVID economic downturm
F2: 33.58 | G2: 107.71 | H2: =F2*G2
F3: 33.52 | G3: 99.6 | H3: =F3*G3
F4: 33.49 | G4: =(H2-H3)/F4 | H4: =28.06-G4
F6: =(1+((2923-2880)/2880)*1.2)*303.74
B28: Pershing
A29: Blackstone | B29: =25/0.549 | C29: $/share
A30: PK | B30: =5.4/0.678 | C30: $/share
A32: 721 | B32: Moscow | C32: =IFERROR(__xludf.DUMMYFUNCTION("AI(""What is the country"",B32)"),"=AI(""What is the country"",B32)")
A33: 1158 | B33: New York | C33: =IFERROR(__xludf.DUMMYFUNCTION("AI(""What is the country"",B33)"),"=AI(""What is the country"",B33)")
A34: 587
A35: 401
A36: 930
A37: =SUM(A32:A36)

Sheet NVScriptsProperties
A1: autocratn | B1: autocratp
A2: dataSheetName | B2: "Все компании"
A3: v | B3: "5.1"
A4: dataSheetId | B4: "0.0"
A5: updateTime | B5: "1.770887443575E12"
A6: vp | B6: "5.1"
A7: ssId | B7: "14Zw71JCwsHTLVyzE-P3vUVB7yMzE_sIAHjSgD3W8wsE"

Sheet S&P 500
C2: =HYPERLINK("https://theassets.ru","The Assets")
C3: S&P 500 companies
B6: Ticker | C6: Company | D6: Industry | E6: Debt / Equity | F6: Current Ratio | G6: Quick Ratio | H6: Gross Margin | I6: Operating Margin | J6: Net Margin | K6: FCF as a % of Sales | L6: FCF as a % of Net Income
B7: MS | C7: Morgan Stanley | D7: Capital Markets | E7: 2.4 | F7: - | G7: - | H7: 0 | I7: 0.29 | J7: 0.232 | K7: 0.993 | L7: 4.278
B8: ETFC | C8: E*TRADE Financial | D8: Capital Markets | E8: 0.2 | F8: - | G8: - | H8: 0 | I8: 0.447 | J8: 0.33 | K8: 0.944 | L8: 2.857
B9: SCHW | C9: Charles Schwab | D9: Capital Markets | E9: 0.3 | F9: - | G9: - | H9: 0 | I9: 0.452 | J9: 0.345 | K9: 0.824 | L9: 2.386
B10: O | C10: Realty Income | D10: REIT - Retail | E10: 0.8 | F10: 2 | G10: 2 | H10: 0.941 | I10: 0.498 | J10: 0.292 | K10: 0.718 | L10: 2.455
B11: PLD | C11: Prologis | D11: REIT - Industrial | E11: 0.6 | F11: 2.6 | G11: 2.6 | H11: 0.724 | I11: 0.298 | J11: 0.473 | K11: 0.68 | L11: 1.44
B12: BAC | C12: Bank of America | D12: Banks - Diversified | E12: 1 | F12: - | G12: - | H12: 0 | I12: 0.398 | J12: 0.3 | K12: 0.677 | L12: 2.254
B13: VRSN | C13: VeriSign | D13: Software - Infrastructure | E13: - | F13: 1.3 | G13: 1.3 | H13: 0.854 | I13: 0.655 | J13: 0.497 | K13: 0.579 | L13: 1.166
B14: COF | C14: Capital One Financial | D14: Credit Services | E14: 1 | F14: - | G14: - | H14: 0 | I14: 0.485 | J14: 0.199 | K14: 0.565 | L14: 2.835
B15: ESS | C15: Essex Property Trust | D15: REIT - Residential | E15: 1 | F15: 0.8 | G15: 0.8 | H15: 0.705 | I15: 0.337 | J15: 0.301 | K15: 0.559 | L15: 1.859
B16: REG | C16: Regency Centers | D16: REIT - Retail | E16: 0.7 | F16: 0.8 | G16: 0.8 | H16: 0.73 | I16: 0.327 | J16: 0.21 | K16: 0.549 | L16: 2.614
B17: V | C17: Visa | D17: Credit Services | E17: 0.5 | F17: 1.3 | G17: 1.3 | H17: 0.815 | I17: 0.667 | J17: 0.526 | K17: 0.537 | L17: 1.02
B18: EXR | C18: Extra Space Storage | D18: REIT - Industrial | E18: 2.1 | F18: 0.5 | G18: 0.5 | H18: 0.721 | I18: 0.484 | J18: 0.321 | K18: 0.535 | L18: 1.666
B19: GS | C19: Goldman Sachs Group | D19: Capital Markets | E19: 3.1 | F19: - | G19: - | H19: 0 | I19: 0.35 | J19: 0.254 | K19: 0.531 | L19: 2.091
B20: SYF | C20: Synchrony Finl | D20: Credit Services | E20: 1.3 | F20: - | G20: - | H20: 0 | I20: 0.753 | J20: 0.218 | K20: 0.524 | L20: 2.404
B21: DFS | C21: Discover Financial | D21: Credit Services | E21: 2.2 | F21: - | G21: - | H21: 0 | I21: 0.625 | J21: 0.258 | K21: 0.513 | L21: 1.987
B22: SPG | C22: Simon Property Group | D22: REIT - Retail | E22: 9.8 | F22: 0.5 | G22: 0.5 | H22: 0.823 | I22: 0.506 | J22: 0.365 | K22: 0.51 | L22: 1.398
B23: AVB | C23: AvalonBay Communities | D23: REIT - Residential | E23: 0.7 | F23: 0.5 | G23: 0.5 | H23: 0.67 | I23: 0.359 | J23: 0.339 | K23: 0.507 | L23: 1.498
B24: PSA | C24: Public Storage | D24: REIT - Industrial | E24: 0.2 | F24: 1.1 | G24: 1.1 | H24: 0.72 | I24: 0.515 | J24: 0.534 | K24: 0.507 | L24: 0.948
B25: KIM | C25: Kimco Realty | D25: REIT - Retail | E25: 1.1 | F25: 1.2 | G25: 1.2 | H25: 0.719 | I25: 0.386 | J25: 0.354 | K25: 0.503 | L25: 1.423
B26: CME | C26: CME Group | D26: Financial Data & Stock Exchanges | E26: 0.1 | F26: 1 | G26: 1 | H26: 0.738 | I26: 0.532 | J26: 0.435 | K26: 0.498 | L26: 1.146
B27: MAA | C27: Mid-America Apartment | D27: REIT - Residential | E27: 0.7 | F27: 0.2 | G27: 0.2 | H27: 0.627 | I27: 0.262 | J27: 0.216 | K27: 0.477 | L27: 2.207
B28: STT | C28: State Street | D28: Asset Management | E28: 0.6 | F28: - | G28: - | H28: 0 | I28: 0.269 | J28: 0.211 | K28: 0.475 | L28: 2.248
B29: DLR | C29: Digital Realty Trust | D29: REIT - Office | E29: 1.1 | F29: 0.5 | G29: 0.5 | H29: 0.628 | I29: 0.196 | J29: 0.181 | K29: 0.472 | L29: 2.608
B30: EQR | C30: Equity Residential | D30: REIT - Residential | E30: 0.9 | F30: 0.3 | G30: 0.3 | H30: 0.664 | I30: 0.337 | J30: 0.362 | K30: 0.471 | L30: 1.303
B31: KEY | C31: KeyCorp | D31: Banks - Regional | E31: 0.8 | F31: - | G31: - | H31: 0 | I31: 0.399 | J31: 0.278 | K31: 0.457 | L31: 1.646
B32: MKTX | C32: MarketAxess Holdings | D32: Capital Markets | E32: 0.1 | F32: 4.4 | G32: 4.3 | H32: 0 | I32: 0.49 | J32: 0.401 | K32: 0.454 | L32: 1.134
B33: ARE | C33: Alexandria Real Estate | D33: REIT - Office | E33: 0.8 | F33: 0.4 | G33: 0.4 | H33: 0.709 | I33: 0.282 | J33: 0.236 | K33: 0.447 | L33: 1.896
B34: BIIB | C34: Biogen | D34: Drug Manufacturers - General | E34: 0.5 | F34: 1.7 | G34: 1.6 | H34: 0.864 | I34: 0.49 | J34: 0.41 | K34: 0.447 | L34: 1.09
B35: MA | C35: Mastercard | D35: Credit Services | E35: 1.5 | F35: 1.4 | G35: 1.4 | H35: 0 | I35: 0.574 | J35: 0.481 | K35: 0.443 | L35: 0.921
B36: RF | C36: Regions Financial | D36: Banks - Regional | E36: 0.6 | F36: - | G36: - | H36: 0 | I36: 0.415 | J36: 0.271 | K36: 0.439 | L36: 1.618
B37: AGN | C37: Allergan | D37: Drug Manufacturers - General | E37: 0.4 | F37: 1 | G37: 0.9 | H37: 0.845 | I37: -0.001 | J37: -0.324 | K37: 0.424 | L37: -
B38: PEAK | C38: Healthpeak Properties | D38: REIT - Healthcare Facilities | E38: 1.1 | F38: 1.9 | G38: 1.9 | H38: 0.559 | I38: 0.178 | J38: 0.022 | K38: 0.424 | L38: 19.592
B39: MSCI | C39: MSCI | D39: Financial Data & Stock Exchanges | E39: - | F39: 2.3 | G39: 2.3 | H39: 0.811 | I39: 0.486 | J39: 0.361 | K39: 0.423 | L39: 1.174
B40: ADSK | C40: Autodesk | D40: Software - Application | E40: - | F40: 0.8 | G40: 0.8 | H40: 0.901 | I40: 0.105 | J40: 0.066 | K40: 0.417 | L40: 6.294
B41: AVGO | C41: Broadcom | D41: Semiconductors | E41: 1.8 | F41: 1.6 | G41: 1.4 | H41: 0.553 | I41: 0.169 | J41: 0.116 | K41: 0.416 | L41: 3.58
B42: PNC | C42: PNC Financial Services Gr | D42: Banks - Regional | E42: 1.1 | F42: - | G42: - | H42: 0 | I42: 0.407 | J42: 0.301 | K42: 0.414 | L42: 1.374
B43: FLT | C43: Fleetcor Technologies | D43: Information Technology Services | E43: 1.4 | F43: 1 | G43: 1 | H43: 0.8 | I43: 0.465 | J43: 0.339 | K43: 0.41 | L43: 1.211
B44: SBAC | C44: SBA Communications | D44: REIT - Specialty | E44: - | F44: 0.3 | G44: 0.3 | H44: 0.755 | I44: 0.314 | J44: 0.073 | K44: 0.405 | L44: 5.537
B45: TXN | C45: Texas Instruments | D45: Semiconductors | E45: 0.7 | F45: 4.1 | G45: 3.2 | H45: 0.637 | I45: 0.416 | J45: 0.349 | K45: 0.405 | L45: 1.161
B46: BXP | C46: Boston Properties | D46: REIT - Office | E46: 2.2 | F46: 3.1 | G46: 3.1 | H46: 0.63 | I46: 0.354 | J46: 0.177 | K46: 0.4 | L46: 2.267
B47: SPGI | C47: S&P Global | D47: Financial Data & Stock Exchanges | E47: 9.8 | F47: 1.5 | G47: 1.5 | H47: 0.733 | I47: 0.475 | J47: 0.318 | K47: 0.4 | L47: 1.258
B48: ANET | C48: Arista Networks | D48: Computer Hardware | E48: 0 | F48: 5.8 | G48: 5.4 | H48: 0.641 | I48: 0.334 | J48: 0.357 | K48: 0.394 | L48: 1.105
B49: NVDA | C49: NVIDIA | D49: Semiconductors | E49: 0.2 | F49: 7.7 | G49: 7.1 | H49: 0.62 | I49: 0.261 | J49: 0.257 | K49: 0.392 | L49: 1.528
B50: UDR | C50: UDR | D50: REIT - Residential | E50: 1.5 | F50: 0.3 | G50: 0.3 | H50: 0.685 | I50: 0.188 | J50: 0.161 | K50: 0.388 | L50: 2.403
B51: ABBV | C51: AbbVie | D51: Drug Manufacturers - General | E51: - | F51: 3.2 | G51: 3.1 | H51: 0.776 | I51: 0.402 | J51: 0.236 | K51: 0.384 | L51: 1.626
B52: ALXN | C52: Alexion Pharmaceuticals | D52: Biotechnology | E52: 0.2 | F52: 4.3 | G52: 3.7 | H52: 0.921 | I52: 0.429 | J52: 0.481 | K52: 0.384 | L52: 0.798
B53: MO | C53: Altria Group | D53: Tobacco | E53: 4.5 | F53: 0.6 | G53: 0.3 | H53: 0.642 | I53: 0.53 | J53: -0.068 | K53: 0.382 | L53: -
B54: AXP | C54: American Express | D54: Credit Services | E54: 2.8 | F54: - | G54: - | H54: 0 | I54: 0.389 | J54: 0.219 | K54: 0.38 | L54: 1.738
B55: NTRS | C55: Northern Trust | D55: Asset Management | E55: 1 | F55: - | G55: - | H55: 0 | I55: 0.364 | J55: 0.282 | K55: 0.378 | L55: 1.343
B56: GILD | C56: Gilead Sciences | D56: Drug Manufacturers - General | E56: 1.1 | F56: 3.1 | G56: 3 | H56: 0.792 | I56: 0.189 | J56: 0.239 | K56: 0.372 | L56: 1.56
B57: ADBE | C57: Adobe | D57: Software - Infrastructure | E57: 0.5 | F57: 1.2 | G57: 1.2 | H57: 0.852 | I57: 0.301 | J57: 0.277 | K57: 0.37 | L57: 1.334
B58: AMGN | C58: Amgen | D58: Drug Manufacturers - General | E58: 3.1 | F58: 1.4 | G58: 1.2 | H58: 0.814 | I58: 0.414 | J58: 0.335 | K58: 0.366 | L58: 1.091
B59: AMT | C59: American Tower | D59: REIT - Specialty | E59: 6.1 | F59: 0.5 | G59: 0.5 | H59: 0.708 | I59: 0.355 | J59: 0.249 | K59: 0.365 | L59: 1.463
B60: ICE | C60: Intercontinental Exchange | D60: Financial Data & Stock Exchanges | E60: 0.5 | F60: 1 | G60: 1 | H60: 0.795 | I60: 0.409 | J60: 0.295 | K60: 0.359 | L60: 1.218
B61: VRTX | C61: Vertex Pharmaceuticals | D61: Biotechnology | E61: 0.1 | F61: 3.6 | G61: 3.4 | H61: 0.868 | I61: 0.288 | J61: 0.282 | K61: 0.359 | L61: 1.271
B62: MTB | C62: M&T Bank | D62: Banks - Regional | E62: 0.4 | F62: - | G62: - | H62: 0 | I62: 0.44 | J62: 0.312 | K62: 0.353 | L62: 1.134
B63: VNO | C63: Vornado Realty | D63: REIT - Office | E63: 1.2 | F63: 3.4 | G63: 3.4 | H63: 0.523 | I63: 0.217 | J63: 1.651 | K63: 0.347 | L63: 0.21
B64: ADI | C64: Analog Devices | D64: Semiconductors | E64: 0.5 | F64: 1.1 | G64: 0.8 | H64: 0.664 | I64: 0.28 | J64: 0.21 | K64: 0.346 | L64: 1.644
B65: MXIM | C65: Maxim Integrated Products | D65: Semiconductors | E65: 0.6 | F65: 6.6 | G65: 6 | H65: 0.642 | I65: 0.304 | J65: 0.361 | K65: 0.338 | L65: 0.936
B66: SIVB | C66: SVB Financial | D66: Banks - Regional | E66: 0.1 | F66: - | G66: - | H66: 0 | I66: 0.529 | J66: 0.349 | K66: 0.336 | L66: 0.964
B67: MCO | C67: Moody's | D67: Financial Data & Stock Exchanges | E67: 10.1 | F67: 1.9 | G67: 1.9 | H67: 0.713 | I67: 0.43 | J67: 0.294 | K67: 0.333 | L67: 1.132
B68: FTNT | C68: Fortinet | D68: Software - Infrastructure | E68: 0 | F68: 1.9 | G68: 1.8 | H68: 0.765 | I68: 0.16 | J68: 0.152 | K68: 0.331 | L68: 2.184
B69: PFG | C69: Principal Financial Group | D69: Insurance - Diversified | E69: 0.3 | F69: - | G69: - | H69: 0 | I69: 0 | J69: 0.086 | K69: 0.331 | L69: 3.861
B70: EA | C70: Electronic Arts | D70: Electronic Gaming & Multimedia | E70: 0.2 | F70: 2.8 | G70: 2.8 | H70: 0.744 | I70: 0.234 | J70: 0.529 | K70: 0.326 | L70: 0.616
B71: COG | C71: Cabot Oil & Gas | D71: Oil & Gas E&P | E71: 0.6 | F71: 1.7 | G71: 1.5 | H71: 0.487 | I71: 0.423 | J71: 0.329 | K71: 0.314 | L71: 0.956
B72: HBAN | C72: Huntington Bancshares | D72: Banks - Regional | E72: 1 | F72: - | G72: - | H72: 0 | I72: 0.417 | J72: 0.302 | K72: 0.313 | L72: 1.037
B73: ORCL | C73: Oracle | D73: Software - Infrastructure | E73: 3.6 | F73: 2.1 | G73: 2.1 | H73: 0.798 | I73: 0.358 | J73: 0.271 | K73: 0.312 | L73: 1.153
B74: PM | C74: Philip Morris Intl | D74: Tobacco | E74: - | F74: 1.1 | G74: 0.6 | H74: 0.647 | I74: 0.351 | J74: 0.242 | K74: 0.312 | L74: 1.291
B75: XLNX | C75: Xilinx | D75: Semiconductors | E75: 0.5 | F75: 6.1 | G75: 5.4 | H75: 0.663 | I75: 0.267 | J75: 0.27 | K75: 0.312 | L75: 1.153
B76: DRE | C76: Duke Realty | D76: REIT - Industrial | E76: 0.6 | F76: 4.2 | G76: 4.2 | H76: 0.676 | I76: 0.259 | J76: 0.444 | K76: 0.306 | L76: 0.689
B77: ABMD | C77: Abiomed | D77: Medical Devices | E77: 0 | F77: 5 | G77: 4.2 | H77: 0.826 | I77: 0.305 | J77: 0.291 | K77: 0.305 | L77: 1.05
B78: SLG | C78: SL Green Realty | D78: REIT - Office | E78: 1 | F78: 3.7 | G78: 3.7 | H78: 0.63 | I78: 0.323 | J78: 0.228 | K78: 0.305 | L78: 1.339
B79: PRU | C79: Prudential Financial | D79: Insurance - Life | E79: 0.4 | F79: - | G79: - | H79: 0 | I79: 0 | J79: 0.065 | K79: 0.304 | L79: 4.702
B80: CMA | C80: Comerica | D80: Banks - Regional | E80: 1 | F80: - | G80: - | H80: 0 | I80: 0.479 | J80: 0.358 | K80: 0.303 | L80: 0.848
B81: MSFT | C81: Microsoft | D81: Software - Infrastructure | E81: 0.7 | F81: 2.8 | G81: 2.8 | H81: 0.677 | I81: 0.368 | J81: 0.331 | K81: 0.302 | L81: 0.913
B82: BKNG | C82: Booking Holdings | D82: Travel Services | E82: 1.5 | F82: 1.8 | G82: 1.8 | H82: 0 | I82: 0.356 | J82: 0.323 | K82: 0.301 | L82: 0.93
B83: ANSS | C83: Ansys | D83: Software - Application | E83: 0.2 | F83: 2.2 | G83: 2.2 | H83: 0.89 | I83: 0.34 | J83: 0.298 | K83: 0.299 | L83: 1.003
B84: FB | C84: Facebook | D84: Internet Content & Information | E84: 0.1 | F84: 4.4 | G84: 4.4 | H84: 0.819 | I84: 0.34 | J84: 0.262 | K84: 0.299 | L84: 1.141
B85: INTU | C85: Intuit | D85: Software - Application | E85: 0.2 | F85: 1.7 | G85: 1.7 | H85: 0.821 | I85: 0.264 | J85: 0.226 | K85: 0.299 | L85: 1.325
B86: WELL | C86: Welltower | D86: REIT - Healthcare Facilities | E86: 1 | F86: 1.9 | G86: 1.9 | H86: 0.364 | I86: 0.134 | J86: 0.242 | K86: 0.299 | L86: 1.234
B87: INCY | C87: Incyte | D87: Biotechnology | E87: 0 | F87: 4.8 | G87: 4.8 | H87: 0.947 | I87: 0.196 | J87: 0.207 | K87: 0.293 | L87: 1.416
B88: GL | C88: Globe Life | D88: Insurance - Life | E88: 0.2 | F88: - | G88: - | H88: 0 | I88: 0 | J88: 0.168 | K88: 0.291 | L88: 1.732
B89: CSCO | C89: Cisco Systems | D89: Communication Equipment | E89: 0.5 | F89: 1.8 | G89: 1.8 | H89: 0.64 | I89: 0.28 | J89: 0.214 | K89: 0.288 | L89: 1.342
B90: QCOM | C90: Qualcomm | D90: Semiconductors | E90: 3.5 | F90: 1.8 | G90: 1.6 | H90: 0.653 | I90: 0.327 | J90: 0.174 | K90: 0.288 | L90: 1.659
B91: TTWO | C91: Take-Two Interactive | D91: Electronic Gaming & Multimedia | E91: 0.1 | F91: 1.6 | G91: 1.6 | H91: 0.51 | I91: 0.127 | J91: 0.118 | K91: 0.287 | L91: 2.429
B92: PAYX | C92: Paychex | D92: Staffing & Employment Services | E92: 0.4 | F92: 1.2 | G92: 1.2 | H92: 0.681 | I92: 0.359 | J92: 0.27 | K92: 0.286 | L92: 1.06
B93: MCHP | C93: Microchip Technology | D93: Semiconductors | E93: 1.7 | F93: 0.9 | G93: 0.6 | H93: 0.616 | I93: 0.147 | J93: 0.122 | K93: 0.281 | L93: 2.295
B94: VRSK | C94: Verisk Analytics | D94: Consulting Services | E94: 1.5 | F94: 0.5 | G94: 0.5 | H94: 0.625 | I94: 0.267 | J94: 0.172 | K94: 0.281 | L94: 1.634
B95: CDNS | C95: Cadence Design Systems | D95: Software - Application | E95: 0.2 | F95: 1.7 | G95: 1.7 | H95: 0.886 | I95: 0.214 | J95: 0.426 | K95: 0.28 | L95: 0.658
B96: DISCA | C96: Discovery | D96: Entertainment | E96: 1.6 | F96: 1.6 | G96: 1.6 | H96: 0.657 | I96: 0.286 | J96: 0.186 | K96: 0.28 | L96: 1.505
B97: DISCK | C97: Discovery | D97: Entertainment | E97: 1.6 | F97: 1.6 | G97: 1.6 | H97: 0.657 | I97: 0.286 | J97: 0.186 | K97: 0.28 | L97: 1.505
B98: BMY | C98: Bristol-Myers Squibb | D98: Drug Manufacturers - General | E98: 0.9 | F98: 1.6 | G98: 1.4 | H98: 0.691 | I98: 0.226 | J98: 0.13 | K98: 0.277 | L98: 2.134
B99: MCD | C99: McDonald's | D99: Restaurants | E99: - | F99: 1 | G99: 1 | H99: 0.528 | I99: 0.422 | J99: 0.286 | K99: 0.272 | L99: 0.949
B100: CSX | C100: CSX | D100: Railroads | E100: 1.4 | F100: 1.5 | G100: 1.4 | H100: 0.408 | I100: 0.408 | J100: 0.279 | K100: 0.267 | L100: 0.958
B101: ATVI | C101: Activision Blizzard | D101: Electronic Gaming & Multimedia | E101: 0.2 | F101: 2.5 | G101: 2.5 | H101: 0.677 | I101: 0.267 | J101: 0.232 | K101: 0.265 | L101: 1.143
B102: ISRG | C102: Intuitive Surgical | D102: Medical Instruments & Supplies | E102: 0 | F102: 4.5 | G102: 4 | H102: 0.695 | I102: 0.307 | J102: 0.308 | K102: 0.262 | L102: 0.852
B103: ROP | C103: Roper Technologies | D103: Specialty Industrial Machinery | E103: 0.6 | F103: 0.8 | G103: 0.8 | H103: 0.639 | I103: 0.279 | J103: 0.33 | K103: 0.261 | L103: 0.792
...

Sheet Errors
A1: Ticker | B1: Error | C1: Timestamp
A2: HOLX | B2: Empty info after 3 attempts | C2: 2026-10-20 15:02:44
A3: SEE | B3: Empty info after 3 attempts | C3: 2026-10-20 15:02:44
A4: BK | B4: Empty info after 3 attempts | C4: 2026-10-20 15:02:44
A5: CTRA | B5: Empty info after 3 attempts | C5: 2026-10-20 15:02:44
